Workbook
Name CorDaCélula: 'ABERTURA DE REQUISIÇÃO'!$O$12

Sheet ABERTURA DE REQUISIÇÃO
A1: EMPRESA | B1: FILIAL | C1: LOJA | D1: CNPJ | E1: COORDENADOR | F1: PROJETO | G1: SERVIÇO | H1: NOTA | I1: FORNECEDOR | J1: ORDEM | K1: REQUISIÇÃO | L1: VALOR | M1: STATUS | N1: PEDIDO | O1: TICKET | P1: STATUS PGTO | Q1: DATA PGTO | R1: MIRO | S1: PENDENTE | T1: data criação linha
B2: 56 | C2: FOR191-15Novembro-CE | D2: 06.626.253/0056-25 | E2: Jordana | F2: LOJAS NOVAS | G2: UTILITES LOJAS NOVAS | H2: ORÇ | I2: ALVO-K | J2: 603700 | K2: 10020172 | L2: 1800 | M2: ENVIADO | T2: 45677
B3: 56 | C3: FOR191-15Novembro-CE | D3: 06.626.253/0056-25 | E3: Jordana | F3: LOJAS NOVAS | G3: UTILITES LOJAS NOVAS | H3: ORÇ | I3: ALVO-K | J3: 603700 | K3: 10020172 | L3: 4015 | M3: ENVIADO | T3: 45677
B4: 513 | C4: CGD23-TrêsBarras-MS | D4: 06.626.253/0513-09 | E4: ANDRE | F4: LOJAS NOVAS | G4: UTILITES LOJAS NOVAS | H4: 5431 | I4: ALVO-K | J4: 603320 | K4: 10020213 | L4: 2000 | M4: ENVIADO | T4: 45677
B5: 513 | C5: CGD23-TrêsBarras-MS | D5: 06.626.253/0513-09 | E5: ANDRE | F5: LOJAS NOVAS | G5: UTILITES LOJAS NOVAS | H5: 5432 | I5: ALVO-K | J5: 603320 | K5: 10020214 | L5: 18800 | M5: ENVIADO | T5: 45677
B6: 1372 | C6: REC74-LuizNunes-PE | D6: 06.626.253/1372-97 | E6: Jordana | F6: LOJAS NOVAS | G6: UTILITES LOJAS NOVAS | H6: 5445 | I6: ALVO-K | J6: 603125 | K6: 10020215 | L6: 1800 | M6: ENVIADO | T6: 45677
B7: 1372 | C7: REC74-LuizNunes-PE | D7: 06.626.253/1372-97 | E7: Jordana | F7: LOJAS NOVAS | G7: UTILITES LOJAS NOVAS | H7: 5446 | I7: ALVO-K | J7: 603125 | K7: 10020216 | L7: 4015 | M7: ENVIADO | T7: 45677
B8: 1372 | C8: REC74-LuizNunes-PE | D8: 06.626.253/1372-97 | E8: Jordana | F8: LOJAS NOVAS | G8: UTILITES LOJAS NOVAS | H8: 5447 | I8: ALVO-K | J8: 603125 | K8: 10020217 | L8: 10350 | M8: ENVIADO | T8: 45677
B9: 1432 | C9: REC72-AntFalcao-PE | D9: 06.626.253/1432-62 | E9: Jordana | F9: LOJAS NOVAS | G9: UTILITES LOJAS NOVAS | H9: 5442 | I9: ALVO-K | J9: 603254 | K9: 10020218 | L9: 1800 | M9: ENVIADO | T9: 45677
B10: 1432 | C10: REC72-AntFalcao-PE | D10: 06.626.253/1432-62 | E10: Jordana | F10: LOJAS NOVAS | G10: UTILITES LOJAS NOVAS | H10: 5443 | I10: ALVO-K | J10: 603254 | K10: 10020219 | L10: 4015 | M10: ENVIADO | T10: 45677
B11: 1432 | C11: REC72-AntFalcao-PE | D11: 06.626.253/1432-62 | E11: Jordana | F11: LOJAS NOVAS | G11: UTILITES LOJAS NOVAS | H11: 5444 | I11: ALVO-K | J11: 603254 | K11: 10020230 | L11: 12500 | M11: ENVIADO | T11: 45677
B12: 1440 | C12: OEI01-Oeiras-PI | D12: 1440 | E12: ANDRE | F12: LOJAS NOVAS | G12: UTILITES LOJAS NOVAS | H12: 5435 | I12: ALVO-K | J12: 602883 | K12: 10020231 | L12: 1800 | M12: ENVIADO | T12: 45677
B13: 1440 | C13: OEI01-Oeiras-PI | D13: 1440 | E13: ANDRE | F13: LOJAS NOVAS | G13: UTILITES LOJAS NOVAS | H13: 5436 | I13: ALVO-K | J13: 602883 | K13: 10020232 | L13: 4015 | M13: ENVIADO | T13: 45677
B14: 1440 | C14: OEI01-Oeiras-PI | D14: 1440 | E14: ANDRE | F14: LOJAS NOVAS | G14: UTILITES LOJAS NOVAS | H14: 5437 | I14: ALVO-K | J14: 602883 | K14: 10020233 | L14: 2000 | M14: ENVIADO | T14: 45677
B15: 1440 | C15: OEI01-Oeiras-PI | D15: 1440 | E15: ANDRE | F15: LOJAS NOVAS | G15: UTILITES LOJAS NOVAS | H15: 5438 | I15: ALVO-K | J15: 602883 | K15: 10020234 | L15: 12500 | M15: ENVIADO | T15: 45677
B16: 1455 | C16: VAR06-JoaoPonce-MT | D16: 06.626.253/1455-59 | E16: Jordana | F16: LOJAS NOVAS | G16: UTILITES LOJAS NOVAS | H16: 5448 | I16: ALVO-K | J16: 603908 | K16: 10020235 | L16: 1800 | M16: ENVIADO | T16: 45677
B17: 1455 | C17: VAR06-JoaoPonce-MT | D17: 06.626.253/1455-59 | E17: Jordana | F17: LOJAS NOVAS | G17: UTILITES LOJAS NOVAS | H17: 5449 | I17: ALVO-K | J17: 603908 | K17: 10020236 | L17: 4015 | M17: ENVIADO | T17: 45677
B18: 1455 | C18: VAR06-JoaoPonce-MT | D18: 06.626.253/1455-59 | E18: Jordana | F18: LOJAS NOVAS | G18: UTILITES LOJAS NOVAS | H18: 5450 | I18: ALVO-K | J18: 603908 | K18: 10020237 | L18: 2000 | M18: ENVIADO | T18: 45677
B19: 1455 | C19: VAR06-JoaoPonce-MT | D19: 06.626.253/1455-59 | E19: Jordana | F19: LOJAS NOVAS | G19: UTILITES LOJAS NOVAS | H19: 5451 | I19: ALVO-K | J19: 603908 | K19: 10020238 | L19: 1800 | M19: ENVIADO | T19: 45677
B20: 1461 | C20: PRB03-Liberdade-PA | D20: 1461 | E20: Henrique | F20: LOJAS NOVAS | G20: UTILITES LOJAS NOVAS | H20: 5439 | I20: ALVO-K | J20: 603682 | K20: 10020239 | L20: 1800 | M20: ENVIADO | T20: 45677
B21: 1461 | C21: PRB03-Liberdade-PA | D21: 1461 | E21: Henrique | F21: LOJAS NOVAS | G21: UTILITES LOJAS NOVAS | H21: 5440 | I21: ALVO-K | J21: 603682 | K21: 10020240 | L21: 4015 | M21: ENVIADO | T21: 45677
B22: 1461 | C22: PRB03-Liberdade-PA | D22: 1461 | E22: Henrique | F22: LOJAS NOVAS | G22: UTILITES LOJAS NOVAS | H22: 5441 | I22: ALVO-K | J22: 603682 | K22: 10020241 | L22: 12500 | M22: ENVIADO | T22: 45677
B23: 1464 | C23: JPE50-FcoLeocadio-PB | D23: 1464 | E23: ANDRE | F23: LOJAS NOVAS | G23: UTILITES LOJAS NOVAS | H23: ORÇ | I23: ALVO-K | J23: 604010 | K23: 10020242 | L23: 1800 | M23: ENVIADO | T23: 45677
B24: 1464 | C24: JPE50-FcoLeocadio-PB | D24: 1464 | E24: ANDRE | F24: LOJAS NOVAS | G24: UTILITES LOJAS NOVAS | H24: ORÇ | I24: ALVO-K | J24: 604010 | K24: 10020243 | L24: 2000 | M24: ENVIADO | T24: 45677
B25: 1464 | C25: JPE50-FcoLeocadio-PB | D25: 1464 | E25: ANDRE | F25: LOJAS NOVAS | G25: UTILITES LOJAS NOVAS | H25: ORÇ | I25: ALVO-K | J25: 604010 | K25: 10020244 | L25: 4015 | M25: ENVIADO | T25: 45677
B26: 1464 | C26: JPE50-FcoLeocadio-PB | D26: 1464 | E26: ANDRE | F26: LOJAS NOVAS | G26: UTILITES LOJAS NOVAS | H26: ORÇ | I26: ALVO-K | J26: 604010 | K26: 10020245 | L26: 10350 | M26: ENVIADO | T26: 45677
B27: 1479 | C27: FOR192-AlCraveiro-CE | D27: 06.626.253/1479-26 | E27: Jordana | F27: LOJAS NOVAS | G27: UTILITES LOJAS NOVAS | H27: ORÇ | I27: ALVO-K | J27: 603708 | K27: 10020175 | L27: 4015 | M27: RECEBIDO | T27: 45677
B28: 1481 | C28: BJS02-ManoelLeite-CE. | D28: 06.626.253/0264-60 | E28: Jordana | F28: LOJAS NOVAS | G28: UTILITES LOJAS NOVAS | H28: ORÇ | I28: ALVO-K | J28: 603999 | K28: 10020246 | L28: 1800 | M28: ENVIADO | T28: 45677
B29: 1481 | C29: BJS02-ManoelLeite-CE. | D29: 06.626.253/0264-60 | E29: Jordana | F29: LOJAS NOVAS | G29: UTILITES LOJAS NOVAS | H29: ORÇ | I29: ALVO-K | J29: 603999 | K29: 10020247 | L29: 4015 | M29: ENVIADO | T29: 45677
B30: 1481 | C30: BJS02-ManoelLeite-CE. | D30: 06.626.253/0264-60 | E30: Jordana | F30: LOJAS NOVAS | G30: UTILITES LOJAS NOVAS | H30: ORÇ | I30: ALVO-K | J30: 603999 | K30: 10020248 | L30: 10350 | M30: ENVIADO | T30: 45677
B31: 140 | C31: MAC02-PontaVerde-AL | D31: =IFERROR(_xlfn.XLOOKUP(B31,'CNPJ LN'!C:C,'CNPJ LN'!D:D),_xlfn.XLOOKUP(B31,'CNPJ BASE jan25'!A:A,'CNPJ BASE jan25'!B:B)) -> MAC02-PontaVerde-AL | E31: ANDRE | F31: LAUDO DE RISCO | G31: REFORMA | H31: ORÇ | I31: BRUNO FANTINATI | J31: 605316 | K31: 10020113 | L31: 5600 | M31: RECEBIDO | N31: 4500776900 | T31: 45645
B32: 7178 | C32: CMT02-CeRaiLea-PA-EF | D32: =IFERROR(_xlfn.XLOOKUP(B32,'CNPJ LN'!C:C,'CNPJ LN'!D:D),_xlfn.XLOOKUP(B32,'CNPJ BASE jan25'!A:A,'CNPJ BASE jan25'!B:B)) -> CMT02-CeRaiLea-PA-EF | E32: ANDRE | F32: VIRADA DE BANDEIRA | G32: REFORMA | H32: ORÇ | I32: CARMELLI | J32: 605492 | K32: 10019999 | L32: 90000 | M32: RECEBIDO | N32: 4500776896 | T32: 45645
B33: 37 | C33: 37-FOR19-VirgTavora-CE | D33: 06.626.253/0037-62 | E33: JORDANA | F33: LAUDO DE RISCO | G33: PINTURA DE FAIXADA | H33: ORÇ | I33: CHIANCA | J33: 604821 | L33: R$ 14.347,98 | M33: RECEBIDO | T33: 45645
B34: 299 | C34: FOR117-SolonPinhe-CE | D34: 06.626.253/1408-32 | E34: JORDANA | F34: LAUDO DE RISCO | G34: PINTURA DE FAIXADA | H34: ORÇ | I34: CHIANCA | J34: 604824 | K34: 10019783 | L34: 8397.35 | M34: RECEBIDO | T34: 45645
B35: 1408 | C35: FOR123-GodMaciel4-CE | D35: 06.626.253/0299-90 | E35: JORDANA | F35: LAUDO DE RISCO | G35: RECUPERAÇÃO ESTACIONAMENTO | H35: ORÇ | I35: CHIANCA | J35: 605518 | L35: R$ 48.053,68 | M35: RECEBIDO | T35: 45645
B36: 79 | C36: SLU01-SaoLuis-MA# | D36: =IFERROR(_xlfn.XLOOKUP(B36,'CNPJ LN'!C:C,'CNPJ LN'!D:D),_xlfn.XLOOKUP(B36,'CNPJ BASE jan25'!A:A,'CNPJ BASE jan25'!B:B)) -> SLU01-SaoLuis-MA# | E36: ANDRE | F36: LAUDO DE RISCO | G36: REFORMA | H36: ORÇ | I36: DWA | J36: 605535 | K36: 10020105 | L36: 50699.453 | M36: RECEBIDO | N36: 4500772073 | T36: 45645
B37: 7054 | C37: SLU45-ColMor49-MA-EF | D37: =IFERROR(_xlfn.XLOOKUP(B37,'CNPJ LN'!C:C,'CNPJ LN'!D:D),_xlfn.XLOOKUP(B37,'CNPJ BASE jan25'!A:A,'CNPJ BASE jan25'!B:B)) -> SLU45-ColMor49-MA-EF | E37: ANDRE | F37: LAUDO DE RISCO | G37: REFORMA | H37: ORÇ | I37: DWA | J37: 605161 | K37: 10020106 | L37: 9706.5912 | M37: RECEBIDO | N37: 4500776912 | T37: 45645
B38: 7107 | C38: SLU50-JerDAlb2-MA-EF | D38: =IFERROR(_xlfn.XLOOKUP(B38,'CNPJ LN'!C:C,'CNPJ LN'!D:D),_xlfn.XLOOKUP(B38,'CNPJ BASE jan25'!A:A,'CNPJ BASE jan25'!B:B)) -> SLU50-JerDAlb2-MA-EF | E38: ANDRE | F38: LAUDO DE RISCO | G38: REFORMA | H38: ORÇ | I38: DWA | J38: 605160 | K38: 10020114 | L38: 13577.88 | M38: RECEBIDO | N38: 4500776904 | T38: 45645
B39: 7174 | C39: SLU58-JoMiJo21-MA-EF | D39: =IFERROR(_xlfn.XLOOKUP(B39,'CNPJ LN'!C:C,'CNPJ LN'!D:D),_xlfn.XLOOKUP(B39,'CNPJ BASE jan25'!A:A,'CNPJ BASE jan25'!B:B)) -> SLU58-JoMiJo21-MA-EF | E39: ANDRE | F39: LAUDO DE RISCO | G39: REFORMA | H39: ORÇ | I39: DWA | J39: 605162 | K39: 10020107 | L39: 5469.29 | M39: RECEBIDO | N39: 4500776915 | T39: 45645
B40: 56 | C40: FOR30-GomesMatos-CE | D40: =IFERROR(_xlfn.XLOOKUP(B40,'CNPJ LN'!C:C,'CNPJ LN'!D:D),_xlfn.XLOOKUP(B40,'CNPJ BASE jan25'!A:A,'CNPJ BASE jan25'!B:B)) -> FOR30-GomesMatos-CE | E40: JORDANA | F40: LOJAS NOVAS | G40: GERENCIAMENTO | H40: 14413 | I40: HTB | J40: 603700 | K40: 10020084 | L40: 36750 | M40: RECEBIDO | T40: 45645
B41: 613 | C41: ITJ01-Itajuba-MG# | D41: =IFERROR(_xlfn.XLOOKUP(B41,'CNPJ LN'!C:C,'CNPJ LN'!D:D),_xlfn.XLOOKUP(B41,'CNPJ BASE jan25'!A:A,'CNPJ BASE jan25'!B:B)) -> ITJ01-Itajuba-MG# | E41: ANDRE | F41: LOJAS NOVAS | G41: GERENCIAMENTO | H41: 14418 | I41: HTB | J41: 603320 | K41: 10020045 | L41: 48500 | M41: RECEBIDO | T41: 45645
B42: 616 | C42: FOR65-Paranjana2-CE# | D42: =IFERROR(_xlfn.XLOOKUP(B42,'CNPJ LN'!C:C,'CNPJ LN'!D:D),_xlfn.XLOOKUP(B42,'CNPJ BASE jan25'!A:A,'CNPJ BASE jan25'!B:B)) -> FOR65-Paranjana2-CE# | E42: JORDANA | F42: LOJAS NOVAS | G42: GERENCIAMENTO | H42: 14412 | I42: HTB | J42: 603708 | K42: 10020083 | L42: 36750 | M42: RECEBIDO | T42: 45645
B43: 1372 | D43: =IFERROR(_xlfn.XLOOKUP(B43,'CNPJ LN'!C:C,'CNPJ LN'!D:D),_xlfn.XLOOKUP(B43,'CNPJ BASE jan25'!A:A,'CNPJ BASE jan25'!B:B)) -> 06.626.253/1372-97 | E43: JORDANA | F43: LOJAS NOVAS | G43: GERENCIAMENTO | H43: 14417 | I43: HTB | J43: 603125 | K43: 10020100 | L43: 48500 | M43: RECEBIDO | T43: 45645
B44: 1432 | D44: =IFERROR(_xlfn.XLOOKUP(B44,'CNPJ LN'!C:C,'CNPJ LN'!D:D),_xlfn.XLOOKUP(B44,'CNPJ BASE jan25'!A:A,'CNPJ BASE jan25'!B:B)) -> 06.626.253/1432-62 | E44: JORDANA | F44: LOJAS NOVAS | G44: GERENCIAMENTO | H44: 14416 | I44: HTB | J44: 603254 | K44: 10020099 | L44: 48500 | M44: RECEBIDO | T44: 45645
B45: 1440 | D45: =IFERROR(_xlfn.XLOOKUP(B45,'CNPJ LN'!C:C,'CNPJ LN'!D:D),_xlfn.XLOOKUP(B45,'CNPJ BASE jan25'!A:A,'CNPJ BASE jan25'!B:B)) -> 06.626.253/1440-72 | E45: ANDRE | F45: LOJAS NOVAS | G45: GERENCIAMENTO | H45: 14415 | I45: HTB | J45: 602883 | K45: 10020098 | L45: 48500 | M45: RECEBIDO | T45: 45645
B46: 1455 | D46: =IFERROR(_xlfn.XLOOKUP(B46,'CNPJ LN'!C:C,'CNPJ LN'!D:D),_xlfn.XLOOKUP(B46,'CNPJ BASE jan25'!A:A,'CNPJ BASE jan25'!B:B)) -> 06.626.253/1455-59 | E46: JORDANA | F46: LOJAS NOVAS | G46: GERENCIAMENTO | H46: 14419 | I46: HTB | J46: 603909 | K46: 10020101 | L46: 48500 | M46: RECEBIDO | T46: 45645
B47: 1461 | D47: =IFERROR(_xlfn.XLOOKUP(B47,'CNPJ LN'!C:C,'CNPJ LN'!D:D),_xlfn.XLOOKUP(B47,'CNPJ BASE jan25'!A:A,'CNPJ BASE jan25'!B:B)) -> 06.626.253/1461-05 | E47: HENRIQUE | F47: LOJAS NOVAS | G47: GERENCIAMENTO | H47: 14414 | I47: HTB | J47: 603682 | K47: 10020097 | L47: 48500 | M47: RECEBIDO | T47: 45645
B48: 1464 | D48: =IFERROR(_xlfn.XLOOKUP(B48,'CNPJ LN'!C:C,'CNPJ LN'!D:D),_xlfn.XLOOKUP(B48,'CNPJ BASE jan25'!A:A,'CNPJ BASE jan25'!B:B)) -> 06.626.253/1464-40 | E48: JORDANA | F48: LOJAS NOVAS | G48: GERENCIAMENTO | H48: ORÇ | I48: HTB | J48: 604010 | K48: 10020156 | L48: 48500 | M48: ENVIADO | O48: aguardando pedido | T48: 45645
B49: 1481 | D49: 06.626.253/0264-60 | E49: JORDANA | F49: LOJAS NOVAS | G49: GERENCIAMENTO | H49: ORÇ | I49: HTB | J49: 603999 | K49: 10020146 | L49: 48500 | M49: RECEBIDO | N49: 4500780399 | T49: 45645
A50: 1000 | B50: 151 | C50: MAC03-Pajucara-AL | D50: =IFERROR(_xlfn.XLOOKUP(B50,'CNPJ LN'!C:C,'CNPJ LN'!D:D),_xlfn.XLOOKUP(B50,'CNPJ BASE jan25'!A:A,'CNPJ BASE jan25'!B:B)) -> MAC03-Pajucara-AL | E50: HENRIQUE | F50: LAUDO DE RISCO | G50: LUMINARIA | H50: ORÇ | I50: LUMICENTER | J50: 605568 | K50: 10020080 | L50: 31138.81 | M50: RECEBIDO | T50: 45645
B51: 323 | C51: REC18-BoaVista-PE | D51: =IFERROR(_xlfn.XLOOKUP(B51,'CNPJ LN'!C:C,'CNPJ LN'!D:D),_xlfn.XLOOKUP(B51,'CNPJ BASE jan25'!A:A,'CNPJ BASE jan25'!B:B)) -> REC18-BoaVista-PE | E51: ANDRE | F51: LAUDO DE RISCO | G51: LUMINARIA | H51: ORÇ | I51: LUMICENTER | J51: 605317 | K51: 10020104 | L51: 18976.53 | M51: RECEBIDO | N51: 4500772063 | T51: 45645
B52: 486 | C52: PRB01-Parauapebas-PA | D52: =IFERROR(_xlfn.XLOOKUP(B52,'CNPJ LN'!C:C,'CNPJ LN'!D:D),_xlfn.XLOOKUP(B52,'CNPJ BASE jan25'!A:A,'CNPJ BASE jan25'!B:B)) -> PRB01-Parauapebas-PA | E52: HENRIQUE | F52: LOJAS NOVAS | G52: LUMINARIA | H52: ORÇ | I52: LUMICENTER | J52: 603682 | K52: 10020120 | L52: 25215.55 | M52: RECEBIDO | N52: 4500780378 | T52: 45645
B53: 7389 | C53: FOR146-FcoSa-CE-EF | D53: =IFERROR(_xlfn.XLOOKUP(B53,'CNPJ LN'!C:C,'CNPJ LN'!D:D),_xlfn.XLOOKUP(B53,'CNPJ BASE jan25'!A:A,'CNPJ BASE jan25'!B:B)) -> FOR146-FcoSa-CE-EF | E53: ANDRE | F53: LAUDO DE RISCO | G53: COMUNICAÇÃO VISUAL | H53: ORÇ | I53: MANDACARU | J53: 605537 | K53: 10020108 | L53: 11000 | M53: RECEBIDO | T53: 45645
B54: 101 | C54: REC06-Caxanga-PE# | D54: =IFERROR(_xlfn.XLOOKUP(B54,'CNPJ LN'!C:C,'CNPJ LN'!D:D),_xlfn.XLOOKUP(B54,'CNPJ BASE jan25'!A:A,'CNPJ BASE jan25'!B:B)) -> REC06-Caxanga-PE# | E54: ANDRE | F54: LAUDO DE RISCO | G54: PERSIANA | H54: ORÇ | I54: PERSUN | J54: 605361 | K54: 10020112 | L54: 4620 | M54: RECEBIDO | N54: 4500772039 | T54: 45645
B55: 140 | C55: MAC02-PontaVerde-AL | D55: =IFERROR(_xlfn.XLOOKUP(B55,'CNPJ LN'!C:C,'CNPJ LN'!D:D),_xlfn.XLOOKUP(B55,'CNPJ BASE jan25'!A:A,'CNPJ BASE jan25'!B:B)) -> MAC02-PontaVerde-AL | E55: ANDRE | F55: LAUDO DE RISCO | G55: TOLDO/PERSIANA | H55: ORÇ | I55: PERSUN | J55: 605316 | K55: 10020111 | L55: 11660 | M55: RECEBIDO | N55: 4500772013 | T55: 45645
A56: 1000 | B56: 151 | C56: MAC03-Pajucara-AL | D56: =IFERROR(_xlfn.XLOOKUP(B56,'CNPJ LN'!C:C,'CNPJ LN'!D:D),_xlfn.XLOOKUP(B56,'CNPJ BASE jan25'!A:A,'CNPJ BASE jan25'!B:B)) -> MAC03-Pajucara-AL | E56: HENRIQUE | F56: LAUDO DE RISCO | G56: TOLDO/PERSIANA | H56: Nº 000097 | I56: PERSUN | J56: 605568 | K56: 10020076 | L56: 14300 | M56: RECEBIDO | T56: 45645
A57: 1000 | B57: 253 | C57: ARA01-Arapiraca-AL | E57: ANDRE | F57: LAUDO DE RISCO | G57: TOLDO/PERSIANA | H57: Nº 000067 | I57: PERSUN | J57: 605360 | K57: 10020155 | L57: 12100 | M57: RECEBIDO | T57: 45645
A58: 1000 | B58: 539 | C58: REC21-Caxanga-PE# | D58: =IFERROR(_xlfn.XLOOKUP(B58,'CNPJ LN'!C:C,'CNPJ LN'!D:D),_xlfn.XLOOKUP(B58,'CNPJ BASE jan25'!A:A,'CNPJ BASE jan25'!B:B)) -> REC21-Caxanga-PE# | E58: HENRIQUE | F58: LAUDO DE RISCO | G58: PERSIANA | H58: 76 | I58: PERSUN | J58: 605030 | K58: 10020079 | L58: 2460 | M58: RECEBIDO | T58: 45645
A59: 1000 | B59: 542 | C59: QIM01-Quixeramob-CE# | D59: =IFERROR(_xlfn.XLOOKUP(B59,'CNPJ LN'!C:C,'CNPJ LN'!D:D),_xlfn.XLOOKUP(B59,'CNPJ BASE jan25'!A:A,'CNPJ BASE jan25'!B:B)) -> QIM01-Quixeramob-CE# | E59: HENRIQUE | F59: LAUDO DE RISCO | G59: TOLDO/PERSIANA | H59: Nº 000102 | I59: PERSUN | J59: 604940 | K59: 10020075 | L59: 14780 | M59: RECEBIDO | T59: 45645
B60: 625 | C60: ARZ01-Aracruz-ES# | D60: =IFERROR(_xlfn.XLOOKUP(B60,'CNPJ LN'!C:C,'CNPJ LN'!D:D),_xlfn.XLOOKUP(B60,'CNPJ BASE jan25'!A:A,'CNPJ BASE jan25'!B:B)) -> ARZ01-Aracruz-ES# | E60: ANDRE | F60: LAUDO DE RISCO | G60: TOLDO/PERSIANA | H60: ORÇ | I60: PERSUN | J60: 605422 | K60: 10020089 | L60: 13602.95 | M60: RECEBIDO | N60: 4500771394 | T60: 45645
A61: 1000 | B61: 733 | C61: FOR76-Messejana2-CE# | E61: HENRIQUE | F61: LAUDO DE RISCO | G61: TOLDO/PERSIANA | H61: Nº 000103 | I61: PERSUN | J61: 605005 | K61: 10020145 | L61: 13260 | M61: RECEBIDO | N61: 4500780407 | O61: COMPLEMENTO | P61: 12905.1 | T61: 45645
B62: 1107 | C62: SAL33-RVermelho4-BA | D62: =IFERROR(_xlfn.XLOOKUP(B62,'CNPJ LN'!C:C,'CNPJ LN'!D:D),_xlfn.XLOOKUP(B62,'CNPJ BASE jan25'!A:A,'CNPJ BASE jan25'!B:B)) -> SAL33-RVermelho4-BA | E62: ANDRE | F62: LAUDO DE RISCO | G62: TOLDO/PERSIANA | H62: ORÇ | I62: PERSUN | J62: 605377 | K62: 10020088 | L62: 16002.94 | M62: RECEBIDO | N62: 4500771392 | T62: 45645
B63: 1134 | C63: VIT09-JdPenha-ES | D63: =IFERROR(_xlfn.XLOOKUP(B63,'CNPJ LN'!C:C,'CNPJ LN'!D:D),_xlfn.XLOOKUP(B63,'CNPJ BASE jan25'!A:A,'CNPJ BASE jan25'!B:B)) -> VIT09-JdPenha-ES | E63: ANDRE | F63: LAUDO DE RISCO | G63: TOLDO/PERSIANA | H63: ORÇ | I63: PERSUN | J63: 605379 | K63: 10020087 | L63: 17024.98 | M63: RECEBIDO | N63: 4500771367 | T63: 45645
B64: 1172 | C64: VDC05-LdeFreitas-BA | D64: =IFERROR(_xlfn.XLOOKUP(B64,'CNPJ LN'!C:C,'CNPJ LN'!D:D),_xlfn.XLOOKUP(B64,'CNPJ BASE jan25'!A:A,'CNPJ BASE jan25'!B:B)) -> VDC05-LdeFreitas-BA | E64: ANDRE | F64: LAUDO DE RISCO | G64: TOLDO/PERSIANA | H64: ORÇ | I64: PERSUN | J64: 605376 | K64: 10020110 | L64: 12522.98 | M64: RECEBIDO | N64: 4500771329 | T64: 45645
B65: 7173 | C65: FOR163-FreCiri-CE-EF | D65: =IFERROR(_xlfn.XLOOKUP(B65,'CNPJ LN'!C:C,'CNPJ LN'!D:D),_xlfn.XLOOKUP(B65,'CNPJ BASE jan25'!A:A,'CNPJ BASE jan25'!B:B)) -> FOR163-FreCiri-CE-EF | E65: HENRIQUE | F65: VIRADA DE BANDEIRA | G65: TOLDO/PERSIANA | H65: ORÇ | I65: PERSUN | J65: 605563 | K65: 10020048 | L65: 14260 | M65: RECEBIDO | T65: 45645
A66: 2000 | B66: 7183 | C66: FOR176-PAntTom-CE-EF | D66: =IFERROR(_xlfn.XLOOKUP(B66,'CNPJ LN'!C:C,'CNPJ LN'!D:D),_xlfn.XLOOKUP(B66,'CNPJ BASE jan25'!A:A,'CNPJ BASE jan25'!B:B)) -> FOR176-PAntTom-CE-EF | E66: HENRIQUE | F66: LAUDO DE RISCO | G66: PERSIANA | H66: Nº 000073 | I66: PERSUN | J66: 605167 | K66: 10020077 | L66: 3880 | M66: RECEBIDO | T66: 45645
B67: 7230 | C67: FOR173-BeirMar-CE-EF | D67: =IFERROR(_xlfn.XLOOKUP(B67,'CNPJ LN'!C:C,'CNPJ LN'!D:D),_xlfn.XLOOKUP(B67,'CNPJ BASE jan25'!A:A,'CNPJ BASE jan25'!B:B)) -> FOR173-BeirMar-CE-EF | E67: HENRIQUE | F67: VIRADA DE BANDEIRA | G67: PERSIANA | H67: ORÇ | I67: PERSUN | J67: 604531 | K67: 10020122 | L67: 6240 | M67: RECEBIDO | N67: 4500780351 | T67: 45645
B68: 7266 | C68: CAX03-Central-MA-EF | D68: =IFERROR(_xlfn.XLOOKUP(B68,'CNPJ LN'!C:C,'CNPJ LN'!D:D),_xlfn.XLOOKUP(B68,'CNPJ BASE jan25'!A:A,'CNPJ BASE jan25'!B:B)) -> CAX03-Central-MA-EF | E68: HENRIQUE | F68: VIRADA DE BANDEIRA | G68: TOLDO/PERSIANA | H68: ORÇ | I68: PERSUN | J68: 605330 | K68: 10020121 | L68: 9280 | M68: RECEBIDO | T68: 45645
B69: 7296 | C69: BAS02-PeFranco-MA-EF | D69: =IFERROR(_xlfn.XLOOKUP(B69,'CNPJ LN'!C:C,'CNPJ LN'!D:D),_xlfn.XLOOKUP(B69,'CNPJ BASE jan25'!A:A,'CNPJ BASE jan25'!B:B)) -> BAS02-PeFranco-MA-EF | E69: HENRIQUE | F69: VIRADA DE BANDEIRA | G69: PERSIANA | H69: ORÇ | I69: PERSUN | J69: 605496 | K69: 10020123 | L69: 4480 | M69: RECEBIDO | T69: 45645
B70: 7320 | C70: FOR133-CapArag-CE-EF | D70: =IFERROR(_xlfn.XLOOKUP(B70,'CNPJ LN'!C:C,'CNPJ LN'!D:D),_xlfn.XLOOKUP(B70,'CNPJ BASE jan25'!A:A,'CNPJ BASE jan25'!B:B)) -> FOR133-CapArag-CE-EF | E70: HENRIQUE | F70: VIRADA DE BANDEIRA | G70: TOLDO/PERSIANA | H70: ORÇ | I70: PERSUN | J70: 605561 | K70: 10020046 | L70: 6240 | M70: RECEBIDO | T70: 45645
B71: 7520 | C71: CRA04-DrJoaPes-CE-EF | D71: =IFERROR(_xlfn.XLOOKUP(B71,'CNPJ LN'!C:C,'CNPJ LN'!D:D),_xlfn.XLOOKUP(B71,'CNPJ BASE jan25'!A:A,'CNPJ BASE jan25'!B:B)) -> CRA04-DrJoaPes-CE-EF | E71: HENRIQUE | F71: VIRADA DE BANDEIRA | G71: TOLDO/PERSIANA | H71: ORÇ | I71: PERSUN | J71: 605330 | K71: 10020047 | L71: 12900 | M71: RECEBIDO | T71: 45645
B72: 7527 | C72: SAL70-JoaAngel-BA-EF | D72: 04.899.316/0527-70 | E72: HENRIQUE | F72: VIRADA DE BANDEIRA | G72: RUFO/BRAÇO | H72: NF | I72: PERSUN | J72: 604871 | K72: 10020144 | L72: 3715 | M72: RECEBIDO | N72: 4500780395 | T72: 45645
B73: 7066 | C73: ANA07-Coquei-PA-EF | D73: =IFERROR(_xlfn.XLOOKUP(B73,'CNPJ LN'!C:C,'CNPJ LN'!D:D),_xlfn.XLOOKUP(B73,'CNPJ BASE jan25'!A:A,'CNPJ BASE jan25'!B:B)) -> ANA07-Coquei-PA-EF | E73: ANDRE | F73: VIRADA DE BANDEIRA | G73: COMUNICAÇÃO VISUAL | H73: ORÇ | I73: TCF | J73: 605495 | K73: 10020025 | L73: 64822.85 | M73: RECEBIDO | N73: 4500776791 | T73: 45645
B74: 7092 | C74: BEL45-SenLemos-PA-EF | D74: =IFERROR(_xlfn.XLOOKUP(B74,'CNPJ LN'!C:C,'CNPJ LN'!D:D),_xlfn.XLOOKUP(B74,'CNPJ BASE jan25'!A:A,'CNPJ BASE jan25'!B:B)) -> BEL45-SenLemos-PA-EF | E74: ANDRE | F74: VIRADA DE BANDEIRA | G74: COMUNICAÇÃO VISUAL | H74: ORÇ | I74: TCF | J74: 605565 | K74: 10020029 | L74: 62252.68 | M74: RECEBIDO | N74: 4500776853 | T74: 45645
B75: 799 | C75: ASS01-Assu-RN# | D75: 06.626.253/0799-04 | E75: JORDANA | F75: LAUDO DE RISCO | H75: ORÇ | I75: PLANORC | J75: 605644 | K75: 10020221 | L75: 2450 | M75: RECEBIDO | T75: 45653
B76: 370 | C76: CAI01-Caico-RN | D76: 06.626.253/0370-71 | E76: JORDANA | F76: LAUDO DE RISCO | H76: ORÇ | I76: PLANORC | J76: 605621 | K76: 10020222 | L76: 2450 | M76: RECEBIDO | T76: 45653
B77: 726 | C77: CPM01-CampoMaior-PI | D77: 06.626.253/0726-59 | E77: JORDANA | F77: LAUDO DE RISCO | H77: ORÇ | I77: PLANORC | J77: 605640 | K77: 10020223 | L77: 2450 | M77: RECEBIDO | T77: 45653
B78: 679 | C78: CUN01-CurraisNv-RN# | D78: 06.626.253/0679-06 | E78: JORDANA | F78: LAUDO DE RISCO | H78: ORÇ | I78: PLANORC | J78: 605598 | K78: 10020224 | L78: 2450 | M78: RECEBIDO | T78: 45653
B79: 954 | C79: NAT22-Potengi-RN | D79: 06.626.253/0954-38 | E79: JORDANA | F79: LAUDO DE RISCO | H79: ORÇ | I79: PLANORC | J79: 605648 | K79: 10020250 | L79: 2450 | M79: RECEBIDO | T79: 45653
B80: 7424 | C80: NAT32-HerDaFon-RN-EF | D80: 04.899.316/0424-65 | E80: JORDANA | F80: LAUDO DE RISCO | H80: ORÇ | I80: PLANORC | J80: 605652 | K80: 10020225 | L80: 2450 | M80: RECEBIDO | T80: 45653
B81: 282 | C81: PAR01-Parnamirim-RN# | D81: 06.626.253/0282-42 | E81: JORDANA | F81: LAUDO DE RISCO | H81: ORÇ | I81: PLANORC | J81: 605614 | K81: 10020226 | L81: 2450 | M81: RECEBIDO | T81: 45653
B82: 480 | C82: PAR02-MaLacerda-RN# | D82: 06.626.253/0480-06 | E82: JORDANA | F82: LAUDO DE RISCO | H82: ORÇ | I82: PLANORC | J82: 605628 | K82: 10020226 | L82: 2450 | M82: RECEBIDO | T82: 45653
B83: 340 | C83: PIC01-Picos-PI | D83: 06.626.253/0340-56 | E83: JORDANA | F83: LAUDO DE RISCO | H83: ORÇ | I83: PLANORC | J83: 605619 | K83: 10020227 | L83: 2450 | M83: RECEBIDO | T83: 45653
B84: 762 | C84: PNC01-PNacional-TO | D84: 06.626.253/0762-12 | E84: JORDANA | F84: LAUDO DE RISCO | H84: ORÇ | I84: PLANORC | J84: 605643 | K84: 10020229 | L84: 2450 | M84: RECEBIDO | T84: 45653
B85: 85 | C85: TER01-Teresina-PI# | D85: 06.626.253/0085-60 | E85: JORDANA | F85: LAUDO DE RISCO | H85: ORÇ | I85: PLANORC | J85: 605556 | K85: 10020270 | L85: 2450 | M85: RECEBIDO | T85: 45653
B86: 87 | C86: TER02-Jockey-PI | D86: 06.626.253/0087-21 | E86: JORDANA | F86: LAUDO DE RISCO | H86: ORÇ | I86: PLANORC | J86: 605557 | K86: 10020270 | L86: 2450 | M86: RECEBIDO | T86: 45653
... B97: 626 | C97: TER14-AguaMineral-PI | D97: 06.626.253/0626-96 | E97: JORDANA | F97: LAUDO DE RISCO | H97: ORÇ | I97: PLANORC | J97: 605596 | K97: 10020270 | L97: 2450 | M97: RECEBIDO | T97: 45653
B98: 1455 | C98: VAR06-JoaoPonce-MT | D98: 06.626.253/1455-59 | E98: JORDANA | F98: LOJAS NOVAS | G98: LUMINARIA | I98: LUMICENTER | J98: 603908 | K98: 10020267 | L98: 32061.72 | M98: RECEBIDO | N98: 4500793684 | O98: =IFERROR(_xlfn.XLOOKUP(N98,'SOLICITAÇÃO DE PAGAMENTO'!T1:T1,'SOLICITAÇÃO DE PAGAMENTO'!V1:V203),"") | T98: 45667
B99: 56 | C99: FOR191-15Novembro-CE | D99: 06.626.253/0056-25 | E99: JORDANA | F99: LOJAS NOVAS | G99: LUMINARIA | H99: 86147 | I99: LUMICENTER | J99: 603700 | K99: 10020291 | L99: 28523.06 | M99: ENVIADO | T99: 45667
B100: 1479 | C100: FOR192-AlCraveiro-CE | D100: 06.626.253/1479-26 | E100: JORDANA | F100: LOJAS NOVAS | G100: LUMINARIA | H100: 85862 | I100: LUMICENTER | J100: 603708 | K100: 10020292 | L100: 22081.07 | M100: RECEBIDO | N100: 4500793694 | O100: =IFERROR(_xlfn.XLOOKUP(N100,'SOLICITAÇÃO DE PAGAMENTO'!#REF!,'SOLICITAÇÃO DE PAGAMENTO'!V2:V205),"") | S100: AJUSTAR CNPJ NO PEDIDO | T100: 45667
B101: 1432 | C101: REC72-AntFalcao-PE | D101: 06.626.253/1432-62 | E101: JORDANA | F101: LOJAS NOVAS | G101: LUMINARIA | I101: LUMICENTER | J101: 603254 | K101: 10020311 | L101: 20379.19 | M101: RECEBIDO | N101: 4500798256 | T101: 45667
B102: 1372 | C102: REC74-LuizNunes-PE | D102: 06.626.253/1372-97 | E102: JORDANA | F102: LOJAS NOVAS | G102: LUMINARIA | I102: LUMICENTER | J102: 603125 | K102: 10020287 | L102: 28719.93 | M102: RECEBIDO | N102: 4500793700 | O102: =IFERROR(_xlfn.XLOOKUP(N102,'SOLICITAÇÃO DE PAGAMENTO'!#REF!,'SOLICITAÇÃO DE PAGAMENTO'!V3:V207),"") | T102: 45667
B103: 1455 | C103: VAR06-JoaoPonce-MT | D103: 06.626.253/1455-59 | E103: JORDANA | F103: LOJAS NOVAS | G103: TOLDO/PERSIANA | I103: PERSUN | J103: 603908 | K103: 10020297 | L103: 12420 | M103: RECEBIDO | N103: 4500798395 | O103: =IFERROR(_xlfn.XLOOKUP(N103,'SOLICITAÇÃO DE PAGAMENTO'!#REF!,'SOLICITAÇÃO DE PAGAMENTO'!V4:V208),"") | T103: 45670
B104: 56 | C104: FOR191-15Novembro-CE | D104: 06.626.253/0056-25 | E104: JORDANA | F104: LOJAS NOVAS | G104: TOLDO/PERSIANA | I104: PERSUN | J104: 603700 | K104: 10020322 | L104: 11920 | M104: RECEBIDO | N104: 4500798260 | O104: =IFERROR(_xlfn.XLOOKUP(N104,'SOLICITAÇÃO DE PAGAMENTO'!#REF!,'SOLICITAÇÃO DE PAGAMENTO'!V5:V209),"") | T104: 45673
B105: 1479 | C105: FOR192-AlCraveiro-CE | D105: 06.626.253/1479-26 | E105: JORDANA | F105: LOJAS NOVAS | G105: TOLDO/PERSIANA | I105: PERSUN | J105: 603708 | K105: 10020298 | L105: 4980 | M105: RECEBIDO | N105: 4500798397 | O105: =IFERROR(_xlfn.XLOOKUP(N105,'SOLICITAÇÃO DE PAGAMENTO'!#REF!,'SOLICITAÇÃO DE PAGAMENTO'!V6:V209),"") | T105: 45670
B106: 1432 | C106: REC72-AntFalcao-PE | D106: 06.626.253/1432-62 | E106: JORDANA | F106: LOJAS NOVAS | G106: TOLDO/PERSIANA | I106: PERSUN | J106: 603254 | K106: 10020299 | L106: 12660 | M106: RECEBIDO | N106: 4500798399 | O106: =IFERROR(_xlfn.XLOOKUP(N106,'SOLICITAÇÃO DE PAGAMENTO'!#REF!,'SOLICITAÇÃO DE PAGAMENTO'!V7:V210),"") | T106: 45670
B107: 1372 | C107: REC74-LuizNunes-PE | D107: 06.626.253/1372-97 | E107: JORDANA | F107: LOJAS NOVAS | G107: TOLDO/PERSIANA | I107: PERSUN | J107: 603125 | K107: 10020300 | L107: 12660 | M107: RECEBIDO | N107: 4500798400 | O107: =IFERROR(_xlfn.XLOOKUP(N107,'SOLICITAÇÃO DE PAGAMENTO'!#REF!,'SOLICITAÇÃO DE PAGAMENTO'!V7:V211),"") | T107: 45670
B108: 1481 | C108: BJS02-ManoelLeite-CE | D108: 06.626.253/0264-60 | E108: JORDANA | F108: LOJAS NOVAS | G108: TOLDO/PERSIANA | I108: PERSUN | J108: 603999 | K108: 10020310 | L108: 13920 | M108: RECEBIDO | N108: 4500798403 | O108: =IFERROR(_xlfn.XLOOKUP(N108,'SOLICITAÇÃO DE PAGAMENTO'!#REF!,'SOLICITAÇÃO DE PAGAMENTO'!V8:V212),"") | T108: 45670
B109: 1464 | C109: JPE50-FcoLeocardio-PB | D109: 06.626.253/1464-40 | E109: ANDRE | F109: LOJAS NOVAS | G109: TOLDO/PERSIANA | I109: PERSUN | J109: 604010 | K109: 10020303 | L109: 12920 | M109: RECEBIDO | N109: 4500798404 | O109: =IFERROR(_xlfn.XLOOKUP(N109,'SOLICITAÇÃO DE PAGAMENTO'!#REF!,'SOLICITAÇÃO DE PAGAMENTO'!V9:V213),"") | T109: 45671
B110: 1381 | C110: MAC26-Aldebaran-AL | D110: 06.626.253/1381-88 | E110: ANDRE | F110: LOJAS NOVAS | G110: TOLDO/PERSIANA | I110: PERSUN | J110: 603265 | K110: 10020305 | L110: 10740 | M110: RECEBIDO | N110: 4500798406 | O110: =IFERROR(_xlfn.XLOOKUP(N110,'SOLICITAÇÃO DE PAGAMENTO'!#REF!,'SOLICITAÇÃO DE PAGAMENTO'!V10:V214),"") | T110: 45671
...

Sheet CNPJ LN
B1: Site | C1: COD | D1: CNPJ | E1: Loja Espelho | F1: Endereço
A2: =_xlfn.XLOOKUP(B2,'SOLICITAÇÃO DE PAGAMENTO'!C:C,'SOLICITAÇÃO DE PAGAMENTO'!E:E) -> JORDANA | B2: FOR191-15Novembro-CE | C2: 1484 | D2: 06.626.253/1484-93 | E2: 06.626.253/0056-25 | F2: Rua 15 de Novembro, 340 – Montese – Fortaleza - CE
A3: =_xlfn.XLOOKUP(B3,'SOLICITAÇÃO DE PAGAMENTO'!C:C,'SOLICITAÇÃO DE PAGAMENTO'!E:E) -> JORDANA | B3: FOR192-AlCraveiro-CE | C3: 1479 | D3: 06.626.253/1479-26 | E3: 06.626.253/0616-14 | F3: Av. Alberto Craveiro, 116 - Boa Vista Castelão, Fortaleza - CE
A4: =_xlfn.XLOOKUP(B4,'SOLICITAÇÃO DE PAGAMENTO'!C:C,'SOLICITAÇÃO DE PAGAMENTO'!E:E) -> HENRIQUE | B4: PRB03-Liberdade-PA | C4: 1461 | D4: 06.626.253/1461-05 | F4: Av. Liberdade, 202, Bairro Da Paz, Parauapebas - PA
A5: =_xlfn.XLOOKUP(B5,'SOLICITAÇÃO DE PAGAMENTO'!C:C,'SOLICITAÇÃO DE PAGAMENTO'!E:E) -> ANDRE | B5: OEI01-Oeiras-PI | C5: 1440 | D5: 06.626.253/1440-72 | E5: 06.626.253/1222-65 | F5: Av. José Tapety, 77, Centro, Oeiras - PI
A6: =_xlfn.XLOOKUP(B6,'SOLICITAÇÃO DE PAGAMENTO'!C:C,'SOLICITAÇÃO DE PAGAMENTO'!E:E) -> JORDANA | B6: REC74-LuizNunes-PE | C6: 1372 | D6: 06.626.253/1372-97 | E6: 06.626.253/0147-05 | F6: Rua Arquiteto Luiz Nunes, 1556 – Imbiribeira
A7: =_xlfn.XLOOKUP(B7,'SOLICITAÇÃO DE PAGAMENTO'!C:C,'SOLICITAÇÃO DE PAGAMENTO'!E:E) -> ANDRE | B7: CGD23-TrêsBarras-MS | C7: 1483 | D7: 06.626.253/1483-02 | F7: Av. Três Barras, 1038 - Vila Vilas Boas, Campo Grande - MS
A8: =_xlfn.XLOOKUP(B8,'SOLICITAÇÃO DE PAGAMENTO'!C:C,'SOLICITAÇÃO DE PAGAMENTO'!E:E) -> JORDANA | B8: VAR06-JoaoPonce-MT | C8: 1455 | D8: 06.626.253/1455-59 | F8: Av. João Ponce de Arruda, 170 - Centro Norte - Várzea Grande - MT
A9: =_xlfn.XLOOKUP(B9,'SOLICITAÇÃO DE PAGAMENTO'!C:C,'SOLICITAÇÃO DE PAGAMENTO'!E:E) -> JORDANA | B9: REC72-AntFalcao-PE | C9: 1432 | D9: 06.626.253/1432-62 | E9: 06.626.253/0134-82 | F9: R. Antônio Falcão, 438 - Boa Viagem, Recife - PE
B10: BJS02-ManuelLeite-CE | C10: 1481 | D10: 06.626.253/1481-40 | F10: R. Manoel Leite de Moura, 498 - Centro, Brejo Santo - CE
A11: JORDANA | B11: PDL01-Paudalho-PE | C11: 1462 | D11: 06.626.253/1462-88 | F11: R. Sen. Pinheiro Ramos, 369C - Centro, Paudalho - PE
B12: AJU30-GetulioVarg-SE | C12: 1012 | D12: 06.626.253/1012-68 | E12: 06.626.253/0827-00 | F12: Avenida Augusto Franco, 2500 – Ponto Novo
A13: =_xlfn.XLOOKUP(B13,'SOLICITAÇÃO DE PAGAMENTO'!C:C,'SOLICITAÇÃO DE PAGAMENTO'!E:E) -> ANDRE | B13: MAC26-Aldebaran-AL | C13: 1381 | D13: 06.626.253/1381-88 | E13: 06.626.253/0186-03 | F13: Rua José Alfredo Marques, 41 – Antares
B14: SAL64-ShBahia-BA
A15: =_xlfn.XLOOKUP(B15,'SOLICITAÇÃO DE PAGAMENTO'!C:C,'SOLICITAÇÃO DE PAGAMENTO'!E:E) -> HENRIQUE | B15: RBR13-VilaIvonete-AC | C15: 1446 | D15: 06.626.253/1446-68 | F15: Av. Antônio da Rocha Viana, 5225 - Vila Ivonete, Rio Branco - AC
B16: CRA05-CelAntLuiz-CE | C16: 1480 | D16: 06.626.253/1480-60 | F16: Rua Cel. Antonio Luiz, 1323 - Pimenta, Crato - CE
B17: TER31-CasteloPiaui-PI | C17: 1473 | D17: 06.626.253/1473-30 | F17: Rua Castelo do Piauí, 3.232, Qd. V, Buenos Aires, Teresina - PI
A18: ANDRE | B18: JPE50-FcoLeocardio-PB | C18: 1464 | D18: 06.626.253/1464-40 | F18: R. Francisco Leocádio Ribeiro Coutinho, S/N - Aeroclube, João Pessoa - PB
B19: CRU10-LeãoDourado-PE | C19: 1369 | D19: 06.626.253/1369-91 | E19: 06.626.253/0552-15 | F19: Avenida Leão Dourado, 222 – São Francisco
B20: SLU78-JoaoPessoa-MA | C20: 1439 | D20: 06.626.253/1439-39 | E20: 06.626.253/1045-26 | F20: Av. João Pessoa, 266-A - Jordoa, São Luís - MA
B21: SLU79-Cajazeiras-MA | E21: 06.626.253/0080-55 | F21: Av. Cajazeiras, 44, Centro, São Luís - MA
B22: JGU11-Montarroyos-PE | C22: 1427 | D22: 06.626.253/1427-03 | E22: 06.626.253/0602-19 | F22: Av. Ulisses Montarroyos, 2898, Piedade, Jaboatão dos Guararapes -PE
B23: JGU14-CuradoII-PE | C23: 400 | D23: 06.626.253/0400-21 | E23: 06.626.253/0923-31 | F23: R. Leonardo da Vinci, 1 - Curado, Recife - PE
B24: JGU15-AnicetoV-PE | C24: 1457 | D24: 06.626.253/1457-10 | F24: Rua Cuiabá, 992, Candeias
B25: PAR08-Rdosventos-RN | C25: 1460 | D25: 06.626.253/1460-16 | F25: Rua Cândido Martins dos Santos, 348, Parnamirim- RN
B26: SLU75-Holandeses-MA | C26: 1476 | D26: 06.626.253/1476-83 | F26: Av. Dos Holandeses, 1803, Ponta D’Areia, São Luís - MA
B27: SLU81-ArturCarval-MA | E27: 06.626.253/1077-03 | F27: Rua General Artur Carvalho, S/N, Turu, São Luís - MA
B28: SLU82-StDumont-MA | F28: Av. Santos Dumont, 21, Qd. 262, Lote 21, Alameda dos Sonhos, São Luís - MA
B29: SLU83-JAlbuquerqu-MA | F29: Av. Jerônimo de Albuquerque, 2.255, Cohama
B30: SLU84-Africanos-MA | C30: 1472 | D30: 06.626.253/1472-50 | F30: Av. dos Africanos, 163 - Coroado
B31: TER32-15deNov-PI | C31: 1475 | D31: 06.626.253/1475-00 | F31: Rua Rodrigues Alves, S/N, Lourival Parente
B32: AGU01-AguaBranca-PI
B33: ALT02-Brasilia-PA
B34: CGD-JMurtinho-MS
B35: CHP02-15Novembro-MA
B36: JBA06-CountryClub-BA
B37: SMG01-SaoMiguelGuama-PA
B38: TAM01-Tamandaré-PE
B39: TUC02-JMarilucy-PA
B40: FOR195-SaoCristovao-CE
B41: JPE48-AvProducao-PB
B42: JUA09-CasteloBranco-CE | C42: 1482 | D42: 06.626.253/1482-21 | F42: R. Raimundo Machado da Silva, S/N - Prefeito Carlos Alberto da Cruz, Juazeiro do Norte - CE
B43: PAR05-RosaFernandes-RN | C43: 1478 | D43: 06.626.253/1478-45 | F43: R. João Januário de Carvalho, 155 - Nova Esperança, Parnamirim - RN
B44: TER30-Aeroporto-PI | C44: 1428 | D44: 06.626.253/1428-86 | F44: Av. Rio de Janeiro, 1520 - Aeroporto, Teresina - PI
B45: BOV14-Jprimavera-RR | F45: Av. Gen. Ataide Teive, 5.960, Jardim Primavera, Boa Vista-RR
B46: AGA09-SadocCorrei-TO
B47: BAR03-Barreirinha-BA
B48: FOR188-Genibau-CE
B49: FOR189-AvIJWalter-CE
B50: GUR03-AvParana-TO
B51: STH01-SantaHelena-MA
B52: FOR197-MallGuararapes-CE

Sheet CNPJ BASE jan25
A1: COD_LOJA | B1: NOME_LOJA | C1: CNPJ
A2: 1 | B2: FOR01-Fortaleza-CE# | C2: 06.626.253/0001-51
A3: 2 | B3: FOR02-BezMenezes-CE# | C3: 06.626.253/0002-32
A4: 3 | B4: FOR03-Abolicao-CE | C4: 06.626.253/0003-13
A5: 4 | B5: FOR04-BrStudart-CE# | C5: 06.626.253/0004-02
A6: 5 | B6: TIN01-Tiangua-CE# | C6: 06.626.253/0005-85
A7: 6 | B7: SOB01-Sobral-CE | C7: 06.626.253/0006-66
A8: 7 | B8: FOR35-OtavioBonfi-CE | C8: 06.626.253/0007-47
A9: 8 | B9: PAC01-Pacajus-CE# | C9: 06.626.253/0008-28
A10: 9 | B10: FOR05-ShAldeota-CE# | C10: 06.626.253/0009-09
A11: 10 | B11: FOR87-CelCarvalh-CE# | C11: 06.626.253/0010-42
A12: 11 | B12: FOR06-AlbertoMag-CE# | C12: 06.626.253/0011-23
A13: 12 | B13: FOR07-JoseWalter-CE# | C13: 06.626.253/0012-04
... A502: 512 | B502: SFI02-WashingtoL-BA | C502: 06.626.253/0512-28
A503: 513 | B503: CGD05-StaDorothe-MS# | C503: 06.626.253/0513-09 | D503: nota
A504: 514 | B504: CGD06-Guanandi-MS# | C504: 06.626.253/0514-90
A505: 515 | B505: GOV01-GValadares-MG# | C505: 06.626.253/0515-70
A506: 516 | B506: FOR61-Expedicion-CE# | C506: 06.626.253/0516-51
A507: 517 | B507: POA03-LimaeSilva-RS | C507: 06.626.253/0517-32
A508: 518 | B508: AJU07-Laranjeiras-SE | C508: 06.626.253/0518-13
A509: 519 | B509: VAR01-VarzeaGran-MT# | C509: 06.626.253/0519-02
A510: 520 | B510: IGU02-Veneza-CE# | C510: 06.626.253/0520-38
A511: 521 | B511: JPA02-MarRondon-RO | C511: 06.626.253/0521-19
A512: 522 | B512: CRS01-CruzeiroSul-AC | C512: 06.626.253/0522-08
A513: 523 | B513: PAF01-PauloAfons-BA# | C513: 06.626.253/0523-80
A514: 524 | B514: SRP01-SJRioPreto-SP | C514: 06.626.253/0524-61
A515: 525 | B515: NAT17-RomualdoGa-RN# | C515: 06.626.253/0525-42
... A600: 612 | B600: CPN05-Taquaral-SP | C600: 06.626.253/0612-90
A601: 613 | B601: ITJ01-Itajuba-MG# | C601: 06.626.253/0613-71 | D601: pedido
A602: 614 | B602: BEL10-SenadoLemos-PA | C602: 06.626.253/0614-52
A603: 615 | B603: BBL01-Barbalha-CE | C603: 06.626.253/0615-33
A604: 616 | B604: FOR65-Paranjana2-CE# | C604: 06.626.253/0616-14
A605: 617 | B605: BEL08-ParqueVerde-PA | C605: 06.626.253/0617-03
A606: 618 | B606: RON02-VilaAurora-MT | C606: 06.626.253/0618-86
A607: 619 | B607: GOI13-SenadCanedo-GO | C607: 06.626.253/0619-67
A608: 620 | B608: BJD01-BeloJardim-PE# | C608: 06.626.253/0620-09
A609: 621 | B609: REC23-Arraial-PE# | C609: 06.626.253/0621-81
A610: 622 | B610: GMA01-Gama-DF | C610: 06.626.253/0622-62
A611: 623 | B611: BSB05-AguasClara-DF# | C611: 06.626.253/0623-43
A612: 624 | B612: CBA08-Mossungue-PR# | C612: 06.626.253/0624-24
A613: 625 | B613: ARZ01-Aracruz-ES# | C613: 06.626.253/0625-05
... A1414: 1479 | B1414: FOR192-AlCraveiro-CE | C1414: 06.626.253/1479-26
A1415: 1484 | B1415: FOR191-15Novembro-CE
A1416: 7011 | B1416: BEL36-GenDeo-PA-EF | C1416: 04.899.316/0011-90
A1417: 7012 | B1417: ANA04-Sn21129-PA-EF | C1417: 04.899.316/0012-70
A1418: 7013 | B1418: BEL74-Atalaia-PA-EF | C1418: 04.899.316/0013-51
A1419: 7014 | B1419: BEL55-AntBarre-PA-EF | C1419: 04.899.316/0014-32
A1420: 7016 | B1420: BEL28-Cremac-PA-EF | C1420: 04.899.316/0016-02
A1421: 7017 | B1421: ANA05-Centro-PA-EF | C1421: 04.899.316/0017-85
A1422: 7018 | B1422: BEL26-GoJoMa-PA-EF | C1422: 04.899.316/0018-66
A1423: 7019 | B1423: ANA06-TreCor-PA-EF | C1423: 04.899.316/0019-47
A1424: 7020 | B1424: BEL93-GoJosMal-PA-EF | C1424: 04.899.316/0020-80
A1425: 7021 | B1425: BEL60-AlmBarro-PA-EF | C1425: 04.899.316/0021-61
A1426: 7022 | B1426: BEL27-DosMun-PA-EF | C1426: 04.899.316/0022-42
A1427: 7023 | B1427: BEL32-DeObid-PA-EF | C1427: 04.899.316/0023-23
... A1814: 7543 | B1814: STI04-CasBranc-MA-EF | C1814: 04.899.316/0543-90
A1815: - | B1815: - | C1815: 04.899.316/0233-20
A1816: - | B1816: - | C1816: 04.899.316/0228-63
A1817: - | B1817: - | C1817: 04.899.316/0083-64
A1818: - | B1818: - | C1818: 04.899.316/0232-40
A1819: - | B1819: - | C1819: -
A1820: - | B1820: - | C1820: 04.899.316/0112-33
A1821: - | B1821: - | C1821: 04.899.316/0195-60
A1822: - | B1822: - | C1822: 04.899.316/0314-20
A1823: - | B1823: - | C1823: 04.899.316/0155-73
A1824: - | B1824: - | C1824: -
A1825: - | B1825: - | C1825: -
A1826: - | B1826: - | C1826: -
... A1890: - | B1890: - | C1890: -
A1891: 67 | B1891: FOR39-StDumont-CE | C1891: 06.626.253/0067-88
A1892: - | B1892: - | C1892: 04.899.316/0426-27
A1893: - | B1893: - | C1893: 04.899.316/0483-15
A1894: - | B1894: - | C1894: 04.899.316/0327-45
A1895: - | B1895: - | C1895: 04.899.316/0018-66
A1896: - | B1896: - | C1896: 04.899.316/0159-05
A1897: - | B1897: - | C1897: 04.899.316/0110-71
A1898: - | B1898: - | C1898: 04.899.316/0261-84
A1899: - | B1899: - | C1899: 04.899.316/0497-10
A1900: - | B1900: - | C1900: 04.899.316/0167-07
A1901: - | B1901: - | C1901: 04.899.316/0391-62

Sheet Ordens
A1: 604771 | B1: Y600 | C1: 1000 | D1: LOJA 7393 [Troca de Bandeira]
A2: 604772 | B2: Y600 | C2: 1000 | D2: LOJA 7394 [Troca de Bandeira]
A3: 604773 | B3: Y600 | C3: 1000 | D3: LOJA 7399 [Troca de Bandeira]
A4: 604774 | B4: Y600 | C4: 1000 | D4: LOJA 7400 [Troca de Bandeira]
A5: 604775 | B5: Y600 | C5: 1000 | D5: LOJA 7414 [Troca de Bandeira]
A6: 604776 | B6: Y600 | C6: 1000 | D6: LOJA 7416 [Troca de Bandeira]
A7: 604777 | B7: Y600 | C7: 1000 | D7: LOJA 7422 [Troca de Bandeira]
A8: 604779 | B8: Y600 | C8: 1000 | D8: LOJA 7439 [Troca de Bandeira]
A9: 604816 | B9: Y600 | C9: 1000 | D9: LOJA 7049 [Troca de Bandeira]
A10: 604817 | B10: Y600 | C10: 1000 | D10: LOJA 7438 [Troca de Bandeira]
A11: 604818 | B11: Y600 | C11: 1000 | D11: LOJA 7454 [Troca de Bandeira]
A12: 604819 | B12: Y600 | C12: 1000 | D12: LOJA 7462 [Troca de Bandeira]
... A132: 604284 | B132: Y600 | C132: 1000 | D132: FOR196-ScarJer-CE-EF [Troca de Bandeira]

Sheet MATERIAIS
B2: Material Luminária
B4: Modelo Forro 1250
B5: 25913
B7: Modelo Forro 617
B8: 25914
B9: Modelo Sem Forro | C9: MODELO PRETO NA IMAGEM
B10: 26772
B11: Modelo EF75-E2000850 | D11: QUADRADO
B12: 32434
B13: Modelo Balizador
B14: 26726
B15: Modelo Bulbo
B16: 32500
B17: LUMINARIA LED 36W 4450m
B18: 32715
B19: Material Toldo e Persiana
B21: Toldo
B22: 25992
B23: Persiana
B24: 26706
B26: Material CONSTRUÇÃO DE LOJAS
B28: LOJAS NOVAS
B29: 20102
B31: GERENCIAMENTO DE OBRAS
B32: 32432
B34: UTILITIES LOJAS NOVAS
B35: 32433
B37: REFORMA DE LOJA
B38: 20103
B40: COMUNICAÇÃO VISUAL
B41: 20029
B43: RUFO LARGO
B44: 30389
B45: BRAÇO ARTICULADO
B46: 32441
B48: ADEQUAÇÃO
B49: 24755
B51: CHAPA DE FERRO
B52: 32367

Sheet SOLICITAÇÃO DE PRESERVAÇÃO
A1: FILIAL | B1: COORDENADOR | C1: PROJETO | D1: SERVIÇO | E1: ORDEM | F1: DATA ENTRADA | G1: DATA SAÍDA | H1: SOLICITADO? | I1: STATUS | J1: DIAS | K1: HORÁRIO ENTRADA | L1: HORÁRIO SAÍDA | M1: VALOR DIA | N1: VALOR TOTAL
A2: 373 | B2: ADRIANO | C2: REVITALIZA | D2: PRESERVAÇÃO | E2: 605784 | F2: 45884 | G2: 45885 | H2: Sim | I2: =IF(Tabela2[[#This Row],[VALOR TOTAL]]>=1,"Concluído",IF(Tabela2[[#This Row],[SOLICITADO?]]="Sim","Solicitado","")) -> Solicitado | J2: =Tabela2[[#This Row],[DATA SAÍDA]]-Tabela2[[#This Row],[DATA ENTRADA]] -> 1 | K2: 0.875 | L2: 0.29166667 | N2: =Tabela2[[#This Row],[VALOR DIA]]*Tabela2[[#This Row],[DIAS]] -> 0
A3: 63 | B3: ADRIANO | C3: LAUDO DE RISCO | D3: PRESERVAÇÃO | E3: 605753 | F3: 45887 | G3: 45892 | H3: Sim | I3: =IF(Tabela2[[#This Row],[VALOR TOTAL]]>=1,"Concluído",IF(Tabela2[[#This Row],[SOLICITADO?]]="Sim","Solicitado","")) -> Solicitado | J3: =Tabela2[[#This Row],[DATA SAÍDA]]-Tabela2[[#This Row],[DATA ENTRADA]] -> 5 | K3: 0.79166667 | L3: 0.29166667 | N3: =Tabela2[[#This Row],[VALOR DIA]]*Tabela2[[#This Row],[DIAS]] -> 0
A4: 260 | B4: ADRIANO | D4: PRESERVAÇÃO | F4: 45894 | G4: 45895 | H4: Sim | I4: =IF(Tabela2[[#This Row],[VALOR TOTAL]]>=1,"Concluído",IF(Tabela2[[#This Row],[SOLICITADO?]]="Sim","Solicitado","")) -> Solicitado | J4: =Tabela2[[#This Row],[DATA SAÍDA]]-Tabela2[[#This Row],[DATA ENTRADA]] -> 1 | K4: 0.91666667 | L4: 0.29166667 | N4: =Tabela2[[#This Row],[VALOR DIA]]*Tabela2[[#This Row],[DIAS]] -> 0
A5: 260 | B5: ADRIANO | D5: PRESERVAÇÃO | F5: 45903 | G5: 45906 | H5: Sim | I5: =IF(Tabela2[[#This Row],[VALOR TOTAL]]>=1,"Concluído",IF(Tabela2[[#This Row],[SOLICITADO?]]="Sim","Solicitado","")) -> Solicitado | J5: =Tabela2[[#This Row],[DATA SAÍDA]]-Tabela2[[#This Row],[DATA ENTRADA]] -> 3 | K5: 0.95833333 | L5: 0.29166667 | N5: =Tabela2[[#This Row],[VALOR DIA]]*Tabela2[[#This Row],[DIAS]] -> 0
A6: 588 | B6: ADRIANO | D6: PRESERVAÇÃO | F6: 45902 | G6: 45903 | H6: Sim | I6: =IF(Tabela2[[#This Row],[VALOR TOTAL]]>=1,"Concluído",IF(Tabela2[[#This Row],[SOLICITADO?]]="Sim","Solicitado","")) -> Solicitado | J6: =Tabela2[[#This Row],[DATA SAÍDA]]-Tabela2[[#This Row],[DATA ENTRADA]] -> 1 | K6: 0.91666667 | L6: 0.29166667 | N6: =Tabela2[[#This Row],[VALOR DIA]]*Tabela2[[#This Row],[DIAS]] -> 0
A7: 429 | B7: ADRIANO | D7: PRESERVAÇÃO | F7: 45911 | G7: 45913 | H7: Sim | I7: =IF(Tabela2[[#This Row],[VALOR TOTAL]]>=1,"Concluído",IF(Tabela2[[#This Row],[SOLICITADO?]]="Sim","Solicitado","")) -> Solicitado | J7: =Tabela2[[#This Row],[DATA SAÍDA]]-Tabela2[[#This Row],[DATA ENTRADA]] -> 2 | K7: 0.95833333 | L7: 0.25 | N7: =Tabela2[[#This Row],[VALOR DIA]]*Tabela2[[#This Row],[DIAS]] -> 0

Sheet PADRÃO COLUNA CRIAÇÃO RC
A1: ORDEM | B1: MATERIAL | H1: QTDE | I1: PREÇO | M1: DATA | O1: LOJA | P1: RC | Q1: Material Luminária | U1: Descrição | AB1: NCM | AC1: COD MAT
A2: f | B2: 25913 | H2: 66 | I2: 261.37 | M2: 06.10.2025 | O2: 1476 | P2: 10023559 | U2: LED MINI TETRIS MAGNETICO 36W 48V 3000K LUZ DIFUSA CONEX. INFERIOR | AB2: 94051190 | AC2: 32564
A3: f | B3: 25914 | H3: 7 | I3: 207.93 | M3: 06.10.2025 | O3: 1476 | P3: 10023559
A4: f | B4: 32434 | H4: 8 | I4: 264.79 | M4: 06.10.2025 | O4: 1476 | P4: 10023559
A5: f | B5: 25913 | H5: 64 | I5: 261.37 | M5: 06.10.2025 | O5: 1437 | P5: att
A6: f | B6: 25914 | H6: 29 | I6: 207.93 | M6: 06.10.2025 | O6: 1437 | P6: att
A7: f | B7: 32434 | H7: 5 | I7: 264.79 | M7: 06.10.2025 | O7: 1437 | P7: att
A8: f | B8: 25913 | H8: 78 | I8: 238.17 | M8: 06.10.2025 | O8: 1427 | P8: 10023580
A9: f | B9: 25914 | H9: 15 | I9: 189.46 | M9: 06.10.2025 | O9: 1427 | P9: 10023580
A10: f | B10: 25913 | H10: 69 | I10: 240.42 | M10: 06.10.2025 | O10: 1506 | P10: att
A11: f | B11: 25914 | H11: 19 | I11: 191.23 | M11: 06.10.2025 | O11: 1506 | P11: att
A12: f | B12: 32434 | H12: 8 | I12: 243.53 | M12: 06.10.2025 | O12: 1506 | P12: att | Q12: Modelo Forro 1250 | U12: LED PERFIL ALUM. KYOTO SOBR. 3M DIF.FOSCO PT MICRO | AB12: 94059900 | AC12: 32565
A13: f | B13: 25913 | H13: 65 | I13: 240.42 | M13: 06.10.2025 | O13: 1505 | P13: 10023581
A14: f | B14: 25914 | H14: 15 | I14: 191.23 | M14: 06.10.2025 | O14: 1505 | P14: 10023581 | Q14: 25913 | U14: LED FITA FLEX DOUBLE LINE 28,8W/M IP20 24V IRC>90 3000K 256 LEDS/M | AB14: 85395100 | AC14: 32618
A15: f | B15: 32434 | H15: 5 | I15: 226.84 | M15: 06.10.2025 | O15: 1505 | P15: 10023581
A16: f | B16: 25913 | H16: 74 | I16: 277.04 | M16: 06.10.2025 | O16: 1499 | P16: 10023582 | Q16: 32433 | W16: 13437.5 | X16: 1 | AB16: 15.09.2025 | AD16: 382
A17: f | B17: 25914 | H17: 17 | I17: 220.37 | M17: 06.10.2025 | O17: 1499 | P17: 10023582
A18: f | B18: 32434 | H18: 6 | I18: 280.66 | M18: 06.10.2025 | O18: 1499 | P18: 10023582
A19: f | B19: 25913 | H19: 73 | I19: 310.41 | M19: 06.10.2025 | O19: 1401 | P19: 10023583
A20: f | B20: 25914 | H20: 21 | I20: 246.92 | M20: 06.10.2025 | O20: 1401 | P20: 10023583 | Q20: Modelo Forro 617 | U20: LED PERFIL KYOTO SOBR. KIT FIXAC. ACO PEND. | AB20: 94059900 | AC20: 32620
A21: f | B21: 32434 | H21: 4 | I21: 314.48 | M21: 06.10.2025 | O21: 1401 | P21: 10023583 | Q21: 25914 | U21: LED LUMI EMB. PAINEL RETANG. 36W 3000K 320X620 | AB21: 94051190 | AC21: 32621
A22: f | B22: 32434 | H22: 7 | I22: 221.77 | M22: 06.10.2025 | O22: 1427 | Q22: Modelo Sem Forro | R22: MODELO PRETO NA IMAGEM | U22: LED PERFIL ALUM. LONDRES SOBR. 3M DIF.FOSCO BR MICRO | AB22: 94059900 | AC22: 32622
A23: f | B23: 25914 | H23: 3 | I23: 282.46 | M23: 06.10.2025 | O23: 1427 | Q23: 26772 | U23: LED FITA FLEX HIGH 14,4W/M IP20 24V IRC>90 3000K 160 LEDS/M | AB23: 85395100 | AC23: 32623
A24: f | B24: 30333 | H24: 4 | M24: 03.11.2025 | O24: 503 | Q24: Modelo EF75-E2000850 | R24: QUADRADO | U24: LED FONTE TENSAO 100W 24V 90~264VAC IP67 LPV-100-24 | AB24: 85044029 | AC24: 32624
A25: f | B25: 30334 | H25: 4 | M25: 03.11.2025 | O25: 503 | Q25: 32434 | U25: LED LUMI TRACK LIGHT MAG. SUPERIOR 1X LED 10W 48V 3000K 24° BR | AB25: 94051190 | AC25: 32625
A26: f | B26: 30229 | H26: 1 | M26: 03.11.2025 | O26: 503 | Q26: Modelo Balizador | U26: TRILHO MAGNETICO SOBR. SLIM 2M BR | AB26: 94051190 | AC26: 32626
A27: f | B27: 30230 | H27: 1 | M27: 03.11.2025 | O27: 503 | Q27: 26726 | U27: TRILHO MAGNETICO SLIM CONECTOR ALIMENT. EMENDA BR | AB27: 94059900 | AC27: 32627
A28: f | B28: 30100 | H28: 1 | M28: 03.11.2025 | O28: 503 | Q28: Modelo Bulbo | U28: TRILHO MAGNETICO SLIM CONECTOR ALIMENT. C/CABO BR | AB28: 94059900 | AC28: 32628
A29: f | B29: 30101 | H29: 1 | M29: 03.11.2025 | O29: 503 | Q29: 32500 | U29: LED FONTE TENSAO 200W 48V BIVOLT CHAVEADA | AB29: 95044030 | AC29: 32629
A30: f | B30: 30022 | H30: 1 | M30: 03.11.2025 | O30: 503 | Q30: Material Toldo e Persiana
A31: f | B31: 30023 | H31: 1 | M31: 03.11.2025 | O31: 503
A32: f | B32: 20424 | H32: 1 | M32: 03.11.2025 | O32: 503 | Q32: Toldo
A33: f | B33: 25789 | H33: 2 | M33: 03.11.2025 | O33: 503 | Q33: 25992 | R33: 25992
Q34: Persiana | R34: 26706
Q35: 26706
Q37: Material CONSTRUÇÃO DE LOJAS
Q39: LOJAS NOVAS
Q40: 20102
Q42: GERENCIAMENTO DE OBRAS
Q43: 32432
Q45: UTILITIES LOJAS NOVAS
Q46: 32433
Q48: REFORMA
Q49: 20103
Q51: COMUNICAÇÃO VISUAL
Q52: 20029
Q54: RUFO LARGO
Q55: 30389
Q56: BRAÇO ARTICULADO
Q57: 32441
Q59: ADEQUAÇÃO
Q60: 24755
Q62: CHAPA DE FERRO
Q63: 32367

Sheet CADASTRO NOVAS UNIDADES CONSUMI
B2: CADASTRO NOVAS UNIDADES CONSUMIDORAS
B3: DT. ABERTURA | C3: CONDIÇÃO | D3: STATUS LOJA | E3: LOJA | F3: ORDEM | G3: FILIAL | H3: COORD | I3: RESULT | J3: TICKET AGUA | K3: DATA TICKET AGUA | L3: STATUS TICKET AGUA | M3: OBS AGUA | N3: TICKET ENERGIA | O3: DATA TICKET ENERGIA | P3: STATUS TICKET ENERGIA | Q3: OBS ENERGIA
B4: =_xlfn.XLOOKUP(E4,[1]Consolidado!$A:$A,[1]Consolidado!$D:$D) -> 45687 | C4: =IF(I4="TICKET CONCLUÍDO", "Concluído", IF(B4 < TODAY(), "Prazo estourado - " & TODAY()-B4 & " dias atrás", IF(TODAY()+30 < B4, "No prazo - faltam " & B4-TODAY() & " dias", IF(AND(B4-TODAY()<=29, B4-TODAY()>7), "Solicitar dados - faltam " & B4-TODAY() & " dias", IF(B4-TODAY()<=7, "Resolicitar - faltam " & B4-TODAY() & " dias", "Verificar") ) ) ) ) -> Concluído | D4: =_xlfn.XLOOKUP(E4,[1]Consolidado!$A:$A,[1]Consolidado!$AN:$AN) -> 0 | E4: OEI01-Oeiras-PI | F4: =_xlfn.XLOOKUP(E4,'SOLICITAÇÃO DE PAGAMENTO'!C:C,'SOLICITAÇÃO DE PAGAMENTO'!M:M) -> 602883 | G4: =_xlfn.XLOOKUP(E4,'SOLICITAÇÃO DE PAGAMENTO'!C:C,'SOLICITAÇÃO DE PAGAMENTO'!B:B) -> 1440 | H4: =_xlfn.XLOOKUP(G4,'SOLICITAÇÃO DE PAGAMENTO'!B:B,'SOLICITAÇÃO DE PAGAMENTO'!E:E) -> ANDRE | I4: =IF(AND(L4="RESPONSABILIDADE CSC",P4="RESPONSABILIDADE CSC"),"TICKET CONCLUÍDO", "PENDENTE") -> TICKET CONCLUÍDO | J4: 1118416 | K4: 45691 | L4: RESPONSABILIDADE CSC | M4: FATURA EM ABERTO PAGA | N4: 1118394 | O4: 45691 | P4: RESPONSABILIDADE CSC | Q4: FATURA EM ABERTO PAGA
B5: =_xlfn.XLOOKUP(E5,[1]Consolidado!$A:$A,[1]Consolidado!$D:$D) -> 45670 | C5: =IF(I5="TICKET CONCLUÍDO", "Concluído", IF(B5 < TODAY(), "Prazo estourado - " & TODAY()-B5 & " dias atrás", IF(TODAY()+30 < B5, "No prazo - faltam " & B5-TODAY() & " dias", IF(AND(B5-TODAY()<=29, B5-TODAY()>7), "Solicitar dados - faltam " & B5-TODAY() & " dias", IF(B5-TODAY()<=7, "Resolicitar - faltam " & B5-TODAY() & " dias", "Verificar") ) ) ) ) -> Concluído | D5: =_xlfn.XLOOKUP(E5,[1]Consolidado!$A:$A,[1]Consolidado!$AN:$AN) -> 0 | E5: FOR192-AlCraveiro-CE | F5: =_xlfn.XLOOKUP(E5,'SOLICITAÇÃO DE PAGAMENTO'!C:C,'SOLICITAÇÃO DE PAGAMENTO'!M:M) -> 603708 | G5: 1479 | H5: =_xlfn.XLOOKUP(G5,'SOLICITAÇÃO DE PAGAMENTO'!B:B,'SOLICITAÇÃO DE PAGAMENTO'!E:E) -> JORDANA | I5: TICKET CONCLUÍDO | L5: COBRANCA VIA CONDOMINIO DO SHOPPING | N5: 1118352 | O5: 45691 | P5: RESPONSABILIDADE CSC
B6: =_xlfn.XLOOKUP(E6,[1]Consolidado!$A:$A,[1]Consolidado!$D:$D) -> 45688 | C6: =IF(I6="TICKET CONCLUÍDO", "Concluído", IF(B6 < TODAY(), "Prazo estourado - " & TODAY()-B6 & " dias atrás", IF(TODAY()+30 < B6, "No prazo - faltam " & B6-TODAY() & " dias", IF(AND(B6-TODAY()<=29, B6-TODAY()>7), "Solicitar dados - faltam " & B6-TODAY() & " dias", IF(B6-TODAY()<=7, "Resolicitar - faltam " & B6-TODAY() & " dias", "Verificar") ) ) ) ) -> Concluído | D6: =_xlfn.XLOOKUP(E6,[1]Consolidado!$A:$A,[1]Consolidado!$AN:$AN) -> 0 | E6: PRB03-Liberdade-PA | F6: =_xlfn.XLOOKUP(E6,'SOLICITAÇÃO DE PAGAMENTO'!C:C,'SOLICITAÇÃO DE PAGAMENTO'!M:M) -> 603682 | G6: 1461 | H6: =_xlfn.XLOOKUP(G6,'SOLICITAÇÃO DE PAGAMENTO'!B:B,'SOLICITAÇÃO DE PAGAMENTO'!E:E) -> HENRIQUE | I6: =IF(AND(L6="RESPONSABILIDADE CSC",P6="RESPONSABILIDADE CSC"),"TICKET CONCLUÍDO", "PENDENTE") -> TICKET CONCLUÍDO | J6: 1118464 | K6: 45691 | L6: RESPONSABILIDADE CSC | N6: 1288763 | O6: 45716 | P6: RESPONSABILIDADE CSC
B7: =_xlfn.XLOOKUP(E7,[1]Consolidado!$A:$A,[1]Consolidado!$D:$D) -> 45684 | C7: =IF(I7="TICKET CONCLUÍDO", "Concluído", IF(B7 < TODAY(), "Prazo estourado - " & TODAY()-B7 & " dias atrás", IF(TODAY()+30 < B7, "No prazo - faltam " & B7-TODAY() & " dias", IF(AND(B7-TODAY()<=29, B7-TODAY()>7), "Solicitar dados - faltam " & B7-TODAY() & " dias", IF(B7-TODAY()<=7, "Resolicitar - faltam " & B7-TODAY() & " dias", "Verificar") ) ) ) ) -> Concluído | D7: =_xlfn.XLOOKUP(E7,[1]Consolidado!$A:$A,[1]Consolidado!$AN:$AN) -> 0 | E7: FOR191-15Novembro-CE | F7: =_xlfn.XLOOKUP(E7,'SOLICITAÇÃO DE PAGAMENTO'!C:C,'SOLICITAÇÃO DE PAGAMENTO'!M:M) -> 603700 | G7: =_xlfn.XLOOKUP(E7,'SOLICITAÇÃO DE PAGAMENTO'!C:C,'SOLICITAÇÃO DE PAGAMENTO'!B:B) -> 1484 | H7: =_xlfn.XLOOKUP(G7,'SOLICITAÇÃO DE PAGAMENTO'!B:B,'SOLICITAÇÃO DE PAGAMENTO'!E:E) -> JORDANA | I7: =IF(AND(L7="RESPONSABILIDADE CSC",P7="RESPONSABILIDADE CSC"),"TICKET CONCLUÍDO", "PENDENTE") -> TICKET CONCLUÍDO | J7: 1118329 | K7: 45691 | L7: RESPONSABILIDADE CSC | N7: 1338816/ 2124182 | O7: 45845 | P7: RESPONSABILIDADE CSC
B8: =_xlfn.XLOOKUP(E8,[1]Consolidado!$A:$A,[1]Consolidado!$D:$D) -> 45701 | C8: =IF(I8="TICKET CONCLUÍDO", "Concluído", IF(B8 < TODAY(), "Prazo estourado - " & TODAY()-B8 & " dias atrás", IF(TODAY()+30 < B8, "No prazo - faltam " & B8-TODAY() & " dias", IF(AND(B8-TODAY()<=29, B8-TODAY()>7), "Solicitar dados - faltam " & B8-TODAY() & " dias", IF(B8-TODAY()<=7, "Resolicitar - faltam " & B8-TODAY() & " dias", "Verificar") ) ) ) ) -> Concluído | D8: =_xlfn.XLOOKUP(E8,[1]Consolidado!$A:$A,[1]Consolidado!$AN:$AN) -> 0 | E8: REC74-LuizNunes-PE | F8: =_xlfn.XLOOKUP(E8,'SOLICITAÇÃO DE PAGAMENTO'!C:C,'SOLICITAÇÃO DE PAGAMENTO'!M:M) -> 603125 | G8: =_xlfn.XLOOKUP(E8,'SOLICITAÇÃO DE PAGAMENTO'!C:C,'SOLICITAÇÃO DE PAGAMENTO'!B:B) -> 1372 | H8: =_xlfn.XLOOKUP(G8,'SOLICITAÇÃO DE PAGAMENTO'!B:B,'SOLICITAÇÃO DE PAGAMENTO'!E:E) -> JORDANA | I8: =IF(AND(L8="RESPONSABILIDADE CSC",P8="RESPONSABILIDADE CSC"),"TICKET CONCLUÍDO", "PENDENTE") -> TICKET CONCLUÍDO | J8: 1338630 | K8: 45726 | L8: RESPONSABILIDADE CSC | N8: 1338590 | O8: 45726 | P8: RESPONSABILIDADE CSC
B9: =_xlfn.XLOOKUP(E9,[1]Consolidado!$A:$A,[1]Consolidado!$D:$D) -> 45719 | C9: =IF(I9="TICKET CONCLUÍDO", "Concluído", IF(B9 < TODAY(), "Prazo estourado - " & TODAY()-B9 & " dias atrás", IF(TODAY()+30 < B9, "No prazo - faltam " & B9-TODAY() & " dias", IF(AND(B9-TODAY()<=29, B9-TODAY()>7), "Solicitar dados - faltam " & B9-TODAY() & " dias", IF(B9-TODAY()<=7, "Resolicitar - faltam " & B9-TODAY() & " dias", "Verificar") ) ) ) ) -> Concluído | D9: =_xlfn.XLOOKUP(E9,[1]Consolidado!$A:$A,[1]Consolidado!$AN:$AN) -> 0 | E9: REC72-AntFalcao-PE | F9: =_xlfn.XLOOKUP(E9,'SOLICITAÇÃO DE PAGAMENTO'!C:C,'SOLICITAÇÃO DE PAGAMENTO'!M:M) -> 603254 | G9: =_xlfn.XLOOKUP(E9,'SOLICITAÇÃO DE PAGAMENTO'!C:C,'SOLICITAÇÃO DE PAGAMENTO'!B:B) -> 1432 | H9: =_xlfn.XLOOKUP(G9,'SOLICITAÇÃO DE PAGAMENTO'!B:B,'SOLICITAÇÃO DE PAGAMENTO'!E:E) -> JORDANA | I9: =IF(AND(L9="RESPONSABILIDADE CSC",P9="RESPONSABILIDADE CSC"),"TICKET CONCLUÍDO", "PENDENTE") -> TICKET CONCLUÍDO | J9: 1338879 | K9: 45726 | L9: RESPONSABILIDADE CSC | N9: 1338858 | O9: 45726 | P9: RESPONSABILIDADE CSC
B10: =_xlfn.XLOOKUP(E10,[1]Consolidado!$A:$A,[1]Consolidado!$D:$D) -> 45726 | C10: =IF(I10="TICKET CONCLUÍDO", "Concluído", IF(B10 < TODAY(), "Prazo estourado - " & TODAY()-B10 & " dias atrás", IF(TODAY()+30 < B10, "No prazo - faltam " & B10-TODAY() & " dias", IF(AND(B10-TODAY()<=29, B10-TODAY()>7), "Solicitar dados - faltam " & B10-TODAY() & " dias", IF(B10-TODAY()<=7, "Resolicitar - faltam " & B10-TODAY() & " dias", "Verificar") ) ) ) ) -> Concluído | D10: =_xlfn.XLOOKUP(E10,[1]Consolidado!$A:$A,[1]Consolidado!$AN:$AN) -> 0 | E10: BJS02-ManuelLeite-CE | F10: 603999 | G10: 1481 | H10: =_xlfn.XLOOKUP(G10,'SOLICITAÇÃO DE PAGAMENTO'!B:B,'SOLICITAÇÃO DE PAGAMENTO'!E:E) -> JORDANA | I10: =IF(AND(L10="RESPONSABILIDADE CSC",P10="RESPONSABILIDADE CSC"),"TICKET CONCLUÍDO", "PENDENTE") -> TICKET CONCLUÍDO | J10: 1381149 | L10: RESPONSABILIDADE CSC | M10: NECESSISDA DE ALTERAÇÃO DE TITULARIDADE | N10: 1381113 | P10: RESPONSABILIDADE CSC
B11: =_xlfn.XLOOKUP(E11,[1]Consolidado!$A:$A,[1]Consolidado!$D:$D) -> 45763 | C11: =IF(I11="TICKET CONCLUÍDO", "Concluído", IF(B11 < TODAY(), "Prazo estourado - " & TODAY()-B11 & " dias atrás", IF(TODAY()+30 < B11, "No prazo - faltam " & B11-TODAY() & " dias", IF(AND(B11-TODAY()<=29, B11-TODAY()>7), "Solicitar dados - faltam " & B11-TODAY() & " dias", IF(B11-TODAY()<=7, "Resolicitar - faltam " & B11-TODAY() & " dias", "Verificar") ) ) ) ) -> Concluído | D11: =_xlfn.XLOOKUP(E11,[1]Consolidado!$A:$A,[1]Consolidado!$AN:$AN) -> 0 | E11: RBR13-VilaIvonete-AC | F11: =_xlfn.XLOOKUP(E11,'SOLICITAÇÃO DE PAGAMENTO'!C:C,'SOLICITAÇÃO DE PAGAMENTO'!M:M) -> 603787 | G11: =_xlfn.XLOOKUP(E11,'SOLICITAÇÃO DE PAGAMENTO'!C:C,'SOLICITAÇÃO DE PAGAMENTO'!B:B) -> 1446 | H11: =_xlfn.XLOOKUP(G11,'SOLICITAÇÃO DE PAGAMENTO'!B:B,'SOLICITAÇÃO DE PAGAMENTO'!E:E) -> HENRIQUE | I11: =IF(AND(L11="RESPONSABILIDADE CSC",P11="RESPONSABILIDADE CSC"),"TICKET CONCLUÍDO", "PENDENTE") -> TICKET CONCLUÍDO | J11: 1664569 | K11: 45777 | L11: RESPONSABILIDADE CSC | M11: FATURA EM ABERTO PAGA | N11: 1664554 | O11: 45777 | P11: RESPONSABILIDADE CSC
B12: =_xlfn.XLOOKUP(E12,[1]Consolidado!$A:$A,[1]Consolidado!$D:$D) -> 45761 | C12: =IF(I12="TICKET CONCLUÍDO", "Concluído", IF(B12 < TODAY(), "Prazo estourado - " & TODAY()-B12 & " dias atrás", IF(TODAY()+30 < B12, "No prazo - faltam " & B12-TODAY() & " dias", IF(AND(B12-TODAY()<=29, B12-TODAY()>7), "Solicitar dados - faltam " & B12-TODAY() & " dias", IF(B12-TODAY()<=7, "Resolicitar - faltam " & B12-TODAY() & " dias", "Verificar") ) ) ) ) -> Concluído | D12: =_xlfn.XLOOKUP(E12,[1]Consolidado!$A:$A,[1]Consolidado!$AN:$AN) -> 0 | E12: MAC26-Aldebaran-AL | F12: =_xlfn.XLOOKUP(E12,'SOLICITAÇÃO DE PAGAMENTO'!C:C,'SOLICITAÇÃO DE PAGAMENTO'!M:M) -> 603265 | G12: =_xlfn.XLOOKUP(E12,'SOLICITAÇÃO DE PAGAMENTO'!C:C,'SOLICITAÇÃO DE PAGAMENTO'!B:B) -> 1381 | H12: =_xlfn.XLOOKUP(G12,'SOLICITAÇÃO DE PAGAMENTO'!B:B,'SOLICITAÇÃO DE PAGAMENTO'!E:E) -> ANDRE | I12: TICKET CONCLUÍDO | L12: AGUARDANDO INSTALAÇÃO DE POÇO ARTESIANO | N12: 1721945 | O12: 45785 | P12: =IF(N12="","AGUARDANDO DADOS","RESPONSABILIDADE CSC") -> RESPONSABILIDADE CSC
B13: =_xlfn.XLOOKUP(E13,[1]Consolidado!$A:$A,[1]Consolidado!$D:$D) -> 45860 | C13: =IF(I13="TICKET CONCLUÍDO", "Concluído", IF(B13 < TODAY(), "Prazo estourado - " & TODAY()-B13 & " dias atrás", IF(TODAY()+30 < B13, "No prazo - faltam " & B13-TODAY() & " dias", IF(AND(B13-TODAY()<=29, B13-TODAY()>7), "Solicitar dados - faltam " & B13-TODAY() & " dias", IF(B13-TODAY()<=7, "Resolicitar - faltam " & B13-TODAY() & " dias", "Verificar") ) ) ) ) -> Concluído | D13: =_xlfn.XLOOKUP(E13,[1]Consolidado!$A:$A,[1]Consolidado!$AN:$AN) -> 0 | E13: JPE50-FcoLeocadio-PB | F13: =_xlfn.XLOOKUP(E13,'SOLICITAÇÃO DE PAGAMENTO'!C:C,'SOLICITAÇÃO DE PAGAMENTO'!M:M) -> 604010 | G13: =_xlfn.XLOOKUP(E13,'SOLICITAÇÃO DE PAGAMENTO'!C:C,'SOLICITAÇÃO DE PAGAMENTO'!B:B) -> 1464 | H13: =_xlfn.XLOOKUP(G13,'SOLICITAÇÃO DE PAGAMENTO'!B:B,'SOLICITAÇÃO DE PAGAMENTO'!E:E) -> ANDRE | I13: =IF(AND(L13="RESPONSABILIDADE CSC",P13="RESPONSABILIDADE CSC"),"TICKET CONCLUÍDO", "PENDENTE") -> TICKET CONCLUÍDO | J13: 1566305 | K13: 45761 | L13: RESPONSABILIDADE CSC | N13: 1565928 | O13: 45761 | P13: RESPONSABILIDADE CSC
B14: =_xlfn.XLOOKUP(E14,[1]Consolidado!$A:$A,[1]Consolidado!$D:$D) -> 45797 | C14: =IF(I14="TICKET CONCLUÍDO", "Concluído", IF(B14 < TODAY(), "Prazo estourado - " & TODAY()-B14 & " dias atrás", IF(TODAY()+30 < B14, "No prazo - faltam " & B14-TODAY() & " dias", IF(AND(B14-TODAY()<=29, B14-TODAY()>7), "Solicitar dados - faltam " & B14-TODAY() & " dias", IF(B14-TODAY()<=7, "Resolicitar - faltam " & B14-TODAY() & " dias", "Verificar") ) ) ) ) -> Concluído | D14: =_xlfn.XLOOKUP(E14,[1]Consolidado!$A:$A,[1]Consolidado!$AN:$AN) -> 0 | E14: SAL64-ShBahia-BA | F14: 605289 | G14: 845 | H14: =_xlfn.XLOOKUP(G14,'SOLICITAÇÃO DE PAGAMENTO'!B:B,'SOLICITAÇÃO DE PAGAMENTO'!E:E) -> ANDRE | I14: =IF(AND(L14="RESPONSABILIDADE CSC",P14="RESPONSABILIDADE CSC"),"TICKET CONCLUÍDO", "PENDENTE") -> TICKET CONCLUÍDO | L14: RESPONSABILIDADE CSC | P14: RESPONSABILIDADE CSC
B15: =_xlfn.XLOOKUP(E15,[1]Consolidado!$A:$A,[1]Consolidado!$D:$D) -> 45813 | C15: =IF(I15="TICKET CONCLUÍDO", "Concluído", IF(B15 < TODAY(), "Prazo estourado - " & TODAY()-B15 & " dias atrás", IF(TODAY()+30 < B15, "No prazo - faltam " & B15-TODAY() & " dias", IF(AND(B15-TODAY()<=29, B15-TODAY()>7), "Solicitar dados - faltam " & B15-TODAY() & " dias", IF(B15-TODAY()<=7, "Resolicitar - faltam " & B15-TODAY() & " dias", "Verificar") ) ) ) ) -> Concluído | D15: =_xlfn.XLOOKUP(E15,[1]Consolidado!$A:$A,[1]Consolidado!$AN:$AN) -> 0 | E15: AGU01-AguaBranca-PI | F15: 604407 | G15: 1486 | H15: =_xlfn.XLOOKUP(G15,'SOLICITAÇÃO DE PAGAMENTO'!B:B,'SOLICITAÇÃO DE PAGAMENTO'!E:E) -> ANDRE | I15: =IF(AND(L15="RESPONSABILIDADE CSC",P15="RESPONSABILIDADE CSC"),"TICKET CONCLUÍDO", "PENDENTE") -> TICKET CONCLUÍDO | J15: 1825691 | K15: 45800 | L15: =IF(J15="","AGUARDANDO DADOS","RESPONSABILIDADE CSC") -> RESPONSABILIDADE CSC | M15: FATURA EM ABERTO PAGA | N15: 1825579 | O15: 45800 | P15: =IF(N15="","AGUARDANDO DADOS","RESPONSABILIDADE CSC") -> RESPONSABILIDADE CSC | Q15: FATURA EM ABERTO PAGA
B16: =_xlfn.XLOOKUP(E16,[1]Consolidado!$A:$A,[1]Consolidado!$D:$D) -> 45780 | C16: =IF(I16="TICKET CONCLUÍDO", "Concluído", IF(B16 < TODAY(), "Prazo estourado - " & TODAY()-B16 & " dias atrás", IF(TODAY()+30 < B16, "No prazo - faltam " & B16-TODAY() & " dias", IF(AND(B16-TODAY()<=29, B16-TODAY()>7), "Solicitar dados - faltam " & B16-TODAY() & " dias", IF(B16-TODAY()<=7, "Resolicitar - faltam " & B16-TODAY() & " dias", "Verificar") ) ) ) ) -> Concluído | D16: =_xlfn.XLOOKUP(E16,[1]Consolidado!$A:$A,[1]Consolidado!$AN:$AN) -> 0 | E16: TER31-CasteloPiaui-PI | F16: =_xlfn.XLOOKUP(E16,'SOLICITAÇÃO DE PAGAMENTO'!C:C,'SOLICITAÇÃO DE PAGAMENTO'!M:M) -> 603846 | G16: =_xlfn.XLOOKUP(E16,'SOLICITAÇÃO DE PAGAMENTO'!C:C,'SOLICITAÇÃO DE PAGAMENTO'!B:B) -> 1473 | H16: =_xlfn.XLOOKUP(G16,'SOLICITAÇÃO DE PAGAMENTO'!B:B,'SOLICITAÇÃO DE PAGAMENTO'!E:E) -> HENRIQUE | I16: =IF(AND(L16="RESPONSABILIDADE CSC",P16="RESPONSABILIDADE CSC"),"TICKET CONCLUÍDO", "PENDENTE") -> TICKET CONCLUÍDO | J16: 1679019 | K16: 45779 | L16: RESPONSABILIDADE CSC | N16: 1679405 | O16: 45779 | P16: RESPONSABILIDADE CSC
B17: =_xlfn.XLOOKUP(E17,[1]Consolidado!$A:$A,[1]Consolidado!$D:$D) -> 45796 | C17: =IF(I17="TICKET CONCLUÍDO", "Concluído", IF(B17 < TODAY(), "Prazo estourado - " & TODAY()-B17 & " dias atrás", IF(TODAY()+30 < B17, "No prazo - faltam " & B17-TODAY() & " dias", IF(AND(B17-TODAY()<=29, B17-TODAY()>7), "Solicitar dados - faltam " & B17-TODAY() & " dias", IF(B17-TODAY()<=7, "Resolicitar - faltam " & B17-TODAY() & " dias", "Verificar") ) ) ) ) -> Concluído | D17: =_xlfn.XLOOKUP(E17,[1]Consolidado!$A:$A,[1]Consolidado!$AN:$AN) -> 0 | E17: CGD23-TrêsBarras-MS | F17: =_xlfn.XLOOKUP(E17,'SOLICITAÇÃO DE PAGAMENTO'!C:C,'SOLICITAÇÃO DE PAGAMENTO'!M:M) -> 603320 | G17: =_xlfn.XLOOKUP(E17,'SOLICITAÇÃO DE PAGAMENTO'!C:C,'SOLICITAÇÃO DE PAGAMENTO'!B:B) -> 1483 | H17: =_xlfn.XLOOKUP(G17,'SOLICITAÇÃO DE PAGAMENTO'!B:B,'SOLICITAÇÃO DE PAGAMENTO'!E:E) -> ANDRE | I17: =IF(AND(L17="RESPONSABILIDADE CSC",P17="RESPONSABILIDADE CSC"),"TICKET CONCLUÍDO", "PENDENTE") -> TICKET CONCLUÍDO | J17: 1721816 | K17: 45785 | L17: =IF(J17="","AGUARDANDO DADOS","RESPONSABILIDADE CSC") -> RESPONSABILIDADE CSC | M17: FATURA EM ABERTO VENC 07/05/2025 (OBRAS) | N17: 1681574 | O17: 45779 | P17: =IF(N17="","AGUARDANDO DADOS","RESPONSABILIDADE CSC") -> RESPONSABILIDADE CSC | Q17: FATURA EM ABERTO PAGA
B18: =_xlfn.XLOOKUP(E18,[1]Consolidado!$A:$A,[1]Consolidado!$D:$D) -> 45796 | C18: =IF(I18="TICKET CONCLUÍDO", "Concluído", IF(B18 < TODAY(), "Prazo estourado - " & TODAY()-B18 & " dias atrás", IF(TODAY()+30 < B18, "No prazo - faltam " & B18-TODAY() & " dias", IF(AND(B18-TODAY()<=29, B18-TODAY()>7), "Solicitar dados - faltam " & B18-TODAY() & " dias", IF(B18-TODAY()<=7, "Resolicitar - faltam " & B18-TODAY() & " dias", "Verificar") ) ) ) ) -> Concluído | D18: =_xlfn.XLOOKUP(E18,[1]Consolidado!$A:$A,[1]Consolidado!$AN:$AN) -> 0 | E18: VAR06-JoaoPonce-MT | F18: =_xlfn.XLOOKUP(E18,'SOLICITAÇÃO DE PAGAMENTO'!C:C,'SOLICITAÇÃO DE PAGAMENTO'!M:M) -> 603908 | G18: =_xlfn.XLOOKUP(E18,'SOLICITAÇÃO DE PAGAMENTO'!C:C,'SOLICITAÇÃO DE PAGAMENTO'!B:B) -> 1455 | H18: =_xlfn.XLOOKUP(G18,'SOLICITAÇÃO DE PAGAMENTO'!B:B,'SOLICITAÇÃO DE PAGAMENTO'!E:E) -> JORDANA | I18: =IF(AND(L18="RESPONSABILIDADE CSC",P18="RESPONSABILIDADE CSC"),"TICKET CONCLUÍDO", "PENDENTE") -> TICKET CONCLUÍDO | J18: 1721727 | K18: 45785 | L18: =IF(J18="","AGUARDANDO DADOS","RESPONSABILIDADE CSC") -> RESPONSABILIDADE CSC | M18: FATURA EM ABERTO PAGA | N18: 1721700 | O18: 45785 | P18: =IF(N18="","AGUARDANDO DADOS","RESPONSABILIDADE CSC") -> RESPONSABILIDADE CSC
B19: =_xlfn.XLOOKUP(E19,[1]Consolidado!$A:$A,[1]Consolidado!$D:$D) -> 45810 | C19: =IF(I19="TICKET CONCLUÍDO", "Concluído", IF(B19 < TODAY(), "Prazo estourado - " & TODAY()-B19 & " dias atrás", IF(TODAY()+30 < B19, "No prazo - faltam " & B19-TODAY() & " dias", IF(AND(B19-TODAY()<=29, B19-TODAY()>7), "Solicitar dados - faltam " & B19-TODAY() & " dias", IF(B19-TODAY()<=7, "Resolicitar - faltam " & B19-TODAY() & " dias", "Verificar") ) ) ) ) -> Concluído | D19: =_xlfn.XLOOKUP(E19,[1]Consolidado!$A:$A,[1]Consolidado!$AN:$AN) -> 0 | E19: CRA05-CelAntLuiz-CE | F19: =_xlfn.XLOOKUP(E19,'SOLICITAÇÃO DE PAGAMENTO'!C:C,'SOLICITAÇÃO DE PAGAMENTO'!M:M) -> 603914 | G19: =_xlfn.XLOOKUP(E19,'SOLICITAÇÃO DE PAGAMENTO'!C:C,'SOLICITAÇÃO DE PAGAMENTO'!B:B) -> 1480 | H19: =_xlfn.XLOOKUP(G19,'SOLICITAÇÃO DE PAGAMENTO'!B:B,'SOLICITAÇÃO DE PAGAMENTO'!E:E) -> JORDANA | I19: =IF(AND(L19="RESPONSABILIDADE CSC",P19="RESPONSABILIDADE CSC"),"TICKET CONCLUÍDO", "PENDENTE") -> TICKET CONCLUÍDO | J19: 1824402 | K19: 45800 | L19: =IF(J19="","AGUARDANDO DADOS","RESPONSABILIDADE CSC") -> RESPONSABILIDADE CSC | N19: 2344147 | O19: 45881 | P19: =IF(N19="","AGUARDANDO DADOS","RESPONSABILIDADE CSC") -> RESPONSABILIDADE CSC | Q19: aguardando troca de titularidade, entender o motivo do atraso
B20: =_xlfn.XLOOKUP(E20,[1]Consolidado!$A:$A,[1]Consolidado!$D:$D) -> 45848 | C20: =IF(I20="TICKET CONCLUÍDO", "Concluído", IF(B20 < TODAY(), "Prazo estourado - " & TODAY()-B20 & " dias atrás", IF(TODAY()+30 < B20, "No prazo - faltam " & B20-TODAY() & " dias", IF(AND(B20-TODAY()<=29, B20-TODAY()>7), "Solicitar dados - faltam " & B20-TODAY() & " dias", IF(B20-TODAY()<=7, "Resolicitar - faltam " & B20-TODAY() & " dias", "Verificar") ) ) ) ) -> Concluído | D20: =_xlfn.XLOOKUP(E20,[1]Consolidado!$A:$A,[1]Consolidado!$AN:$AN) -> 0 | E20: TER32-15deNov-PI | F20: =_xlfn.XLOOKUP(E20,'SOLICITAÇÃO DE PAGAMENTO'!C:C,'SOLICITAÇÃO DE PAGAMENTO'!M:M) -> 604002 | G20: =_xlfn.XLOOKUP(E20,'SOLICITAÇÃO DE PAGAMENTO'!C:C,'SOLICITAÇÃO DE PAGAMENTO'!B:B) -> 1475 | H20: =_xlfn.XLOOKUP(G20,'SOLICITAÇÃO DE PAGAMENTO'!B:B,'SOLICITAÇÃO DE PAGAMENTO'!E:E) -> ANDRE | I20: =IF(AND(L20="RESPONSABILIDADE CSC",P20="RESPONSABILIDADE CSC"),"TICKET CONCLUÍDO", "PENDENTE") -> TICKET CONCLUÍDO | J20: 2080458 | K20: 45839 | L20: =IF(J20="","AGUARDANDO DADOS","RESPONSABILIDADE CSC") -> RESPONSABILIDADE CSC | N20: 2080508 | O20: 45839 | P20: =IF(N20="","AGUARDANDO DADOS","RESPONSABILIDADE CSC") -> RESPONSABILIDADE CSC
B21: =_xlfn.XLOOKUP(E21,[1]Consolidado!$A:$A,[1]Consolidado!$D:$D) -> 45835 | C21: =IF(I21="TICKET CONCLUÍDO", "Concluído", IF(B21 < TODAY(), "Prazo estourado - " & TODAY()-B21 & " dias atrás", IF(TODAY()+30 < B21, "No prazo - faltam " & B21-TODAY() & " dias", IF(AND(B21-TODAY()<=29, B21-TODAY()>7), "Solicitar dados - faltam " & B21-TODAY() & " dias", IF(B21-TODAY()<=7, "Resolicitar - faltam " & B21-TODAY() & " dias", "Verificar") ) ) ) ) -> Concluído | D21: =_xlfn.XLOOKUP(E21,[1]Consolidado!$A:$A,[1]Consolidado!$AN:$AN) -> 0 | E21: AQU03-BeachPark-CE | F21: =_xlfn.XLOOKUP(E21,'SOLICITAÇÃO DE PAGAMENTO'!C:C,'SOLICITAÇÃO DE PAGAMENTO'!M:M) -> 605638 | G21: =_xlfn.XLOOKUP(E21,'SOLICITAÇÃO DE PAGAMENTO'!C:C,'SOLICITAÇÃO DE PAGAMENTO'!B:B) -> 1485 | H21: =_xlfn.XLOOKUP(G21,'SOLICITAÇÃO DE PAGAMENTO'!B:B,'SOLICITAÇÃO DE PAGAMENTO'!E:E) -> JORDANA | I21: =IF(AND(L21="RESPONSABILIDADE CSC",P21="RESPONSABILIDADE CSC"),"TICKET CONCLUÍDO", "PENDENTE") -> TICKET CONCLUÍDO | L21: RESPONSABILIDADE CSC | P21: RESPONSABILIDADE CSC
B22: =_xlfn.XLOOKUP(E22,[1]Consolidado!$A:$A,[1]Consolidado!$D:$D) -> 45843 | C22: =IF(I22="TICKET CONCLUÍDO", "Concluído", IF(B22 < TODAY(), "Prazo estourado - " & TODAY()-B22 & " dias atrás", IF(TODAY()+30 < B22, "No prazo - faltam " & B22-TODAY() & " dias", IF(AND(B22-TODAY()<=29, B22-TODAY()>7), "Solicitar dados - faltam " & B22-TODAY() & " dias", IF(B22-TODAY()<=7, "Resolicitar - faltam " & B22-TODAY() & " dias", "Verificar") ) ) ) ) -> Concluído | D22: =_xlfn.XLOOKUP(E22,[1]Consolidado!$A:$A,[1]Consolidado!$AN:$AN) -> 0 | E22: CRU14-LeãoDourado-PE | F22: 603049 | G22: 1369 | H22: JORDANA | I22: =IF(AND(L22="RESPONSABILIDADE CSC",P22="RESPONSABILIDADE CSC"),"TICKET CONCLUÍDO", "PENDENTE") -> TICKET CONCLUÍDO | J22: 2069000 | K22: 45838 | L22: =IF(J22="","AGUARDANDO DADOS","RESPONSABILIDADE CSC") -> RESPONSABILIDADE CSC | N22: 2211965 | O22: 45859 | P22: =IF(N22="","AGUARDANDO DADOS","RESPONSABILIDADE CSC") -> RESPONSABILIDADE CSC | Q22: [16:41, 11/07/2025] Carina Alvo K: a concessionária, por questões sistêmicas, vai precisar alterar a conta contrato, inativando a existente (somente no sistema, e não fisicamente). Sendo assim, o pedido de troca da titularidade anterior foi cancelado. E uma solicitação de nova Conta Contrato será protocolada pelo Sílvio. [16:43, 11/07/2025] Carina Alvo K: Ele disse que esse novo cadastro será feito até sexta feira que vem, 18/07
B23: =_xlfn.XLOOKUP(E23,[1]Consolidado!$A:$A,[1]Consolidado!$D:$D) -> 45896 | C23: =IF(I23="TICKET CONCLUÍDO", "Concluído", IF(B23 < TODAY(), "Prazo estourado - " & TODAY()-B23 & " dias atrás", IF(TODAY()+30 < B23, "No prazo - faltam " & B23-TODAY() & " dias", IF(AND(B23-TODAY()<=29, B23-TODAY()>7), "Solicitar dados - faltam " & B23-TODAY() & " dias", IF(B23-TODAY()<=7, "Resolicitar - faltam " & B23-TODAY() & " dias", "Verificar") ) ) ) ) -> Concluído | D23: =_xlfn.XLOOKUP(E23,[1]Consolidado!$A:$A,[1]Consolidado!$AN:$AN) -> 0 | E23: SLU79-Cajazeiras-MA | F23: =_xlfn.XLOOKUP(E23,'SOLICITAÇÃO DE PAGAMENTO'!C:C,'SOLICITAÇÃO DE PAGAMENTO'!M:M) -> 603464 | G23: =_xlfn.XLOOKUP(E23,'SOLICITAÇÃO DE PAGAMENTO'!C:C,'SOLICITAÇÃO DE PAGAMENTO'!B:B,"") -> 1498 | H23: HENRIQUE | I23: =IF(AND(L23="RESPONSABILIDADE CSC",P23="RESPONSABILIDADE CSC"),"TICKET CONCLUÍDO", "PENDENTE") -> TICKET CONCLUÍDO | J23: 2190263 | K23: 45855 | L23: =IF(J23="","AGUARDANDO DADOS","RESPONSABILIDADE CSC") -> RESPONSABILIDADE CSC | M23: solicitei dados cadastrais aguardando | N23: 2190230 | O23: 45855 | P23: =IF(N23="","AGUARDANDO DADOS","RESPONSABILIDADE CSC") -> RESPONSABILIDADE CSC | Q23: solicitei dados cadastrais aguardando
B24: =_xlfn.XLOOKUP(E24,[1]Consolidado!$A:$A,[1]Consolidado!$D:$D) -> 45874 | C24: =IF(I24="TICKET CONCLUÍDO", "Concluído", IF(B24 < TODAY(), "Prazo estourado - " & TODAY()-B24 & " dias atrás", IF(TODAY()+30 < B24, "No prazo - faltam " & B24-TODAY() & " dias", IF(AND(B24-TODAY()<=29, B24-TODAY()>7), "Solicitar dados - faltam " & B24-TODAY() & " dias", IF(B24-TODAY()<=7, "Resolicitar - faltam " & B24-TODAY() & " dias", "Verificar") ) ) ) ) -> Concluído | D24: =_xlfn.XLOOKUP(E24,[1]Consolidado!$A:$A,[1]Consolidado!$AN:$AN) -> 0 | E24: SLU78-JoaoPessoa-MA | F24: =_xlfn.XLOOKUP(E24,'SOLICITAÇÃO DE PAGAMENTO'!C:C,'SOLICITAÇÃO DE PAGAMENTO'!M:M) -> 603440 | G24: 1439 | H24: HENRIQUE | I24: =IF(AND(L24="RESPONSABILIDADE CSC",P24="RESPONSABILIDADE CSC"),"TICKET CONCLUÍDO", "PENDENTE") -> TICKET CONCLUÍDO | J24: 2193601 | K24: 45856 | L24: =IF(J24="","AGUARDANDO DADOS","RESPONSABILIDADE CSC") -> RESPONSABILIDADE CSC | M24: solicitei dados cadastrais aguardando | N24: 2193568 | O24: 45856 | P24: =IF(N24="","AGUARDANDO DADOS","RESPONSABILIDADE CSC") -> RESPONSABILIDADE CSC | Q24: solicitei dados cadastrais aguardando
B25: =_xlfn.XLOOKUP(E25,[1]Consolidado!$A:$A,[1]Consolidado!$D:$D) -> 45889 | C25: =IF(I25="TICKET CONCLUÍDO", "Concluído", IF(B25 < TODAY(), "Prazo estourado - " & TODAY()-B25 & " dias atrás", IF(TODAY()+30 < B25, "No prazo - faltam " & B25-TODAY() & " dias", IF(AND(B25-TODAY()<=29, B25-TODAY()>7), "Solicitar dados - faltam " & B25-TODAY() & " dias", IF(B25-TODAY()<=7, "Resolicitar - faltam " & B25-TODAY() & " dias", "Verificar") ) ) ) ) -> Concluído | D25: =_xlfn.XLOOKUP(E25,[1]Consolidado!$A:$A,[1]Consolidado!$AN:$AN) -> 0 | E25: AGA09-SadocCorrei-TO | F25: =_xlfn.XLOOKUP(E25,'SOLICITAÇÃO DE PAGAMENTO'!C:C,'SOLICITAÇÃO DE PAGAMENTO'!M:M) -> 605482 | G25: 1489 | H25: ANDRE | I25: =IF(AND(L25="RESPONSABILIDADE CSC",P25="RESPONSABILIDADE CSC"),"TICKET CONCLUÍDO", "PENDENTE") -> TICKET CONCLUÍDO | J25: 2271086 | K25: 45869 | L25: =IF(J25="","AGUARDANDO DADOS","RESPONSABILIDADE CSC") -> RESPONSABILIDADE CSC | N25: 2271026 | O25: 45869 | P25: =IF(N25="","AGUARDANDO DADOS","RESPONSABILIDADE CSC") -> RESPONSABILIDADE CSC
B26: =_xlfn.XLOOKUP(E26,[1]Consolidado!$A:$A,[1]Consolidado!$D:$D) -> 45899 | C26: =IF(I26="TICKET CONCLUÍDO", "Concluído", IF(B26 < TODAY(), "Prazo estourado - " & TODAY()-B26 & " dias atrás", IF(TODAY()+30 < B26, "No prazo - faltam " & B26-TODAY() & " dias", IF(AND(B26-TODAY()<=29, B26-TODAY()>7), "Solicitar dados - faltam " & B26-TODAY() & " dias", IF(B26-TODAY()<=7, "Resolicitar - faltam " & B26-TODAY() & " dias", "Verificar") ) ) ) ) -> Concluído | D26: =_xlfn.XLOOKUP(E26,[1]Consolidado!$A:$A,[1]Consolidado!$AN:$AN) -> 0 | E26: ALT03-Brasilia-PA | F26: 603167 | G26: 1492 | H26: HENRIQUE | I26: =IF(AND(L26="RESPONSABILIDADE CSC",P26="RESPONSABILIDADE CSC"),"TICKET CONCLUÍDO", "PENDENTE") -> TICKET CONCLUÍDO | L26: RESPONSABILIDADE CSC | M26: Não haverá cobrança | N26: 2274886 | O26: 45869 | P26: =IF(N26="","AGUARDANDO DADOS","RESPONSABILIDADE CSC") -> RESPONSABILIDADE CSC
B27: =_xlfn.XLOOKUP(E27,[1]Consolidado!$A:$A,[1]Consolidado!$D:$D) -> 45927 | C27: =IF(I27="TICKET CONCLUÍDO", "Concluído", IF(B27 < TODAY(), "Prazo estourado - " & TODAY()-B27 & " dias atrás", IF(TODAY()+30 < B27, "No prazo - faltam " & B27-TODAY() & " dias", IF(AND(B27-TODAY()<=29, B27-TODAY()>7), "Solicitar dados - faltam " & B27-TODAY() & " dias", IF(B27-TODAY()<=7, "Resolicitar - faltam " & B27-TODAY() & " dias", "Verificar") ) ) ) ) -> Concluído | D27: =_xlfn.XLOOKUP(E27,[1]Consolidado!$A:$A,[1]Consolidado!$AN:$AN) -> Atraso emissão da I.E. | E27: CGR08-Quarenta-PB | F27: =_xlfn.XLOOKUP(E27,'SOLICITAÇÃO DE PAGAMENTO'!C:C,'SOLICITAÇÃO DE PAGAMENTO'!M:M) -> 603123 | G27: =_xlfn.XLOOKUP(E27,'SOLICITAÇÃO DE PAGAMENTO'!C:C,'SOLICITAÇÃO DE PAGAMENTO'!B:B,"") -> 1459 | H27: =_xlfn.XLOOKUP(G27,'SOLICITAÇÃO DE PAGAMENTO'!B:B,'SOLICITAÇÃO DE PAGAMENTO'!E:E) -> ANDRE | I27: =IF(AND(L27="RESPONSABILIDADE CSC",P27="RESPONSABILIDADE CSC"),"TICKET CONCLUÍDO", "PENDENTE") -> TICKET CONCLUÍDO | J27: 2436969 | K27: 45896 | L27: =IF(J27="","AGUARDANDO DADOS","RESPONSABILIDADE CSC") -> RESPONSABILIDADE CSC | N27: 2751482 | O27: 45938 | P27: =IF(N27="","AGUARDANDO DADOS","RESPONSABILIDADE CSC") -> RESPONSABILIDADE CSC
B28: =_xlfn.XLOOKUP(E28,[1]Consolidado!$A:$A,[1]Consolidado!$D:$D) -> 45876 | C28: =IF(I28="TICKET CONCLUÍDO", "Concluído", IF(B28 < TODAY(), "Prazo estourado - " & TODAY()-B28 & " dias atrás", IF(TODAY()+30 < B28, "No prazo - faltam " & B28-TODAY() & " dias", IF(AND(B28-TODAY()<=29, B28-TODAY()>7), "Solicitar dados - faltam " & B28-TODAY() & " dias", IF(B28-TODAY()<=7, "Resolicitar - faltam " & B28-TODAY() & " dias", "Verificar") ) ) ) ) -> Concluído | D28: =_xlfn.XLOOKUP(E28,[1]Consolidado!$A:$A,[1]Consolidado!$AN:$AN) -> 0 | E28: FOR192-LesteOeste-CE | F28: =_xlfn.XLOOKUP(E28,'SOLICITAÇÃO DE PAGAMENTO'!C:C,'SOLICITAÇÃO DE PAGAMENTO'!M:M) -> 605741 | G28: =_xlfn.XLOOKUP(E28,'SOLICITAÇÃO DE PAGAMENTO'!C:C,'SOLICITAÇÃO DE PAGAMENTO'!B:B,"") -> 1494 | H28: =_xlfn.XLOOKUP(G28,'SOLICITAÇÃO DE PAGAMENTO'!B:B,'SOLICITAÇÃO DE PAGAMENTO'!E:E,"") -> JORDANA | I28: =IF(AND(L28="RESPONSABILIDADE CSC",P28="RESPONSABILIDADE CSC"),"TICKET CONCLUÍDO", "PENDENTE") -> TICKET CONCLUÍDO | L28: RESPONSABILIDADE CSC | M28: Consumo via poço | N28: 2385189 | O28: 19//08/2025 | P28: =IF(N28="","AGUARDANDO DADOS","RESPONSABILIDADE CSC") -> RESPONSABILIDADE CSC | Q28: solicitei dados cadastrais aguardando
B29: =_xlfn.XLOOKUP(E29,[1]Consolidado!$A:$A,[1]Consolidado!$D:$D) -> 45918 | C29: =IF(I29="TICKET CONCLUÍDO", "Concluído", IF(B29 < TODAY(), "Prazo estourado - " & TODAY()-B29 & " dias atrás", IF(TODAY()+30 < B29, "No prazo - faltam " & B29-TODAY() & " dias", IF(AND(B29-TODAY()<=29, B29-TODAY()>7), "Solicitar dados - faltam " & B29-TODAY() & " dias", IF(B29-TODAY()<=7, "Resolicitar - faltam " & B29-TODAY() & " dias", "Verificar") ) ) ) ) -> Concluído | D29: =_xlfn.XLOOKUP(E29,[1]Consolidado!$A:$A,[1]Consolidado!$AN:$AN) -> Atrasou I.E para envio de mercadoria / Atraso no envio de fardamento | E29: CHP02-15Novembro-MA | F29: =_xlfn.XLOOKUP(E29,'SOLICITAÇÃO DE PAGAMENTO'!C:C,'SOLICITAÇÃO DE PAGAMENTO'!M:M) -> 604328 | G29: =_xlfn.XLOOKUP(E29,'SOLICITAÇÃO DE PAGAMENTO'!C:C,'SOLICITAÇÃO DE PAGAMENTO'!B:B,"") -> 1496 | H29: =_xlfn.XLOOKUP(G29,'SOLICITAÇÃO DE PAGAMENTO'!B:B,'SOLICITAÇÃO DE PAGAMENTO'!E:E,"") -> HENRIQUE | I29: =IF(AND(L29="RESPONSABILIDADE CSC",P29="RESPONSABILIDADE CSC"),"TICKET CONCLUÍDO", "PENDENTE") -> TICKET CONCLUÍDO | J29: 2404923 | K29: 45891 | L29: =IF(J29="","AGUARDANDO DADOS","RESPONSABILIDADE CSC") -> RESPONSABILIDADE CSC | N29: 2404905 | O29: 45891 | P29: =IF(N29="","AGUARDANDO DADOS","RESPONSABILIDADE CSC") -> RESPONSABILIDADE CSC
B30: =_xlfn.XLOOKUP(E30,[1]Consolidado!$A:$A,[1]Consolidado!$D:$D) -> 45917 | C30: =IF(I30="TICKET CONCLUÍDO", "Concluído", IF(B30 < TODAY(), "Prazo estourado - " & TODAY()-B30 & " dias atrás", IF(TODAY()+30 < B30, "No prazo - faltam " & B30-TODAY() & " dias", IF(AND(B30-TODAY()<=29, B30-TODAY()>7), "Solicitar dados - faltam " & B30-TODAY() & " dias", IF(B30-TODAY()<=7, "Resolicitar - faltam " & B30-TODAY() & " dias", "Verificar") ) ) ) ) -> Concluído | D30: =_xlfn.XLOOKUP(E30,[1]Consolidado!$A:$A,[1]Consolidado!$AN:$AN) -> Atraso na contratação farma que gerou atraso nos Alvarás. Erro na inclinação de obra vão resolver após abertura | E30: PRB04-PA160-PA | F30: =_xlfn.XLOOKUP(E30,'SOLICITAÇÃO DE PAGAMENTO'!C:C,'SOLICITAÇÃO DE PAGAMENTO'!M:M) -> 605480 | G30: =_xlfn.XLOOKUP(E30,'SOLICITAÇÃO DE PAGAMENTO'!C:C,'SOLICITAÇÃO DE PAGAMENTO'!B:B,"") -> 1497 | H30: =_xlfn.XLOOKUP(G30,'SOLICITAÇÃO DE PAGAMENTO'!B:B,'SOLICITAÇÃO DE PAGAMENTO'!E:E,"") -> HENRIQUE | I30: =IF(AND(L30="RESPONSABILIDADE CSC",P30="RESPONSABILIDADE CSC"),"TICKET CONCLUÍDO", "PENDENTE") -> TICKET CONCLUÍDO | J30: 2401951 | K30: 45890 | L30: =IF(J30="","AGUARDANDO DADOS","RESPONSABILIDADE CSC") -> RESPONSABILIDADE CSC | N30: 2486560 | O30: 45903 | P30: =IF(N30="","AGUARDANDO DADOS","RESPONSABILIDADE CSC") -> RESPONSABILIDADE CSC
B31: =_xlfn.XLOOKUP(E31,[1]Consolidado!$A:$A,[1]Consolidado!$D:$D) -> 45940 | C31: =IF(I31="TICKET CONCLUÍDO", "Concluído", IF(B31 < TODAY(), "Prazo estourado - " & TODAY()-B31 & " dias atrás", IF(TODAY()+30 < B31, "No prazo - faltam " & B31-TODAY() & " dias", IF(AND(B31-TODAY()<=29, B31-TODAY()>7), "Solicitar dados - faltam " & B31-TODAY() & " dias", IF(B31-TODAY()<=7, "Resolicitar - faltam " & B31-TODAY() & " dias", "Verificar") ) ) ) ) -> Concluído | D31: =_xlfn.XLOOKUP(E31,[1]Consolidado!$A:$A,[1]Consolidado!$AN:$AN) -> controlado liberado 22/09 / Emissão do Alvará de funcionamento segurou a abertura. Pbra executada em desacordo com o projeto aprovado. Atraso significativo na entrega de documentação | E31: TER30-Aeroporto-PI | F31: =_xlfn.XLOOKUP(E31,'SOLICITAÇÃO DE PAGAMENTO'!C:C,'SOLICITAÇÃO DE PAGAMENTO'!M:M) -> 602884 | G31: =_xlfn.XLOOKUP(E31,'SOLICITAÇÃO DE PAGAMENTO'!C:C,'SOLICITAÇÃO DE PAGAMENTO'!B:B,"") -> 1428 | H31: =_xlfn.XLOOKUP(G31,'SOLICITAÇÃO DE PAGAMENTO'!B:B,'SOLICITAÇÃO DE PAGAMENTO'!E:E,"") -> ANDRE | I31: =IF(AND(L31="RESPONSABILIDADE CSC",P31="RESPONSABILIDADE CSC"),"TICKET CONCLUÍDO", "PENDENTE") -> TICKET CONCLUÍDO | J31: 2760018 | K31: 45939 | L31: =IF(J31="","AGUARDANDO DADOS","RESPONSABILIDADE CSC") -> RESPONSABILIDADE CSC | N31: 2759982 | O31: 45939 | P31: =IF(N31="","AGUARDANDO DADOS","RESPONSABILIDADE CSC") -> RESPONSABILIDADE CSC
B32: =_xlfn.XLOOKUP(E32,[1]Consolidado!$A:$A,[1]Consolidado!$D:$D) -> 45976 | C32: =IF(I32="TICKET CONCLUÍDO", "Concluído", IF(B32 < TODAY(), "Prazo estourado - " & TODAY()-B32 & " dias atrás", IF(TODAY()+30 < B32, "No prazo - faltam " & B32-TODAY() & " dias", IF(AND(B32-TODAY()<=29, B32-TODAY()>7), "Solicitar dados - faltam " & B32-TODAY() & " dias", IF(B32-TODAY()<=7, "Resolicitar - faltam " & B32-TODAY() & " dias", "Verificar") ) ) ) ) -> Concluído | D32: =_xlfn.XLOOKUP(E32,[1]Consolidado!$A:$A,[1]Consolidado!$AN:$AN) -> vistoria de vigilância | E32: SLU75-Holandeses-MA | F32: =_xlfn.XLOOKUP(E32,'SOLICITAÇÃO DE PAGAMENTO'!C:C,'SOLICITAÇÃO DE PAGAMENTO'!M:M) -> 603852 | G32: =_xlfn.XLOOKUP(E32,'SOLICITAÇÃO DE PAGAMENTO'!C:C,'SOLICITAÇÃO DE PAGAMENTO'!B:B,"") -> 1476 | H32: =_xlfn.XLOOKUP(G32,'SOLICITAÇÃO DE PAGAMENTO'!B:B,'SOLICITAÇÃO DE PAGAMENTO'!E:E,"") -> HENRIQUE | I32: =IF(AND(L32="RESPONSABILIDADE CSC",P32="RESPONSABILIDADE CSC"),"TICKET CONCLUÍDO", "PENDENTE") -> TICKET CONCLUÍDO | J32: 3048009 | K32: 45973 | L32: =IF(J32="","AGUARDANDO DADOS","RESPONSABILIDADE CSC") -> RESPONSABILIDADE CSC | N32: 3048039 | O32: 45973 | P32: =IF(N32="","AGUARDANDO DADOS","RESPONSABILIDADE CSC") -> RESPONSABILIDADE CSC | Q32: AGUARDANDO PADRAO 12.10
B33: =_xlfn.XLOOKUP(E33,[1]Consolidado!$A:$A,[1]Consolidado!$D:$D) -> 46155 | C33: =IF(I33="TICKET CONCLUÍDO", "Concluído", IF(B33 < TODAY(), "Prazo estourado - " & TODAY()-B33 & " dias atrás", IF(TODAY()+30 < B33, "No prazo - faltam " & B33-TODAY() & " dias", IF(AND(B33-TODAY()<=29, B33-TODAY()>7), "Solicitar dados - faltam " & B33-TODAY() & " dias", IF(B33-TODAY()<=7, "Resolicitar - faltam " & B33-TODAY() & " dias", "Verificar") ) ) ) ) -> No prazo - faltam 140 dias | D33: =_xlfn.XLOOKUP(E33,[1]Consolidado!$A:$A,[1]Consolidado!$AN:$AN) -> 0 | E33: SLU83-JAlbuquerqu-MA | F33: =_xlfn.XLOOKUP(E33,'SOLICITAÇÃO DE PAGAMENTO'!C:C,'SOLICITAÇÃO DE PAGAMENTO'!M:M) -> #N/A | G33: =_xlfn.XLOOKUP(E33,'SOLICITAÇÃO DE PAGAMENTO'!C:C,'SOLICITAÇÃO DE PAGAMENTO'!B:B,"") | H33: =_xlfn.XLOOKUP(G33,'SOLICITAÇÃO DE PAGAMENTO'!B:B,'SOLICITAÇÃO DE PAGAMENTO'!E:E,"") | I33: =IF(AND(L33="RESPONSABILIDADE CSC",P33="RESPONSABILIDADE CSC"),"TICKET CONCLUÍDO", "PENDENTE") -> PENDENTE | L33: =IF(J33="","AGUARDANDO DADOS","RESPONSABILIDADE CSC") -> AGUARDANDO DADOS | P33: =IF(N33="","AGUARDANDO DADOS","RESPONSABILIDADE CSC") -> AGUARDANDO DADOS
B34: =_xlfn.XLOOKUP(E34,[1]Consolidado!$A:$A,[1]Consolidado!$D:$D) -> 45979 | C34: =IF(I34="TICKET CONCLUÍDO", "Concluído", IF(B34 < TODAY(), "Prazo estourado - " & TODAY()-B34 & " dias atrás", IF(TODAY()+30 < B34, "No prazo - faltam " & B34-TODAY() & " dias", IF(AND(B34-TODAY()<=29, B34-TODAY()>7), "Solicitar dados - faltam " & B34-TODAY() & " dias", IF(B34-TODAY()<=7, "Resolicitar - faltam " & B34-TODAY() & " dias", "Verificar") ) ) ) ) -> Concluído | D34: =_xlfn.XLOOKUP(E34,[1]Consolidado!$A:$A,[1]Consolidado!$AN:$AN) -> Pendente contrato de resíduos |jurídico | E34: BOV14-Jprimavera-RR | F34: =_xlfn.XLOOKUP(E34,'SOLICITAÇÃO DE PAGAMENTO'!C:C,'SOLICITAÇÃO DE PAGAMENTO'!M:M) -> 604304 | G34: =_xlfn.XLOOKUP(E34,'SOLICITAÇÃO DE PAGAMENTO'!C:C,'SOLICITAÇÃO DE PAGAMENTO'!B:B,"") -> 1487 | H34: =_xlfn.XLOOKUP(G34,'SOLICITAÇÃO DE PAGAMENTO'!B:B,'SOLICITAÇÃO DE PAGAMENTO'!E:E,"") -> HENRIQUE | I34: =IF(AND(L34="RESPONSABILIDADE CSC",P34="RESPONSABILIDADE CSC"),"TICKET CONCLUÍDO", "PENDENTE") -> TICKET CONCLUÍDO | J34: 2728371 | K34: 45936 | L34: =IF(J34="","AGUARDANDO DADOS","RESPONSABILIDADE CSC") -> RESPONSABILIDADE CSC | N34: 2728403 | O34: 45936 | P34: =IF(N34="","AGUARDANDO DADOS","RESPONSABILIDADE CSC") -> RESPONSABILIDADE CSC
B35: =_xlfn.XLOOKUP(E35,[1]Consolidado!$A:$A,[1]Consolidado!$D:$D) -> 46155 | C35: =IF(I35="TICKET CONCLUÍDO", "Concluído", IF(B35 < TODAY(), "Prazo estourado - " & TODAY()-B35 & " dias atrás", IF(TODAY()+30 < B35, "No prazo - faltam " & B35-TODAY() & " dias", IF(AND(B35-TODAY()<=29, B35-TODAY()>7), "Solicitar dados - faltam " & B35-TODAY() & " dias", IF(B35-TODAY()<=7, "Resolicitar - faltam " & B35-TODAY() & " dias", "Verificar") ) ) ) ) -> No prazo - faltam 140 dias | D35: =_xlfn.XLOOKUP(E35,[1]Consolidado!$A:$A,[1]Consolidado!$AN:$AN) -> 0 | E35: PAR05-RosaFernandes-RN | F35: =_xlfn.XLOOKUP(E35,'SOLICITAÇÃO DE PAGAMENTO'!C:C,'SOLICITAÇÃO DE PAGAMENTO'!M:M) -> #N/A | G35: =_xlfn.XLOOKUP(E35,'SOLICITAÇÃO DE PAGAMENTO'!C:C,'SOLICITAÇÃO DE PAGAMENTO'!B:B,"") | H35: =_xlfn.XLOOKUP(G35,'SOLICITAÇÃO DE PAGAMENTO'!B:B,'SOLICITAÇÃO DE PAGAMENTO'!E:E,"") | I35: =IF(AND(L35="RESPONSABILIDADE CSC",P35="RESPONSABILIDADE CSC"),"TICKET CONCLUÍDO", "PENDENTE") -> PENDENTE | L35: =IF(J35="","AGUARDANDO DADOS","RESPONSABILIDADE CSC") -> AGUARDANDO DADOS | P35: =IF(N35="","AGUARDANDO DADOS","RESPONSABILIDADE CSC") -> AGUARDANDO DADOS
B36: =_xlfn.XLOOKUP(E36,[1]Consolidado!$A:$A,[1]Consolidado!$D:$D) -> 0 | C36: =IF(I36="TICKET CONCLUÍDO", "Concluído", IF(B36 < TODAY(), "Prazo estourado - " & TODAY()-B36 & " dias atrás", IF(TODAY()+30 < B36, "No prazo - faltam " & B36-TODAY() & " dias", IF(AND(B36-TODAY()<=29, B36-TODAY()>7), "Solicitar dados - faltam " & B36-TODAY() & " dias", IF(B36-TODAY()<=7, "Resolicitar - faltam " & B36-TODAY() & " dias", "Verificar") ) ) ) ) -> Prazo estourado - 46015 dias atrás | D36: =_xlfn.XLOOKUP(E36,[1]Consolidado!$A:$A,[1]Consolidado!$AN:$AN) -> 0 | E36: FOR190-CelCarval2-CE | F36: =_xlfn.XLOOKUP(E36,'SOLICITAÇÃO DE PAGAMENTO'!C:C,'SOLICITAÇÃO DE PAGAMENTO'!M:M) -> #N/A | G36: =_xlfn.XLOOKUP(E36,'SOLICITAÇÃO DE PAGAMENTO'!C:C,'SOLICITAÇÃO DE PAGAMENTO'!B:B,"") | H36: =_xlfn.XLOOKUP(G36,'SOLICITAÇÃO DE PAGAMENTO'!B:B,'SOLICITAÇÃO DE PAGAMENTO'!E:E,"") | I36: =IF(AND(L36="RESPONSABILIDADE CSC",P36="RESPONSABILIDADE CSC"),"TICKET CONCLUÍDO", "PENDENTE") -> PENDENTE | L36: =IF(J36="","AGUARDANDO DADOS","RESPONSABILIDADE CSC") -> AGUARDANDO DADOS | P36: =IF(N36="","AGUARDANDO DADOS","RESPONSABILIDADE CSC") -> AGUARDANDO DADOS
B37: =_xlfn.XLOOKUP(E37,[1]Consolidado!$A:$A,[1]Consolidado!$D:$D) -> 46007 | C37: =IF(I37="TICKET CONCLUÍDO", "Concluído", IF(B37 < TODAY(), "Prazo estourado - " & TODAY()-B37 & " dias atrás", IF(TODAY()+30 < B37, "No prazo - faltam " & B37-TODAY() & " dias", IF(AND(B37-TODAY()<=29, B37-TODAY()>7), "Solicitar dados - faltam " & B37-TODAY() & " dias", IF(B37-TODAY()<=7, "Resolicitar - faltam " & B37-TODAY() & " dias", "Verificar") ) ) ) ) -> Concluído | D37: =_xlfn.XLOOKUP(E37,[1]Consolidado!$A:$A,[1]Consolidado!$AN:$AN) -> 0 | E37: APG02-Independenc-GO | F37: =_xlfn.XLOOKUP(E37,'SOLICITAÇÃO DE PAGAMENTO'!C:C,'SOLICITAÇÃO DE PAGAMENTO'!M:M) -> 602910 | G37: =_xlfn.XLOOKUP(E37,'SOLICITAÇÃO DE PAGAMENTO'!C:C,'SOLICITAÇÃO DE PAGAMENTO'!B:B,"") -> 1499 | H37: ANDRE | I37: =IF(AND(L37="RESPONSABILIDADE CSC",P37="RESPONSABILIDADE CSC"),"TICKET CONCLUÍDO", "PENDENTE") -> TICKET CONCLUÍDO | J37: 3230864 | K37: 45994 | L37: =IF(J37="","AGUARDANDO DADOS","RESPONSABILIDADE CSC") -> RESPONSABILIDADE CSC | N37: 3231171 | O37: 45994 | P37: =IF(N37="","AGUARDANDO DADOS","RESPONSABILIDADE CSC") -> RESPONSABILIDADE CSC
B38: =_xlfn.XLOOKUP(E38,[1]Consolidado!$A:$A,[1]Consolidado!$D:$D) -> 46057 | C38: =IF(I38="TICKET CONCLUÍDO", "Concluído", IF(B38 < TODAY(), "Prazo estourado - " & TODAY()-B38 & " dias atrás", IF(TODAY()+30 < B38, "No prazo - faltam " & B38-TODAY() & " dias", IF(AND(B38-TODAY()<=29, B38-TODAY()>7), "Solicitar dados - faltam " & B38-TODAY() & " dias", IF(B38-TODAY()<=7, "Resolicitar - faltam " & B38-TODAY() & " dias", "Verificar") ) ) ) ) -> No prazo - faltam 42 dias | D38: =_xlfn.XLOOKUP(E38,[1]Consolidado!$A:$A,[1]Consolidado!$AN:$AN) -> 0 | E38: GOI23-FeirSantana-GO | F38: =_xlfn.XLOOKUP(E38,'SOLICITAÇÃO DE PAGAMENTO'!C:C,'SOLICITAÇÃO DE PAGAMENTO'!M:M) -> #N/A | G38: =_xlfn.XLOOKUP(E38,'SOLICITAÇÃO DE PAGAMENTO'!C:C,'SOLICITAÇÃO DE PAGAMENTO'!B:B,"") | H38: =_xlfn.XLOOKUP(G38,'SOLICITAÇÃO DE PAGAMENTO'!B:B,'SOLICITAÇÃO DE PAGAMENTO'!E:E,"") | I38: =IF(AND(L38="RESPONSABILIDADE CSC",P38="RESPONSABILIDADE CSC"),"TICKET CONCLUÍDO", "PENDENTE") -> PENDENTE | L38: =IF(J38="","AGUARDANDO DADOS","RESPONSABILIDADE CSC") -> AGUARDANDO DADOS | P38: =IF(N38="","AGUARDANDO DADOS","RESPONSABILIDADE CSC") -> AGUARDANDO DADOS
B39: =_xlfn.XLOOKUP(E39,[1]Consolidado!$A:$A,[1]Consolidado!$D:$D) -> 0 | C39: =IF(I39="TICKET CONCLUÍDO", "Concluído", IF(B39 < TODAY(), "Prazo estourado - " & TODAY()-B39 & " dias atrás", IF(TODAY()+30 < B39, "No prazo - faltam " & B39-TODAY() & " dias", IF(AND(B39-TODAY()<=29, B39-TODAY()>7), "Solicitar dados - faltam " & B39-TODAY() & " dias", IF(B39-TODAY()<=7, "Resolicitar - faltam " & B39-TODAY() & " dias", "Verificar") ) ) ) ) -> Prazo estourado - 46015 dias atrás | D39: =_xlfn.XLOOKUP(E39,[1]Consolidado!$A:$A,[1]Consolidado!$AN:$AN) -> 0 | E39: DRD03-JoaqmTeixei-MS | F39: =_xlfn.XLOOKUP(E39,'SOLICITAÇÃO DE PAGAMENTO'!C:C,'SOLICITAÇÃO DE PAGAMENTO'!M:M) -> #N/A | G39: =_xlfn.XLOOKUP(E39,'SOLICITAÇÃO DE PAGAMENTO'!C:C,'SOLICITAÇÃO DE PAGAMENTO'!B:B,"") | H39: =_xlfn.XLOOKUP(G39,'SOLICITAÇÃO DE PAGAMENTO'!B:B,'SOLICITAÇÃO DE PAGAMENTO'!E:E,"") | I39: =IF(AND(L39="RESPONSABILIDADE CSC",P39="RESPONSABILIDADE CSC"),"TICKET CONCLUÍDO", "PENDENTE") -> PENDENTE | L39: =IF(J39="","AGUARDANDO DADOS","RESPONSABILIDADE CSC") -> AGUARDANDO DADOS | P39: =IF(N39="","AGUARDANDO DADOS","RESPONSABILIDADE CSC") -> AGUARDANDO DADOS
B40: =_xlfn.XLOOKUP(E40,[1]Consolidado!$A:$A,[1]Consolidado!$D:$D) -> 45965 | C40: =IF(I40="TICKET CONCLUÍDO", "Concluído", IF(B40 < TODAY(), "Prazo estourado - " & TODAY()-B40 & " dias atrás", IF(TODAY()+30 < B40, "No prazo - faltam " & B40-TODAY() & " dias", IF(AND(B40-TODAY()<=29, B40-TODAY()>7), "Solicitar dados - faltam " & B40-TODAY() & " dias", IF(B40-TODAY()<=7, "Resolicitar - faltam " & B40-TODAY() & " dias", "Verificar") ) ) ) ) -> Concluído | D40: =_xlfn.XLOOKUP(E40,[1]Consolidado!$A:$A,[1]Consolidado!$AN:$AN) -> Atraso na entrega de linha branca | E40: MAN19-ManecaMarqu-AM | F40: =_xlfn.XLOOKUP(E40,'SOLICITAÇÃO DE PAGAMENTO'!C:C,'SOLICITAÇÃO DE PAGAMENTO'!M:M) -> 604306 | G40: =_xlfn.XLOOKUP(E40,'SOLICITAÇÃO DE PAGAMENTO'!C:C,'SOLICITAÇÃO DE PAGAMENTO'!B:B,"") -> 1470 | H40: HENRIQUE | I40: =IF(AND(L40="RESPONSABILIDADE CSC",P40="RESPONSABILIDADE CSC"),"TICKET CONCLUÍDO", "PENDENTE") -> TICKET CONCLUÍDO | J40: 2751707 | K40: 45938 | L40: =IF(J40="","AGUARDANDO DADOS","RESPONSABILIDADE CSC") -> RESPONSABILIDADE CSC | N40: 2765158 | O40: 45940 | P40: =IF(N40="","AGUARDANDO DADOS","RESPONSABILIDADE CSC") -> RESPONSABILIDADE CSC
B41: =_xlfn.XLOOKUP(E41,[1]Consolidado!$A:$A,[1]Consolidado!$D:$D) -> 46037 | C41: =IF(I41="TICKET CONCLUÍDO", "Concluído", IF(B41 < TODAY(), "Prazo estourado - " & TODAY()-B41 & " dias atrás", IF(TODAY()+30 < B41, "No prazo - faltam " & B41-TODAY() & " dias", IF(AND(B41-TODAY()<=29, B41-TODAY()>7), "Solicitar dados - faltam " & B41-TODAY() & " dias", IF(B41-TODAY()<=7, "Resolicitar - faltam " & B41-TODAY() & " dias", "Verificar") ) ) ) ) -> Concluído | D41: =_xlfn.XLOOKUP(E41,[1]Consolidado!$A:$A,[1]Consolidado!$AN:$AN) -> 4 vistorias | evolução de obra | placas sinalização | CND | Contrato CSC JUR | E41: JPE48-AvProducao-PB | F41: =_xlfn.XLOOKUP(E41,'SOLICITAÇÃO DE PAGAMENTO'!C:C,'SOLICITAÇÃO DE PAGAMENTO'!M:M) -> 603839 | G41: =_xlfn.XLOOKUP(E41,'SOLICITAÇÃO DE PAGAMENTO'!C:C,'SOLICITAÇÃO DE PAGAMENTO'!B:B,"") -> 1435 | H41: =_xlfn.XLOOKUP(G41,'SOLICITAÇÃO DE PAGAMENTO'!B:B,'SOLICITAÇÃO DE PAGAMENTO'!E:E,"") -> ANDRE | I41: =IF(AND(L41="RESPONSABILIDADE CSC",P41="RESPONSABILIDADE CSC"),"TICKET CONCLUÍDO", "PENDENTE") -> TICKET CONCLUÍDO | J41: 3047870 | K41: 45973 | L41: =IF(J41="","AGUARDANDO DADOS","RESPONSABILIDADE CSC") -> RESPONSABILIDADE CSC | N41: 3047927 | O41: 45973 | P41: =IF(N41="","AGUARDANDO DADOS","RESPONSABILIDADE CSC") -> RESPONSABILIDADE CSC | Q41: AGUARDANDO PADRÃO 24.09
B42: =_xlfn.XLOOKUP(E42,[1]Consolidado!$A:$A,[1]Consolidado!$D:$D) -> 45936 | C42: Concluído | D42: =_xlfn.XLOOKUP(E42,[1]Consolidado!$A:$A,[1]Consolidado!$AN:$AN) -> Atraso na emissão da I.E. / Atraso na solicitação de mercadoria, confirmaram o envio sem estar confirmado | E42: STH01-SantaHelena-MA | F42: =_xlfn.XLOOKUP(E42,'SOLICITAÇÃO DE PAGAMENTO'!C:C,'SOLICITAÇÃO DE PAGAMENTO'!M:M) -> 605462 | G42: =_xlfn.XLOOKUP(E42,'SOLICITAÇÃO DE PAGAMENTO'!C:C,'SOLICITAÇÃO DE PAGAMENTO'!B:B,"") -> 1495 | H42: =_xlfn.XLOOKUP(G42,'SOLICITAÇÃO DE PAGAMENTO'!B:B,'SOLICITAÇÃO DE PAGAMENTO'!E:E,"") -> HENRIQUE | I42: =IF(AND(L42="RESPONSABILIDADE CSC",P42="RESPONSABILIDADE CSC"),"TICKET CONCLUÍDO", "PENDENTE") -> PENDENTE | L42: POÇO | M42: POÇO | N42: 2751527 | O42: 45938 | P42: =IF(N42="","AGUARDANDO DADOS","RESPONSABILIDADE CSC") -> RESPONSABILIDADE CSC | Q42: ENERGIA LIGADA - AGUARDANDO DADOS
B43: =_xlfn.XLOOKUP(E43,[1]Consolidado!$A:$A,[1]Consolidado!$D:$D) -> 45971 | C43: =IF(I43="TICKET CONCLUÍDO", "Concluído", IF(B43 < TODAY(), "Prazo estourado - " & TODAY()-B43 & " dias atrás", IF(TODAY()+30 < B43, "No prazo - faltam " & B43-TODAY() & " dias", IF(AND(B43-TODAY()<=29, B43-TODAY()>7), "Solicitar dados - faltam " & B43-TODAY() & " dias", IF(B43-TODAY()<=7, "Resolicitar - faltam " & B43-TODAY() & " dias", "Verificar") ) ) ) ) -> Concluído | D43: =_xlfn.XLOOKUP(E43,[1]Consolidado!$A:$A,[1]Consolidado!$AN:$AN) -> 0 | E43: JGU11-Montarroyos-PE | F43: =_xlfn.XLOOKUP(E43,'SOLICITAÇÃO DE PAGAMENTO'!C:C,'SOLICITAÇÃO DE PAGAMENTO'!M:M) -> 603806 | G43: =_xlfn.XLOOKUP(E43,'SOLICITAÇÃO DE PAGAMENTO'!C:C,'SOLICITAÇÃO DE PAGAMENTO'!B:B,"") -> 1427 | H43: =_xlfn.XLOOKUP(G43,'SOLICITAÇÃO DE PAGAMENTO'!B:B,'SOLICITAÇÃO DE PAGAMENTO'!E:E,"") -> ADRIANO | I43: =IF(AND(L43="RESPONSABILIDADE CSC",P43="RESPONSABILIDADE CSC"),"TICKET CONCLUÍDO", "PENDENTE") -> TICKET CONCLUÍDO | J43: 3228816 | K43: 45994 | L43: =IF(J43="","AGUARDANDO DADOS","RESPONSABILIDADE CSC") -> RESPONSABILIDADE CSC | M43: CISTERNA | N43: 3228779 | O43: 45994 | P43: =IF(N43="","AGUARDANDO DADOS","RESPONSABILIDADE CSC") -> RESPONSABILIDADE CSC | Q43: AGUARDANDO LIGAÇÃO 22.09
B44: =_xlfn.XLOOKUP(E44,[1]Consolidado!$A:$A,[1]Consolidado!$D:$D) -> 46133 | C44: =IF(I44="TICKET CONCLUÍDO", "Concluído", IF(B44 < TODAY(), "Prazo estourado - " & TODAY()-B44 & " dias atrás", IF(TODAY()+30 < B44, "No prazo - faltam " & B44-TODAY() & " dias", IF(AND(B44-TODAY()<=29, B44-TODAY()>7), "Solicitar dados - faltam " & B44-TODAY() & " dias", IF(B44-TODAY()<=7, "Resolicitar - faltam " & B44-TODAY() & " dias", "Verificar") ) ) ) ) -> No prazo - faltam 118 dias | D44: =_xlfn.XLOOKUP(E44,[1]Consolidado!$A:$A,[1]Consolidado!$AN:$AN) -> 0 | E44: JGU15-AnicetoV-PE | F44: =_xlfn.XLOOKUP(E44,'SOLICITAÇÃO DE PAGAMENTO'!C:C,'SOLICITAÇÃO DE PAGAMENTO'!M:M) -> #N/A | G44: =_xlfn.XLOOKUP(E44,'SOLICITAÇÃO DE PAGAMENTO'!C:C,'SOLICITAÇÃO DE PAGAMENTO'!B:B,"") | H44: =_xlfn.XLOOKUP(G44,'SOLICITAÇÃO DE PAGAMENTO'!B:B,'SOLICITAÇÃO DE PAGAMENTO'!E:E,"") | I44: =IF(AND(L44="RESPONSABILIDADE CSC",P44="RESPONSABILIDADE CSC"),"TICKET CONCLUÍDO", "PENDENTE") -> PENDENTE | L44: =IF(J44="","AGUARDANDO DADOS","RESPONSABILIDADE CSC") -> AGUARDANDO DADOS | P44: =IF(N44="","AGUARDANDO DADOS","RESPONSABILIDADE CSC") -> AGUARDANDO DADOS
B45: =_xlfn.XLOOKUP(E45,[1]Consolidado!$A:$A,[1]Consolidado!$D:$D) -> 46045 | C45: =IF(I45="TICKET CONCLUÍDO", "Concluído", IF(B45 < TODAY(), "Prazo estourado - " & TODAY()-B45 & " dias atrás", IF(TODAY()+30 < B45, "No prazo - faltam " & B45-TODAY() & " dias", IF(AND(B45-TODAY()<=29, B45-TODAY()>7), "Solicitar dados - faltam " & B45-TODAY() & " dias", IF(B45-TODAY()<=7, "Resolicitar - faltam " & B45-TODAY() & " dias", "Verificar") ) ) ) ) -> Verificar | D45: =_xlfn.XLOOKUP(E45,[1]Consolidado!$A:$A,[1]Consolidado!$AN:$AN) -> 0 | E45: PAR08-Rdosventos-RN | F45: 603926 | G45: =_xlfn.XLOOKUP(E45,'SOLICITAÇÃO DE PAGAMENTO'!C:C,'SOLICITAÇÃO DE PAGAMENTO'!B:B,"") | H45: =_xlfn.XLOOKUP(G45,'SOLICITAÇÃO DE PAGAMENTO'!B:B,'SOLICITAÇÃO DE PAGAMENTO'!E:E,"") | I45: =IF(AND(L45="RESPONSABILIDADE CSC",P45="RESPONSABILIDADE CSC"),"TICKET CONCLUÍDO", "PENDENTE") -> PENDENTE | L45: =IF(J45="","AGUARDANDO DADOS","RESPONSABILIDADE CSC") -> AGUARDANDO DADOS | P45: =IF(N45="","AGUARDANDO DADOS","RESPONSABILIDADE CSC") -> AGUARDANDO DADOS
B46: =_xlfn.XLOOKUP(E46,[1]Consolidado!$A:$A,[1]Consolidado!$D:$D) -> 45768 | C46: =IF(I46="TICKET CONCLUÍDO", "Concluído", IF(B46 < TODAY(), "Prazo estourado - " & TODAY()-B46 & " dias atrás", IF(TODAY()+30 < B46, "No prazo - faltam " & B46-TODAY() & " dias", IF(AND(B46-TODAY()<=29, B46-TODAY()>7), "Solicitar dados - faltam " & B46-TODAY() & " dias", IF(B46-TODAY()<=7, "Resolicitar - faltam " & B46-TODAY() & " dias", "Verificar") ) ) ) ) -> Prazo estourado - 247 dias atrás | D46: =_xlfn.XLOOKUP(E46,[1]Consolidado!$A:$A,[1]Consolidado!$AN:$AN) -> 0 | E46: SLU82-StDumont-MA | F46: =_xlfn.XLOOKUP(E46,'SOLICITAÇÃO DE PAGAMENTO'!C:C,'SOLICITAÇÃO DE PAGAMENTO'!M:M) -> #N/A | G46: =_xlfn.XLOOKUP(E46,'SOLICITAÇÃO DE PAGAMENTO'!C:C,'SOLICITAÇÃO DE PAGAMENTO'!B:B,"") | H46: =_xlfn.XLOOKUP(G46,'SOLICITAÇÃO DE PAGAMENTO'!B:B,'SOLICITAÇÃO DE PAGAMENTO'!E:E,"") | I46: =IF(AND(L46="RESPONSABILIDADE CSC",P46="RESPONSABILIDADE CSC"),"TICKET CONCLUÍDO", "PENDENTE") -> PENDENTE | L46: =IF(J46="","AGUARDANDO DADOS","RESPONSABILIDADE CSC") -> AGUARDANDO DADOS | P46: =IF(N46="","AGUARDANDO DADOS","RESPONSABILIDADE CSC") -> AGUARDANDO DADOS
B47: =_xlfn.XLOOKUP(E47,[1]Consolidado!$A:$A,[1]Consolidado!$D:$D) -> 45969 | C47: =IF(I47="TICKET CONCLUÍDO", "Concluído", IF(B47 < TODAY(), "Prazo estourado - " & TODAY()-B47 & " dias atrás", IF(TODAY()+30 < B47, "No prazo - faltam " & B47-TODAY() & " dias", IF(AND(B47-TODAY()<=29, B47-TODAY()>7), "Solicitar dados - faltam " & B47-TODAY() & " dias", IF(B47-TODAY()<=7, "Resolicitar - faltam " & B47-TODAY() & " dias", "Verificar") ) ) ) ) -> Concluído | D47: =_xlfn.XLOOKUP(E47,[1]Consolidado!$A:$A,[1]Consolidado!$AN:$AN) -> Pendente contrato de resíduos |jurídico | E47: TUM01-Tucuma-PA | F47: =_xlfn.XLOOKUP(E47,'SOLICITAÇÃO DE PAGAMENTO'!C:C,'SOLICITAÇÃO DE PAGAMENTO'!M:M) -> 605664 | G47: =_xlfn.XLOOKUP(E47,'SOLICITAÇÃO DE PAGAMENTO'!C:C,'SOLICITAÇÃO DE PAGAMENTO'!B:B,"") -> 1508 | H47: =_xlfn.XLOOKUP(G47,'SOLICITAÇÃO DE PAGAMENTO'!B:B,'SOLICITAÇÃO DE PAGAMENTO'!E:E,"") -> HENRIQUE | I47: =IF(AND(L47="RESPONSABILIDADE CSC",P47="RESPONSABILIDADE CSC"),"TICKET CONCLUÍDO", "PENDENTE") -> TICKET CONCLUÍDO | J47: 2541563 | K47: 45910 | L47: =IF(J47="","AGUARDANDO DADOS","RESPONSABILIDADE CSC") -> RESPONSABILIDADE CSC | N47: 2541612 | O47: 45910 | P47: =IF(N47="","AGUARDANDO DADOS","RESPONSABILIDADE CSC") -> RESPONSABILIDADE CSC
B48: =_xlfn.XLOOKUP(E48,[1]Consolidado!$A:$A,[1]Consolidado!$D:$D) -> 45946 | C48: =IF(I48="TICKET CONCLUÍDO", "Concluído", IF(B48 < TODAY(), "Prazo estourado - " & TODAY()-B48 & " dias atrás", IF(TODAY()+30 < B48, "No prazo - faltam " & B48-TODAY() & " dias", IF(AND(B48-TODAY()<=29, B48-TODAY()>7), "Solicitar dados - faltam " & B48-TODAY() & " dias", IF(B48-TODAY()<=7, "Resolicitar - faltam " & B48-TODAY() & " dias", "Verificar") ) ) ) ) -> Concluído | D48: =_xlfn.XLOOKUP(E48,[1]Consolidado!$A:$A,[1]Consolidado!$AN:$AN) -> Obs: só terá câmera e alarme dia 18/10. Vistoria agendada para 15/10 | E48: CRS03-25Agosto-AC | F48: =_xlfn.XLOOKUP(E48,'SOLICITAÇÃO DE PAGAMENTO'!C:C,'SOLICITAÇÃO DE PAGAMENTO'!M:M) -> 605662 | G48: =_xlfn.XLOOKUP(E48,'SOLICITAÇÃO DE PAGAMENTO'!C:C,'SOLICITAÇÃO DE PAGAMENTO'!B:B,"") -> 1500 | H48: =_xlfn.XLOOKUP(G48,'SOLICITAÇÃO DE PAGAMENTO'!B:B,'SOLICITAÇÃO DE PAGAMENTO'!E:E,"") -> HENRIQUE | I48: =IF(AND(L48="RESPONSABILIDADE CSC",P48="RESPONSABILIDADE CSC"),"TICKET CONCLUÍDO", "PENDENTE") -> TICKET CONCLUÍDO | J48: 2751744 | K48: 45938 | L48: =IF(J48="","AGUARDANDO DADOS","RESPONSABILIDADE CSC") -> RESPONSABILIDADE CSC | N48: 2751767 | O48: 45938 | P48: =IF(N48="","AGUARDANDO DADOS","RESPONSABILIDADE CSC") -> RESPONSABILIDADE CSC
B49: =_xlfn.XLOOKUP(E49,[1]Consolidado!$A:$A,[1]Consolidado!$D:$D) -> 46017 | C49: =IF(I49="TICKET CONCLUÍDO", "Concluído", IF(B49 < TODAY(), "Prazo estourado - " & TODAY()-B49 & " dias atrás", IF(TODAY()+30 < B49, "No prazo - faltam " & B49-TODAY() & " dias", IF(AND(B49-TODAY()<=29, B49-TODAY()>7), "Solicitar dados - faltam " & B49-TODAY() & " dias", IF(B49-TODAY()<=7, "Resolicitar - faltam " & B49-TODAY() & " dias", "Verificar") ) ) ) ) -> Concluído | D49: =_xlfn.XLOOKUP(E49,[1]Consolidado!$A:$A,[1]Consolidado!$AN:$AN) -> 0 | E49: CGD23-JMurtinho-MS | F49: =_xlfn.XLOOKUP(E49,'SOLICITAÇÃO DE PAGAMENTO'!C:C,'SOLICITAÇÃO DE PAGAMENTO'!M:M) -> 605585 | G49: 1491 | H49: =_xlfn.XLOOKUP(G49,'SOLICITAÇÃO DE PAGAMENTO'!B:B,'SOLICITAÇÃO DE PAGAMENTO'!E:E,"") -> ANDRE | I49: =IF(AND(L49="RESPONSABILIDADE CSC",P49="RESPONSABILIDADE CSC"),"TICKET CONCLUÍDO", "PENDENTE") -> TICKET CONCLUÍDO | J49: 3293657 | K49: 46001 | L49: =IF(J49="","AGUARDANDO DADOS","RESPONSABILIDADE CSC") -> RESPONSABILIDADE CSC | N49: 3293630 | O49: 46001 | P49: =IF(N49="","AGUARDANDO DADOS","RESPONSABILIDADE CSC") -> RESPONSABILIDADE CSC
B50: =_xlfn.XLOOKUP(E50,[1]Consolidado!$A:$A,[1]Consolidado!$D:$D) -> 45952 | C50: =IF(I50="TICKET CONCLUÍDO", "Concluído", IF(B50 < TODAY(), "Prazo estourado - " & TODAY()-B50 & " dias atrás", IF(TODAY()+30 < B50, "No prazo - faltam " & B50-TODAY() & " dias", IF(AND(B50-TODAY()<=29, B50-TODAY()>7), "Solicitar dados - faltam " & B50-TODAY() & " dias", IF(B50-TODAY()<=7, "Resolicitar - faltam " & B50-TODAY() & " dias", "Verificar") ) ) ) ) -> Concluído | D50: =_xlfn.XLOOKUP(E50,[1]Consolidado!$A:$A,[1]Consolidado!$AN:$AN) -> Atraso documentação. Causa Raiz: Atraso aprovação de projeto e contratação farma | E50: RVD02-PqBuritis-GO | F50: =_xlfn.XLOOKUP(E50,'SOLICITAÇÃO DE PAGAMENTO'!C:C,'SOLICITAÇÃO DE PAGAMENTO'!M:M) -> 604006 | G50: =_xlfn.XLOOKUP(E50,'SOLICITAÇÃO DE PAGAMENTO'!C:C,'SOLICITAÇÃO DE PAGAMENTO'!B:B,"") -> 1488 | H50: =_xlfn.XLOOKUP(G50,'SOLICITAÇÃO DE PAGAMENTO'!B:B,'SOLICITAÇÃO DE PAGAMENTO'!E:E,"") -> ANDRE | I50: =IF(AND(L50="RESPONSABILIDADE CSC",P50="RESPONSABILIDADE CSC"),"TICKET CONCLUÍDO", "PENDENTE") -> TICKET CONCLUÍDO | J50: 2636899 | K50: 45923 | L50: =IF(J50="","AGUARDANDO DADOS","RESPONSABILIDADE CSC") -> RESPONSABILIDADE CSC | N50: 2636876 | O50: 45923 | P50: =IF(N50="","AGUARDANDO DADOS","RESPONSABILIDADE CSC") -> RESPONSABILIDADE CSC
B51: =_xlfn.XLOOKUP(E51,[1]Consolidado!$A:$A,[1]Consolidado!$D:$D) -> 45989 | C51: =IF(I51="TICKET CONCLUÍDO", "Concluído", IF(B51 < TODAY(), "Prazo estourado - " & TODAY()-B51 & " dias atrás", IF(TODAY()+30 < B51, "No prazo - faltam " & B51-TODAY() & " dias", IF(AND(B51-TODAY()<=29, B51-TODAY()>7), "Solicitar dados - faltam " & B51-TODAY() & " dias", IF(B51-TODAY()<=7, "Resolicitar - faltam " & B51-TODAY() & " dias", "Verificar") ) ) ) ) -> Concluído | D51: =_xlfn.XLOOKUP(E51,[1]Consolidado!$A:$A,[1]Consolidado!$AN:$AN) -> Exigido apresentar licença ambiental | 30 dias | CNAE retirar vacina | E51: SIN04-Flamboyants-MT | F51: =_xlfn.XLOOKUP(E51,'SOLICITAÇÃO DE PAGAMENTO'!C:C,'SOLICITAÇÃO DE PAGAMENTO'!M:M) -> 605746 | G51: =_xlfn.XLOOKUP(E51,'SOLICITAÇÃO DE PAGAMENTO'!C:C,'SOLICITAÇÃO DE PAGAMENTO'!B:B,"") -> 1512 | H51: =_xlfn.XLOOKUP(G51,'SOLICITAÇÃO DE PAGAMENTO'!B:B,'SOLICITAÇÃO DE PAGAMENTO'!E:E,"") -> ANDRE | I51: =IF(AND(L51="RESPONSABILIDADE CSC",P51="RESPONSABILIDADE CSC"),"TICKET CONCLUÍDO", "PENDENTE") -> TICKET CONCLUÍDO | J51: 3076502 | K51: 45976 | L51: =IF(J51="","AGUARDANDO DADOS","RESPONSABILIDADE CSC") -> RESPONSABILIDADE CSC | N51: 3076465 | O51: 45976 | P51: =IF(N51="","AGUARDANDO DADOS","RESPONSABILIDADE CSC") -> RESPONSABILIDADE CSC | Q51: AGUARDANDO LIGAÇÃO
B52: =_xlfn.XLOOKUP(E52,[1]Consolidado!$A:$A,[1]Consolidado!$D:$D) -> 45989 | C52: =IF(I52="TICKET CONCLUÍDO", "Concluído", IF(B52 < TODAY(), "Prazo estourado - " & TODAY()-B52 & " dias atrás", IF(TODAY()+30 < B52, "No prazo - faltam " & B52-TODAY() & " dias", IF(AND(B52-TODAY()<=29, B52-TODAY()>7), "Solicitar dados - faltam " & B52-TODAY() & " dias", IF(B52-TODAY()<=7, "Resolicitar - faltam " & B52-TODAY() & " dias", "Verificar") ) ) ) ) -> Concluído | D52: =_xlfn.XLOOKUP(E52,[1]Consolidado!$A:$A,[1]Consolidado!$AN:$AN) -> 0 | E52: IRA01-Iranduba-AM | F52: =_xlfn.XLOOKUP(E52,'SOLICITAÇÃO DE PAGAMENTO'!C:C,'SOLICITAÇÃO DE PAGAMENTO'!M:M) -> 605470 | G52: =_xlfn.XLOOKUP(E52,'SOLICITAÇÃO DE PAGAMENTO'!C:C,'SOLICITAÇÃO DE PAGAMENTO'!B:B,"") -> 1502 | H52: =_xlfn.XLOOKUP(G52,'SOLICITAÇÃO DE PAGAMENTO'!B:B,'SOLICITAÇÃO DE PAGAMENTO'!E:E,"") -> HENRIQUE | I52: =IF(AND(L52="RESPONSABILIDADE CSC",P52="RESPONSABILIDADE CSC"),"TICKET CONCLUÍDO", "PENDENTE") -> TICKET CONCLUÍDO | J52: 3218972 | K52: 45993 | L52: =IF(J52="","AGUARDANDO DADOS","RESPONSABILIDADE CSC") -> RESPONSABILIDADE CSC | N52: 3218999 | O52: 45993 | P52: =IF(N52="","AGUARDANDO DADOS","RESPONSABILIDADE CSC") -> RESPONSABILIDADE CSC | Q52: AGUARDANDO PADRÃO 26.10
B53: =_xlfn.XLOOKUP(E53,[1]Consolidado!$A:$A,[1]Consolidado!$D:$D) -> 46105 | C53: =IF(I53="TICKET CONCLUÍDO", "Concluído", IF(B53 < TODAY(), "Prazo estourado - " & TODAY()-B53 & " dias atrás", IF(TODAY()+30 < B53, "No prazo - faltam " & B53-TODAY() & " dias", IF(AND(B53-TODAY()<=29, B53-TODAY()>7), "Solicitar dados - faltam " & B53-TODAY() & " dias", IF(B53-TODAY()<=7, "Resolicitar - faltam " & B53-TODAY() & " dias", "Verificar") ) ) ) ) -> No prazo - faltam 90 dias | D53: =_xlfn.XLOOKUP(E53,[1]Consolidado!$A:$A,[1]Consolidado!$AN:$AN) -> 0 | E53: MAN22-CidadeDeus-AM | F53: =_xlfn.XLOOKUP(E53,'SOLICITAÇÃO DE PAGAMENTO'!C:C,'SOLICITAÇÃO DE PAGAMENTO'!M:M) -> #N/A | G53: =_xlfn.XLOOKUP(E53,'SOLICITAÇÃO DE PAGAMENTO'!C:C,'SOLICITAÇÃO DE PAGAMENTO'!B:B,"") | H53: =_xlfn.XLOOKUP(G53,'SOLICITAÇÃO DE PAGAMENTO'!B:B,'SOLICITAÇÃO DE PAGAMENTO'!E:E,"") | I53: =IF(AND(L53="RESPONSABILIDADE CSC",P53="RESPONSABILIDADE CSC"),"TICKET CONCLUÍDO", "PENDENTE") -> PENDENTE | L53: =IF(J53="","AGUARDANDO DADOS","RESPONSABILIDADE CSC") -> AGUARDANDO DADOS | P53: =IF(N53="","AGUARDANDO DADOS","RESPONSABILIDADE CSC") -> AGUARDANDO DADOS
B54: =_xlfn.XLOOKUP(E54,[1]Consolidado!$A:$A,[1]Consolidado!$D:$D) -> 45947 | C54: =IF(I54="TICKET CONCLUÍDO", "Concluído", IF(B54 < TODAY(), "Prazo estourado - " & TODAY()-B54 & " dias atrás", IF(TODAY()+30 < B54, "No prazo - faltam " & B54-TODAY() & " dias", IF(AND(B54-TODAY()<=29, B54-TODAY()>7), "Solicitar dados - faltam " & B54-TODAY() & " dias", IF(B54-TODAY()<=7, "Resolicitar - faltam " & B54-TODAY() & " dias", "Verificar") ) ) ) ) -> Concluído | D54: =_xlfn.XLOOKUP(E54,[1]Consolidado!$A:$A,[1]Consolidado!$AN:$AN) -> Construtora não conseguiu entregar a tempo, alterada de 23/09 para 30/09 | E54: PRB05-JdCanada-PA | F54: =_xlfn.XLOOKUP(E54,'SOLICITAÇÃO DE PAGAMENTO'!C:C,'SOLICITAÇÃO DE PAGAMENTO'!M:M) -> 605727 | G54: =_xlfn.XLOOKUP(E54,'SOLICITAÇÃO DE PAGAMENTO'!C:C,'SOLICITAÇÃO DE PAGAMENTO'!B:B,"") -> 1501 | H54: =_xlfn.XLOOKUP(G54,'SOLICITAÇÃO DE PAGAMENTO'!B:B,'SOLICITAÇÃO DE PAGAMENTO'!E:E,"") -> HENRIQUE | I54: =IF(AND(L54="RESPONSABILIDADE CSC",P54="RESPONSABILIDADE CSC"),"TICKET CONCLUÍDO", "PENDENTE") -> TICKET CONCLUÍDO | J54: 2401973 | K54: 45890 | L54: =IF(J54="","AGUARDANDO DADOS","RESPONSABILIDADE CSC") -> RESPONSABILIDADE CSC | N54: 2897168 | O54: 45957 | P54: =IF(N54="","AGUARDANDO DADOS","RESPONSABILIDADE CSC") -> RESPONSABILIDADE CSC | Q54: PADRÃO MONTADO, LIGAÇÃO NÃO OCORREU [PREVISTO 19/09]
B55: =_xlfn.XLOOKUP(E55,[1]Consolidado!$A:$A,[1]Consolidado!$D:$D) -> 45987 | C55: =IF(I55="TICKET CONCLUÍDO", "Concluído", IF(B55 < TODAY(), "Prazo estourado - " & TODAY()-B55 & " dias atrás", IF(TODAY()+30 < B55, "No prazo - faltam " & B55-TODAY() & " dias", IF(AND(B55-TODAY()<=29, B55-TODAY()>7), "Solicitar dados - faltam " & B55-TODAY() & " dias", IF(B55-TODAY()<=7, "Resolicitar - faltam " & B55-TODAY() & " dias", "Verificar") ) ) ) ) -> Concluído | D55: =_xlfn.XLOOKUP(E55,[1]Consolidado!$A:$A,[1]Consolidado!$AN:$AN) -> IE pendente | previsão 24/10 | E55: ANT01-Anastacio-MS | F55: =_xlfn.XLOOKUP(E55,'SOLICITAÇÃO DE PAGAMENTO'!C:C,'SOLICITAÇÃO DE PAGAMENTO'!M:M) -> 605728 | G55: =_xlfn.XLOOKUP(E55,'SOLICITAÇÃO DE PAGAMENTO'!C:C,'SOLICITAÇÃO DE PAGAMENTO'!B:B,"") -> 1505 | H55: =_xlfn.XLOOKUP(G55,'SOLICITAÇÃO DE PAGAMENTO'!B:B,'SOLICITAÇÃO DE PAGAMENTO'!E:E,"") -> ANDRE | I55: =IF(AND(L55="RESPONSABILIDADE CSC",P55="RESPONSABILIDADE CSC"),"TICKET CONCLUÍDO", "PENDENTE") -> TICKET CONCLUÍDO | J55: 3076621 | K55: 45976 | L55: =IF(J55="","AGUARDANDO DADOS","RESPONSABILIDADE CSC") -> RESPONSABILIDADE CSC | N55: 3048065 | O55: 45973 | P55: =IF(N55="","AGUARDANDO DADOS","RESPONSABILIDADE CSC") -> RESPONSABILIDADE CSC | Q55: AGUARDANDO PADRÃO
B56: =_xlfn.XLOOKUP(E56,[1]Consolidado!$A:$A,[1]Consolidado!$D:$D) -> 45989 | C56: =IF(I56="TICKET CONCLUÍDO", "Concluído", IF(B56 < TODAY(), "Prazo estourado - " & TODAY()-B56 & " dias atrás", IF(TODAY()+30 < B56, "No prazo - faltam " & B56-TODAY() & " dias", IF(AND(B56-TODAY()<=29, B56-TODAY()>7), "Solicitar dados - faltam " & B56-TODAY() & " dias", IF(B56-TODAY()<=7, "Resolicitar - faltam " & B56-TODAY() & " dias", "Verificar") ) ) ) ) -> Concluído | D56: =_xlfn.XLOOKUP(E56,[1]Consolidado!$A:$A,[1]Consolidado!$AN:$AN) -> 0 | E56: SMG01-SMigGuama-PA | F56: =_xlfn.XLOOKUP(E56,'SOLICITAÇÃO DE PAGAMENTO'!C:C,'SOLICITAÇÃO DE PAGAMENTO'!M:M) -> 604037 | G56: =_xlfn.XLOOKUP(E56,'SOLICITAÇÃO DE PAGAMENTO'!C:C,'SOLICITAÇÃO DE PAGAMENTO'!B:B,"") -> 1504 | H56: =_xlfn.XLOOKUP(G56,'SOLICITAÇÃO DE PAGAMENTO'!B:B,'SOLICITAÇÃO DE PAGAMENTO'!E:E,"") -> HENRIQUE | I56: =IF(AND(L56="RESPONSABILIDADE CSC",P56="RESPONSABILIDADE CSC"),"TICKET CONCLUÍDO", "PENDENTE") -> TICKET CONCLUÍDO | L56: RESPONSABILIDADE CSC | M56: Não haverá cobrança | N56: 2840256 | O56: 45950 | P56: =IF(N56="","AGUARDANDO DADOS","RESPONSABILIDADE CSC") -> RESPONSABILIDADE CSC | Q56: AGUARDANDO LIGAÇÃO
B57: =_xlfn.XLOOKUP(E57,[1]Consolidado!$A:$A,[1]Consolidado!$D:$D) -> 106 | C57: =IF(I57="TICKET CONCLUÍDO", "Concluído", IF(B57 < TODAY(), "Prazo estourado - " & TODAY()-B57 & " dias atrás", IF(TODAY()+30 < B57, "No prazo - faltam " & B57-TODAY() & " dias", IF(AND(B57-TODAY()<=29, B57-TODAY()>7), "Solicitar dados - faltam " & B57-TODAY() & " dias", IF(B57-TODAY()<=7, "Resolicitar - faltam " & B57-TODAY() & " dias", "Verificar") ) ) ) ) -> Prazo estourado - 45909 dias atrás | D57: 6. cancelado | E57: FOR188-Genibau-CE | F57: =_xlfn.XLOOKUP(E57,'SOLICITAÇÃO DE PAGAMENTO'!C:C,'SOLICITAÇÃO DE PAGAMENTO'!M:M) -> #N/A | G57: 1509 | H57: =_xlfn.XLOOKUP(G57,'SOLICITAÇÃO DE PAGAMENTO'!B:B,'SOLICITAÇÃO DE PAGAMENTO'!E:E,"") | I57: =IF(AND(L57="RESPONSABILIDADE CSC",P57="RESPONSABILIDADE CSC"),"TICKET CONCLUÍDO", "PENDENTE") -> PENDENTE | L57: =IF(J57="","AGUARDANDO DADOS","RESPONSABILIDADE CSC") -> AGUARDANDO DADOS | P57: =IF(N57="","AGUARDANDO DADOS","RESPONSABILIDADE CSC") -> AGUARDANDO DADOS
B58: =_xlfn.XLOOKUP(E58,[1]Consolidado!$A:$A,[1]Consolidado!$D:$D) -> 46001 | C58: =IF(I58="TICKET CONCLUÍDO", "Concluído", IF(B58 < TODAY(), "Prazo estourado - " & TODAY()-B58 & " dias atrás", IF(TODAY()+30 < B58, "No prazo - faltam " & B58-TODAY() & " dias", IF(AND(B58-TODAY()<=29, B58-TODAY()>7), "Solicitar dados - faltam " & B58-TODAY() & " dias", IF(B58-TODAY()<=7, "Resolicitar - faltam " & B58-TODAY() & " dias", "Verificar") ) ) ) ) -> Concluído | D58: =_xlfn.XLOOKUP(E58,[1]Consolidado!$A:$A,[1]Consolidado!$AN:$AN) -> 0 | E58: COD03-Rotatoria-MA | F58: =_xlfn.XLOOKUP(E58,'SOLICITAÇÃO DE PAGAMENTO'!C:C,'SOLICITAÇÃO DE PAGAMENTO'!M:M) -> 605803 | H58: =_xlfn.XLOOKUP(G58,'SOLICITAÇÃO DE PAGAMENTO'!B:B,'SOLICITAÇÃO DE PAGAMENTO'!E:E,"") -> 0 | I58: =IF(AND(L58="RESPONSABILIDADE CSC",P58="RESPONSABILIDADE CSC"),"TICKET CONCLUÍDO", "PENDENTE") -> TICKET CONCLUÍDO | J58: 3219051 | K58: 45993 | L58: =IF(J58="","AGUARDANDO DADOS","RESPONSABILIDADE CSC") -> RESPONSABILIDADE CSC | N58: 3293808 | O58: 46001 | P58: =IF(N58="","AGUARDANDO DADOS","RESPONSABILIDADE CSC") -> RESPONSABILIDADE CSC
B59: =_xlfn.XLOOKUP(E59,[1]Consolidado!$A:$A,[1]Consolidado!$D:$D) -> 45975 | C59: =IF(I59="TICKET CONCLUÍDO", "Concluído", IF(B59 < TODAY(), "Prazo estourado - " & TODAY()-B59 & " dias atrás", IF(TODAY()+30 < B59, "No prazo - faltam " & B59-TODAY() & " dias", IF(AND(B59-TODAY()<=29, B59-TODAY()>7), "Solicitar dados - faltam " & B59-TODAY() & " dias", IF(B59-TODAY()<=7, "Resolicitar - faltam " & B59-TODAY() & " dias", "Verificar") ) ) ) ) -> Prazo estourado - 40 dias atrás | D59: =_xlfn.XLOOKUP(E59,[1]Consolidado!$A:$A,[1]Consolidado!$AN:$AN) -> 0 | E59: IGA02-CruzRebouca-PE | F59: =_xlfn.XLOOKUP(E59,'SOLICITAÇÃO DE PAGAMENTO'!C:C,'SOLICITAÇÃO DE PAGAMENTO'!M:M) -> 605905 | G59: =_xlfn.XLOOKUP(E59,'SOLICITAÇÃO DE PAGAMENTO'!C:C,'SOLICITAÇÃO DE PAGAMENTO'!B:B,"") -> 1437 | H59: =_xlfn.XLOOKUP(G59,'SOLICITAÇÃO DE PAGAMENTO'!B:B,'SOLICITAÇÃO DE PAGAMENTO'!E:E,"") -> ADRIANO | I59: =IF(AND(L59="RESPONSABILIDADE CSC",P59="RESPONSABILIDADE CSC"),"TICKET CONCLUÍDO", "PENDENTE") -> PENDENTE | L59: =IF(J59="","AGUARDANDO DADOS","RESPONSABILIDADE CSC") -> AGUARDANDO DADOS | P59: =IF(N59="","AGUARDANDO DADOS","RESPONSABILIDADE CSC") -> AGUARDANDO DADOS | Q59: AGUARDANDO LIGAÇÃO
B60: =_xlfn.XLOOKUP(E60,[1]Consolidado!$A:$A,[1]Consolidado!$D:$D) -> 46116 | C60: =IF(I60="TICKET CONCLUÍDO", "Concluído", IF(B60 < TODAY(), "Prazo estourado - " & TODAY()-B60 & " dias atrás", IF(TODAY()+30 < B60, "No prazo - faltam " & B60-TODAY() & " dias", IF(AND(B60-TODAY()<=29, B60-TODAY()>7), "Solicitar dados - faltam " & B60-TODAY() & " dias", IF(B60-TODAY()<=7, "Resolicitar - faltam " & B60-TODAY() & " dias", "Verificar") ) ) ) ) -> No prazo - faltam 101 dias | D60: =_xlfn.XLOOKUP(E60,[1]Consolidado!$A:$A,[1]Consolidado!$AN:$AN) -> 0 | E60: TER36-ZequinhaFre-PI | F60: =_xlfn.XLOOKUP(E60,'SOLICITAÇÃO DE PAGAMENTO'!C:C,'SOLICITAÇÃO DE PAGAMENTO'!M:M) -> #N/A | G60: =_xlfn.XLOOKUP(E60,'SOLICITAÇÃO DE PAGAMENTO'!C:C,'SOLICITAÇÃO DE PAGAMENTO'!B:B,"") | H60: =_xlfn.XLOOKUP(G60,'SOLICITAÇÃO DE PAGAMENTO'!B:B,'SOLICITAÇÃO DE PAGAMENTO'!E:E,"") | I60: =IF(AND(L60="RESPONSABILIDADE CSC",P60="RESPONSABILIDADE CSC"),"TICKET CONCLUÍDO", "PENDENTE") -> PENDENTE | L60: =IF(J60="","AGUARDANDO DADOS","RESPONSABILIDADE CSC") -> AGUARDANDO DADOS | P60: =IF(N60="","AGUARDANDO DADOS","RESPONSABILIDADE CSC") -> AGUARDANDO DADOS
B61: =_xlfn.XLOOKUP(E61,[1]Consolidado!$A:$A,[1]Consolidado!$D:$D) -> 46011 | C61: =IF(I61="TICKET CONCLUÍDO", "Concluído", IF(B61 < TODAY(), "Prazo estourado - " & TODAY()-B61 & " dias atrás", IF(TODAY()+30 < B61, "No prazo - faltam " & B61-TODAY() & " dias", IF(AND(B61-TODAY()<=29, B61-TODAY()>7), "Solicitar dados - faltam " & B61-TODAY() & " dias", IF(B61-TODAY()<=7, "Resolicitar - faltam " & B61-TODAY() & " dias", "Verificar") ) ) ) ) -> Prazo estourado - 4 dias atrás | D61: =_xlfn.XLOOKUP(E61,[1]Consolidado!$A:$A,[1]Consolidado!$AN:$AN) -> 0 | E61: JAI01-Jatai-GO | F61: =_xlfn.XLOOKUP(E61,'SOLICITAÇÃO DE PAGAMENTO'!C:C,'SOLICITAÇÃO DE PAGAMENTO'!M:M) -> 605740 | G61: 585 | H61: =_xlfn.XLOOKUP(G61,'SOLICITAÇÃO DE PAGAMENTO'!B:B,'SOLICITAÇÃO DE PAGAMENTO'!E:E,"") -> ANDRE | I61: =IF(AND(L61="RESPONSABILIDADE CSC",P61="RESPONSABILIDADE CSC"),"TICKET CONCLUÍDO", "PENDENTE") -> PENDENTE | L61: =IF(J61="","AGUARDANDO DADOS","RESPONSABILIDADE CSC") -> AGUARDANDO DADOS | P61: =IF(N61="","AGUARDANDO DADOS","RESPONSABILIDADE CSC") -> AGUARDANDO DADOS
B62: =_xlfn.XLOOKUP(E62,[1]Consolidado!$A:$A,[1]Consolidado!$D:$D) -> 45986 | C62: =IF(I62="TICKET CONCLUÍDO", "Concluído", IF(B62 < TODAY(), "Prazo estourado - " & TODAY()-B62 & " dias atrás", IF(TODAY()+30 < B62, "No prazo - faltam " & B62-TODAY() & " dias", IF(AND(B62-TODAY()<=29, B62-TODAY()>7), "Solicitar dados - faltam " & B62-TODAY() & " dias", IF(B62-TODAY()<=7, "Resolicitar - faltam " & B62-TODAY() & " dias", "Verificar") ) ) ) ) -> Concluído | D62: =_xlfn.XLOOKUP(E62,[1]Consolidado!$A:$A,[1]Consolidado!$AN:$AN) -> IE liberada | E62: NAV01-Naviraí-MS | F62: =_xlfn.XLOOKUP(E62,'SOLICITAÇÃO DE PAGAMENTO'!C:C,'SOLICITAÇÃO DE PAGAMENTO'!M:M) -> 605804 | G62: =_xlfn.XLOOKUP(E62,'SOLICITAÇÃO DE PAGAMENTO'!C:C,'SOLICITAÇÃO DE PAGAMENTO'!B:B,"") -> 1506 | H62: =_xlfn.XLOOKUP(G62,'SOLICITAÇÃO DE PAGAMENTO'!B:B,'SOLICITAÇÃO DE PAGAMENTO'!E:E,"") -> ANDRE | I62: =IF(AND(L62="RESPONSABILIDADE CSC",P62="RESPONSABILIDADE CSC"),"TICKET CONCLUÍDO", "PENDENTE") -> TICKET CONCLUÍDO | J62: 3076353 | K62: 45976 | L62: =IF(J62="","AGUARDANDO DADOS","RESPONSABILIDADE CSC") -> RESPONSABILIDADE CSC | N62: 3076344 | O62: 45976 | P62: =IF(N62="","AGUARDANDO DADOS","RESPONSABILIDADE CSC") -> RESPONSABILIDADE CSC | Q62: AGUARDANDO PADRÃO
B63: =_xlfn.XLOOKUP(E63,[1]Consolidado!$A:$A,[1]Consolidado!$D:$D) -> 46006 | C63: =IF(I63="TICKET CONCLUÍDO", "Concluído", IF(B63 < TODAY(), "Prazo estourado - " & TODAY()-B63 & " dias atrás", IF(TODAY()+30 < B63, "No prazo - faltam " & B63-TODAY() & " dias", IF(AND(B63-TODAY()<=29, B63-TODAY()>7), "Solicitar dados - faltam " & B63-TODAY() & " dias", IF(B63-TODAY()<=7, "Resolicitar - faltam " & B63-TODAY() & " dias", "Verificar") ) ) ) ) -> Concluído | D63: =_xlfn.XLOOKUP(E63,[1]Consolidado!$A:$A,[1]Consolidado!$AN:$AN) -> 0 | E63: CMC02-JoseAlencar-CE | F63: =_xlfn.XLOOKUP(E63,'SOLICITAÇÃO DE PAGAMENTO'!C:C,'SOLICITAÇÃO DE PAGAMENTO'!M:M) -> 605789 | G63: =_xlfn.XLOOKUP(E63,'SOLICITAÇÃO DE PAGAMENTO'!C:C,'SOLICITAÇÃO DE PAGAMENTO'!B:B,"") -> 1513 | H63: JORDANA | I63: =IF(AND(L63="RESPONSABILIDADE CSC",P63="RESPONSABILIDADE CSC"),"TICKET CONCLUÍDO", "PENDENTE") -> TICKET CONCLUÍDO | J63: 3327771 | K63: 46006 | L63: =IF(J63="","AGUARDANDO DADOS","RESPONSABILIDADE CSC") -> RESPONSABILIDADE CSC | N63: 3327861 | O63: 46006 | P63: =IF(N63="","AGUARDANDO DADOS","RESPONSABILIDADE CSC") -> RESPONSABILIDADE CSC | Q63: AGUARDANDO PADRÃO 14.10
E64: IGU04-CarlosRCost-CE | F64: =_xlfn.XLOOKUP(E64,'SOLICITAÇÃO DE PAGAMENTO'!C:C,'SOLICITAÇÃO DE PAGAMENTO'!M:M) -> 605801 | G64: =_xlfn.XLOOKUP(E64,'SOLICITAÇÃO DE PAGAMENTO'!C:C,'SOLICITAÇÃO DE PAGAMENTO'!B:B,"") -> 1510 | H64: JORDANA | I64: =IF(AND(L64="RESPONSABILIDADE CSC",P64="RESPONSABILIDADE CSC"),"TICKET CONCLUÍDO", "PENDENTE") -> PENDENTE | L64: =IF(J64="","AGUARDANDO DADOS","RESPONSABILIDADE CSC") -> AGUARDANDO DADOS | P64: =IF(N64="","AGUARDANDO DADOS","RESPONSABILIDADE CSC") -> AGUARDANDO DADOS
B65: =_xlfn.XLOOKUP(E65,[1]Consolidado!$A:$A,[1]Consolidado!$D:$D) -> 46000 | C65: =IF(I65="TICKET CONCLUÍDO", "Concluído", IF(B65 < TODAY(), "Prazo estourado - " & TODAY()-B65 & " dias atrás", IF(TODAY()+30 < B65, "No prazo - faltam " & B65-TODAY() & " dias", IF(AND(B65-TODAY()<=29, B65-TODAY()>7), "Solicitar dados - faltam " & B65-TODAY() & " dias", IF(B65-TODAY()<=7, "Resolicitar - faltam " & B65-TODAY() & " dias", "Verificar") ) ) ) ) -> Concluído | D65: =_xlfn.XLOOKUP(E65,[1]Consolidado!$A:$A,[1]Consolidado!$AN:$AN) -> Risco de documentação. Só pode inaugurar se tiver inscrição municipal Ativa | E65: AME01-AvBrasil-SP | F65: =_xlfn.XLOOKUP(E65,'SOLICITAÇÃO DE PAGAMENTO'!C:C,'SOLICITAÇÃO DE PAGAMENTO'!M:M) -> 605906 | G65: =_xlfn.XLOOKUP(E65,'SOLICITAÇÃO DE PAGAMENTO'!C:C,'SOLICITAÇÃO DE PAGAMENTO'!B:B,"") -> 1516 | H65: ADRIANO | I65: =IF(AND(L65="RESPONSABILIDADE CSC",P65="RESPONSABILIDADE CSC"),"TICKET CONCLUÍDO", "PENDENTE") -> TICKET CONCLUÍDO | J65: 3271192 | K65: 45999 | L65: =IF(J65="","AGUARDANDO DADOS","RESPONSABILIDADE CSC") -> RESPONSABILIDADE CSC | N65: 3364827 | O65: 46010 | P65: =IF(N65="","AGUARDANDO DADOS","RESPONSABILIDADE CSC") -> RESPONSABILIDADE CSC
B66: =_xlfn.XLOOKUP(E66,[1]Consolidado!$A:$A,[1]Consolidado!$D:$D) -> #N/A | C66: =IF(I66="TICKET CONCLUÍDO", "Concluído", IF(B66 < TODAY(), "Prazo estourado - " & TODAY()-B66 & " dias atrás", IF(TODAY()+30 < B66, "No prazo - faltam " & B66-TODAY() & " dias", IF(AND(B66-TODAY()<=29, B66-TODAY()>7), "Solicitar dados - faltam " & B66-TODAY() & " dias", IF(B66-TODAY()<=7, "Resolicitar - faltam " & B66-TODAY() & " dias", "Verificar") ) ) ) ) -> #N/A | D66: =_xlfn.XLOOKUP(E66,[1]Consolidado!$A:$A,[1]Consolidado!$AN:$AN) -> #N/A | E66: [Relocation]SUZ02-FraGlicerio-SP | F66: =_xlfn.XLOOKUP(E66,'SOLICITAÇÃO DE PAGAMENTO'!C:C,'SOLICITAÇÃO DE PAGAMENTO'!M:M) -> 605973 | G66: 320 | H66: =_xlfn.XLOOKUP(G66,'SOLICITAÇÃO DE PAGAMENTO'!B:B,'SOLICITAÇÃO DE PAGAMENTO'!E:E,"") -> ADRIANO | I66: =IF(AND(L66="RESPONSABILIDADE CSC",P66="RESPONSABILIDADE CSC"),"TICKET CONCLUÍDO", "PENDENTE") -> PENDENTE | L66: =IF(J66="","AGUARDANDO DADOS","RESPONSABILIDADE CSC") -> AGUARDANDO DADOS | P66: =IF(N66="","AGUARDANDO DADOS","RESPONSABILIDADE CSC") -> AGUARDANDO DADOS

Sheet SOLICITAÇÃO DE PAGAMENTO
A1: EMP | B1: FILIAL | C1: LOJA | D1: CNPJ | E1: COORDENADOR | F1: PROJETO | G1: SERVIÇO | H1: NOTA | I1: FORNECEDOR | J1: ARQUIVO | K1: ENVIAR COORD? | L1: cód forn | M1: ORDEM | N1: REQUISIÇÃO | O1: RC ENVIADA? | P1: VALOR RC | Q1: VALOR A PAGAR | R1: VALOR BI | S1: STATUS RC | T1: PEDIDO | U1: ASSUNTO | V1: ID | W1: LINK | X1: CHAMADO | Y1: Status | Z1: procx status | AA1: se status | AB1: Solved + Closed | AC1: Data_pgto_sap | AD1: MIRO | AE1: Abrir ticket? | AF1: teste se status | AG1: Status Result1 | AH1: Data criação linha | AI1: Data criação ticket | AJ1: procx ticket | AK1: se ticket | AL1: Data criação RC | AM1: Data criação ticket br | AN1: Prazo | AO1: Solicitado apoio? | AP1: Coluna1 | AQ1: Idpadrao | AR1: Coluna2
A2: =IF(B2<7000,1000,2000) -> 1000 | B2: 1491 | C2: CGD23-JMurtinho-MS | D2: 1491 | E2: ANDRE | F2: LOJAS NOVAS | G2: Gerenciadora | H2: 15219 | I2: HTB | M2: 605585 | N2: 10023481 | O2: sim | P2: 48500 | Q2: 14550 | R2: =IF(Tabela1[[#This Row],[VALOR A PAGAR]]>1,Tabela1[[#This Row],[VALOR A PAGAR]],Tabela1[[#This Row],[VALOR RC]]) -> 14550 | S2: =IF( Tabela1[[#This Row],[PEDIDO]] <> "", "Pedido Criado", IF( AND(Tabela1[[#This Row],[REQUISIÇÃO]] = "", Tabela1[[#This Row],[PEDIDO]] = ""), "Orçamento Recebido", IF( AND(Tabela1[[#This Row],[REQUISIÇÃO]] <> "", Tabela1[[#This Row],[PEDIDO]] = "", Tabela1[[#This Row],[RC ENVIADA?]] = ""), "Requisição Feita", IF( AND(Tabela1[[#This Row],[RC ENVIADA?]] = "SIM", Tabela1[[#This Row],[REQUISIÇÃO]] <> "", Tabela1[[#This Row],[PEDIDO]] = ""), "Aguardando Pedido", "" ) ) ) ) -> Aguardando Pedido | U2: =F2 & " " & " " & B2 & " - " & I2 & " - " & "N°" & H2 & " - " & Tabela1[[#This Row],[Coluna1]] -> LOJAS NOVAS 1491 - HTB - N°15219 - | X2: =IF(V2<>"","ABERTO","PENDENTE") -> PENDENTE | AA2: =IF(Tabela1[[#This Row],[CHAMADO]]="ABERTO",Tabela1[[#This Row],[procx status]],"") | AE2: =IF(Tabela1[[#This Row],[Status Result1]]="Aguardando autorização pgto", "sim","") | AF2: =IF(Tabela1[[#This Row],[ID]]<>"", IF(Tabela1[[#This Row],[Data_pgto_sap]]<>"", "Data de pagamento: "&TEXT(Tabela1[[#This Row],[Data_pgto_sap]],"dd/mm/aaaa"), "Chamado aberto, aguardando programação de pagamento"), IF(AND(Tabela1[[#This Row],[PEDIDO]]<>"",Tabela1[[#This Row],[NOTA]]<>""), "Há pedido e há nota, aguardando autorização pgto", IF(AND(Tabela1[[#This Row],[PEDIDO]]<>"",Tabela1[[#This Row],[NOTA]]=""), "Aguardando nota, há pedido", IF(AND(Tabela1[[#This Row],[PEDIDO]]="",Tabela1[[#This Row],[NOTA]]<>""), "Aguardando pedido, há nota",) ))) -> Aguardando pedido, há nota | AG2: =IF(Tabela1[[#This Row],[ID]]<>"", IF(Tabela1[[#This Row],[Data_pgto_sap]]<>"", "Data de pagamento: "&TEXT(Tabela1[[#This Row],[Data_pgto_sap]],"dd/mm/aaaa"), "Chamado aberto, aguardando programação de pagamento"), IF(AND(Tabela1[[#This Row],[PEDIDO]]<>"",Tabela1[[#This Row],[NOTA]]<>""), "Aguardando autorização pgto", IF(AND(Tabela1[[#This Row],[PEDIDO]]<>"",Tabela1[[#This Row],[NOTA]]=""), "Aguardando nota", IF(AND(Tabela1[[#This Row],[PEDIDO]]="",Tabela1[[#This Row],[NOTA]]<>""), "Aguardando pedido", "Aguardando ambos")))) -> Aguardando pedido | AK2: =IF(Tabela1[[#This Row],[procx ticket]]="",Tabela1[[#This Row],[Data criação ticket]],Tabela1[[#This Row],[procx ticket]]) -> 0 | AM2: 45698 | AN2: =IFERROR( IF( Tabela1[[#This Row],[Data_pgto_sap]] <> "", "pagamento efetivado", IF( AND( Tabela1[[#This Row],[Status Result1]] = "Chamado aberto, aguardando programação de pagamento", TODAY() - Tabela1[[#This Row],[Data criação ticket br]] >= 5 ), "fora do prazo (" & (TODAY() - Tabela1[[#This Row],[Data criação ticket br]]) & " dias)", "no prazo" ) ), "") -> no prazo | AQ2: =Tabela1[[#This Row],[FILIAL]]&Tabela1[[#This Row],[ORDEM]]&Tabela1[[#This Row],[VALOR RC]]&Tabela1[[#This Row],[COORDENADOR]]&Tabela1[[#This Row],[PROJETO]]&Tabela1[[#This Row],[SERVIÇO]]&Tabela1[[#This Row],[FORNECEDOR]] -> 149160558548500ANDRELOJAS NOVASGerenciadoraHTB | AR2: #N/A
A3: =IF(B3<7000,1000,2000) -> 2000 | B3: 7161 | C3: =_xlfn.XLOOKUP(Tabela1[[#This Row],[FILIAL]],'CNPJ BASE jan25'!A:A,'CNPJ BASE jan25'!B:B) -> FOR161-AntSale-CE-EF | D3: =_xlfn.XLOOKUP(Tabela1[[#This Row],[FILIAL]],'CNPJ BASE jan25'!A:A,'CNPJ BASE jan25'!C:C) -> 04.899.316/0161-11 | E3: ADRIANO | F3: VIRADA DE BANDEIRA | G3: Luminária | H3: 96031 | I3: LUMICENTER | M3: 605999 | P3: 17339.93 | R3: =IF(Tabela1[[#This Row],[VALOR A PAGAR]]>1,Tabela1[[#This Row],[VALOR A PAGAR]],Tabela1[[#This Row],[VALOR RC]]) -> 17339.93 | S3: =IF( Tabela1[[#This Row],[PEDIDO]] <> "", "Pedido Criado", IF( AND(Tabela1[[#This Row],[REQUISIÇÃO]] = "", Tabela1[[#This Row],[PEDIDO]] = ""), "Orçamento Recebido", IF( AND(Tabela1[[#This Row],[REQUISIÇÃO]] <> "", Tabela1[[#This Row],[PEDIDO]] = "", Tabela1[[#This Row],[RC ENVIADA?]] = ""), "Requisição Feita", IF( AND(Tabela1[[#This Row],[RC ENVIADA?]] = "SIM", Tabela1[[#This Row],[REQUISIÇÃO]] <> "", Tabela1[[#This Row],[PEDIDO]] = ""), "Aguardando Pedido", "" ) ) ) ) -> Orçamento Recebido | U3: =F3 & " " & " " & B3 & " - " & I3 & " - " & "N°" & H3 & " - " & Tabela1[[#This Row],[Coluna1]] -> VIRADA DE BANDEIRA 7161 - LUMICENTER - N°96031 - aguardando orçamento, aguardando retorno adriano | X3: =IF(V3<>"","ABERTO","PENDENTE") -> PENDENTE | AA3: =IF(Tabela1[[#This Row],[CHAMADO]]="ABERTO",Tabela1[[#This Row],[procx status]],"") | AE3: =IF(Tabela1[[#This Row],[Status Result1]]="Aguardando autorização pgto", "sim","") | AF3: =IF(Tabela1[[#This Row],[ID]]<>"", IF(Tabela1[[#This Row],[Data_pgto_sap]]<>"", "Data de pagamento: "&TEXT(Tabela1[[#This Row],[Data_pgto_sap]],"dd/mm/aaaa"), "Chamado aberto, aguardando programação de pagamento"), IF(AND(Tabela1[[#This Row],[PEDIDO]]<>"",Tabela1[[#This Row],[NOTA]]<>""), "Há pedido e há nota, aguardando autorização pgto", IF(AND(Tabela1[[#This Row],[PEDIDO]]<>"",Tabela1[[#This Row],[NOTA]]=""), "Aguardando nota, há pedido", IF(AND(Tabela1[[#This Row],[PEDIDO]]="",Tabela1[[#This Row],[NOTA]]<>""), "Aguardando pedido, há nota",) ))) -> Aguardando pedido, há nota | AG3: =IF(Tabela1[[#This Row],[ID]]<>"", IF(Tabela1[[#This Row],[Data_pgto_sap]]<>"", "Data de pagamento: "&TEXT(Tabela1[[#This Row],[Data_pgto_sap]],"dd/mm/aaaa"), "Chamado aberto, aguardando programação de pagamento"), IF(AND(Tabela1[[#This Row],[PEDIDO]]<>"",Tabela1[[#This Row],[NOTA]]<>""), "Aguardando autorização pgto", IF(AND(Tabela1[[#This Row],[PEDIDO]]<>"",Tabela1[[#This Row],[NOTA]]=""), "Aguardando nota", IF(AND(Tabela1[[#This Row],[PEDIDO]]="",Tabela1[[#This Row],[NOTA]]<>""), "Aguardando pedido", "Aguardando ambos")))) -> Aguardando pedido | AK3: =IF(Tabela1[[#This Row],[procx ticket]]="",Tabela1[[#This Row],[Data criação ticket]],Tabela1[[#This Row],[procx ticket]]) -> 0 | AM3: =IF( OR( Tabela1[[#This Row],[Data criação ticket]]="", Tabela1[[#This Row],[Data criação ticket]]=0, ISERROR(DATEVALUE(Tabela1[[#This Row],[Data criação ticket]])) ), "", RIGHT(Tabela1[[#This Row],[Data criação ticket]],2) & "/" & MID(Tabela1[[#This Row],[Data criação ticket]],6,2) & "/" & LEFT(Tabela1[[#This Row],[Data criação ticket]],4) ) | AN3: =IFERROR( IF( Tabela1[[#This Row],[Data_pgto_sap]] <> "", "pagamento efetivado", IF( AND( Tabela1[[#This Row],[Status Result1]] = "Chamado aberto, aguardando programação de pagamento", TODAY() - Tabela1[[#This Row],[Data criação ticket br]] >= 5 ), "fora do prazo (" & (TODAY() - Tabela1[[#This Row],[Data criação ticket br]]) & " dias)", "no prazo" ) ), "") | AP3: aguardando orçamento, aguardando retorno adriano | AQ3: =Tabela1[[#This Row],[FILIAL]]&Tabela1[[#This Row],[ORDEM]]&Tabela1[[#This Row],[VALOR RC]]&Tabela1[[#This Row],[COORDENADOR]]&Tabela1[[#This Row],[PROJETO]]&Tabela1[[#This Row],[SERVIÇO]]&Tabela1[[#This Row],[FORNECEDOR]] -> 716160599917339,93ADRIANOVIRADA DE BANDEIRALumináriaLUMICENTER | AR3: #N/A
A4: =IF(B4<7000,1000,2000) -> 1000 | B4: 1514 | C4: COD03-Rotatoria-MA | D4: 06.626.253/1334-61 | E4: HENRIQUE | F4: LOJAS NOVAS | G4: Persianas | H4: 265 | I4: PERSUN | J4: 4 | M4: 605803 | N4: 0010024352 | P4: 2880 | R4: =IF(Tabela1[[#This Row],[VALOR A PAGAR]]>1,Tabela1[[#This Row],[VALOR A PAGAR]],Tabela1[[#This Row],[VALOR RC]]) -> 2880 | S4: =IF( Tabela1[[#This Row],[PEDIDO]] <> "", "Pedido Criado", IF( AND(Tabela1[[#This Row],[REQUISIÇÃO]] = "", Tabela1[[#This Row],[PEDIDO]] = ""), "Orçamento Recebido", IF( AND(Tabela1[[#This Row],[REQUISIÇÃO]] <> "", Tabela1[[#This Row],[PEDIDO]] = "", Tabela1[[#This Row],[RC ENVIADA?]] = ""), "Requisição Feita", IF( AND(Tabela1[[#This Row],[RC ENVIADA?]] = "SIM", Tabela1[[#This Row],[REQUISIÇÃO]] <> "", Tabela1[[#This Row],[PEDIDO]] = ""), "Aguardando Pedido", "" ) ) ) ) -> Requisição Feita | U4: =F4 & " " & " " & B4 & " - " & I4 & " - " & "N°" & H4 & " - " & Tabela1[[#This Row],[Coluna1]] -> LOJAS NOVAS 1514 - PERSUN - N°265 - | X4: =IF(V4<>"","ABERTO","PENDENTE") -> PENDENTE | AA4: =IF(Tabela1[[#This Row],[CHAMADO]]="ABERTO",Tabela1[[#This Row],[procx status]],"") | AE4: =IF(Tabela1[[#This Row],[Status Result1]]="Aguardando autorização pgto", "sim","") | AF4: =IF(Tabela1[[#This Row],[ID]]<>"", IF(Tabela1[[#This Row],[Data_pgto_sap]]<>"", "Data de pagamento: "&TEXT(Tabela1[[#This Row],[Data_pgto_sap]],"dd/mm/aaaa"), "Chamado aberto, aguardando programação de pagamento"), IF(AND(Tabela1[[#This Row],[PEDIDO]]<>"",Tabela1[[#This Row],[NOTA]]<>""), "Há pedido e há nota, aguardando autorização pgto", IF(AND(Tabela1[[#This Row],[PEDIDO]]<>"",Tabela1[[#This Row],[NOTA]]=""), "Aguardando nota, há pedido", IF(AND(Tabela1[[#This Row],[PEDIDO]]="",Tabela1[[#This Row],[NOTA]]<>""), "Aguardando pedido, há nota",) ))) -> Aguardando pedido, há nota | AG4: =IF(Tabela1[[#This Row],[ID]]<>"", IF(Tabela1[[#This Row],[Data_pgto_sap]]<>"", "Data de pagamento: "&TEXT(Tabela1[[#This Row],[Data_pgto_sap]],"dd/mm/aaaa"), "Chamado aberto, aguardando programação de pagamento"), IF(AND(Tabela1[[#This Row],[PEDIDO]]<>"",Tabela1[[#This Row],[NOTA]]<>""), "Aguardando autorização pgto", IF(AND(Tabela1[[#This Row],[PEDIDO]]<>"",Tabela1[[#This Row],[NOTA]]=""), "Aguardando nota", IF(AND(Tabela1[[#This Row],[PEDIDO]]="",Tabela1[[#This Row],[NOTA]]<>""), "Aguardando pedido", "Aguardando ambos")))) -> Aguardando pedido | AK4: =IF(Tabela1[[#This Row],[procx ticket]]="",Tabela1[[#This Row],[Data criação ticket]],Tabela1[[#This Row],[procx ticket]]) -> 0 | AM4: =IF( OR( Tabela1[[#This Row],[Data criação ticket]]="", Tabela1[[#This Row],[Data criação ticket]]=0, ISERROR(DATEVALUE(Tabela1[[#This Row],[Data criação ticket]])) ), "", RIGHT(Tabela1[[#This Row],[Data criação ticket]],2) & "/" & MID(Tabela1[[#This Row],[Data criação ticket]],6,2) & "/" & LEFT(Tabela1[[#This Row],[Data criação ticket]],4) ) | AN4: =IFERROR( IF( Tabela1[[#This Row],[Data_pgto_sap]] <> "", "pagamento efetivado", IF( AND( Tabela1[[#This Row],[Status Result1]] = "Chamado aberto, aguardando programação de pagamento", TODAY() - Tabela1[[#This Row],[Data criação ticket br]] >= 5 ), "fora do prazo (" & (TODAY() - Tabela1[[#This Row],[Data criação ticket br]]) & " dias)", "no prazo" ) ), "") | AQ4: =Tabela1[[#This Row],[FILIAL]]&Tabela1[[#This Row],[ORDEM]]&Tabela1[[#This Row],[VALOR RC]]&Tabela1[[#This Row],[COORDENADOR]]&Tabela1[[#This Row],[PROJETO]]&Tabela1[[#This Row],[SERVIÇO]]&Tabela1[[#This Row],[FORNECEDOR]] -> 15146058032880HENRIQUELOJAS NOVASPersianasPERSUN | AR4: #N/A
A5: =IF(B5<7000,1000,2000) -> 2000 | B5: 7174 | C5: =_xlfn.XLOOKUP(Tabela1[[#This Row],[FILIAL]],'CNPJ BASE jan25'!A:A,'CNPJ BASE jan25'!B:B) -> SLU58-JoMiJo21-MA-EF | D5: =_xlfn.XLOOKUP(Tabela1[[#This Row],[FILIAL]],'CNPJ BASE jan25'!A:A,'CNPJ BASE jan25'!C:C) -> 04.899.316/0174-36 | E5: HENRIQUE | F5: VIRADA DE BANDEIRA | G5: Persianas | H5: 264 | I5: PERSUN | J5: 13 | M5: 606037 | P5: 4980 | R5: =IF(Tabela1[[#This Row],[VALOR A PAGAR]]>1,Tabela1[[#This Row],[VALOR A PAGAR]],Tabela1[[#This Row],[VALOR RC]]) -> 4980 | S5: =IF( Tabela1[[#This Row],[PEDIDO]] <> "", "Pedido Criado", IF( AND(Tabela1[[#This Row],[REQUISIÇÃO]] = "", Tabela1[[#This Row],[PEDIDO]] = ""), "Orçamento Recebido", IF( AND(Tabela1[[#This Row],[REQUISIÇÃO]] <> "", Tabela1[[#This Row],[PEDIDO]] = "", Tabela1[[#This Row],[RC ENVIADA?]] = ""), "Requisição Feita", IF( AND(Tabela1[[#This Row],[RC ENVIADA?]] = "SIM", Tabela1[[#This Row],[REQUISIÇÃO]] <> "", Tabela1[[#This Row],[PEDIDO]] = ""), "Aguardando Pedido", "" ) ) ) ) -> Orçamento Recebido | U5: =F5 & " " & " " & B5 & " - " & I5 & " - " & "N°" & H5 & " - " & Tabela1[[#This Row],[Coluna1]] -> VIRADA DE BANDEIRA 7174 - PERSUN - N°264 - VENC 07/02/2026 suplementar 4900 | X5: =IF(V5<>"","ABERTO","PENDENTE") -> PENDENTE | AA5: =IF(Tabela1[[#This Row],[CHAMADO]]="ABERTO",Tabela1[[#This Row],[procx status]],"") | AE5: =IF(Tabela1[[#This Row],[Status Result1]]="Aguardando autorização pgto", "sim","") | AF5: =IF(Tabela1[[#This Row],[ID]]<>"", IF(Tabela1[[#This Row],[Data_pgto_sap]]<>"", "Data de pagamento: "&TEXT(Tabela1[[#This Row],[Data_pgto_sap]],"dd/mm/aaaa"), "Chamado aberto, aguardando programação de pagamento"), IF(AND(Tabela1[[#This Row],[PEDIDO]]<>"",Tabela1[[#This Row],[NOTA]]<>""), "Há pedido e há nota, aguardando autorização pgto", IF(AND(Tabela1[[#This Row],[PEDIDO]]<>"",Tabela1[[#This Row],[NOTA]]=""), "Aguardando nota, há pedido", IF(AND(Tabela1[[#This Row],[PEDIDO]]="",Tabela1[[#This Row],[NOTA]]<>""), "Aguardando pedido, há nota",) ))) -> Aguardando pedido, há nota | AG5: =IF(Tabela1[[#This Row],[ID]]<>"", IF(Tabela1[[#This Row],[Data_pgto_sap]]<>"", "Data de pagamento: "&TEXT(Tabela1[[#This Row],[Data_pgto_sap]],"dd/mm/aaaa"), "Chamado aberto, aguardando programação de pagamento"), IF(AND(Tabela1[[#This Row],[PEDIDO]]<>"",Tabela1[[#This Row],[NOTA]]<>""), "Aguardando autorização pgto", IF(AND(Tabela1[[#This Row],[PEDIDO]]<>"",Tabela1[[#This Row],[NOTA]]=""), "Aguardando nota", IF(AND(Tabela1[[#This Row],[PEDIDO]]="",Tabela1[[#This Row],[NOTA]]<>""), "Aguardando pedido", "Aguardando ambos")))) -> Aguardando pedido | AK5: =IF(Tabela1[[#This Row],[procx ticket]]="",Tabela1[[#This Row],[Data criação ticket]],Tabela1[[#This Row],[procx ticket]]) -> 0 | AM5: =IF( OR( Tabela1[[#This Row],[Data criação ticket]]="", Tabela1[[#This Row],[Data criação ticket]]=0, ISERROR(DATEVALUE(Tabela1[[#This Row],[Data criação ticket]])) ), "", RIGHT(Tabela1[[#This Row],[Data criação ticket]],2) & "/" & MID(Tabela1[[#This Row],[Data criação ticket]],6,2) & "/" & LEFT(Tabela1[[#This Row],[Data criação ticket]],4) ) | AN5: =IFERROR( IF( Tabela1[[#This Row],[Data_pgto_sap]] <> "", "pagamento efetivado", IF( AND( Tabela1[[#This Row],[Status Result1]] = "Chamado aberto, aguardando programação de pagamento", TODAY() - Tabela1[[#This Row],[Data criação ticket br]] >= 5 ), "fora do prazo (" & (TODAY() - Tabela1[[#This Row],[Data criação ticket br]]) & " dias)", "no prazo" ) ), "") | AP5: VENC 07/02/2026 suplementar 4900 | AQ5: =Tabela1[[#This Row],[FILIAL]]&Tabela1[[#This Row],[ORDEM]]&Tabela1[[#This Row],[VALOR RC]]&Tabela1[[#This Row],[COORDENADOR]]&Tabela1[[#This Row],[PROJETO]]&Tabela1[[#This Row],[SERVIÇO]]&Tabela1[[#This Row],[FORNECEDOR]] -> 71746060374980HENRIQUEVIRADA DE BANDEIRAPersianasPERSUN | AR5: #N/A
A6: =IF(B6<7000,1000,2000) -> 2000 | B6: 7045 | C6: =_xlfn.XLOOKUP(Tabela1[[#This Row],[FILIAL]],'CNPJ BASE jan25'!A:A,'CNPJ BASE jan25'!B:B) -> SLU36-JoaPesso-MA-EF | D6: =_xlfn.XLOOKUP(Tabela1[[#This Row],[FILIAL]],'CNPJ BASE jan25'!A:A,'CNPJ BASE jan25'!C:C) -> 04.899.316/0045-39 | E6: HENRIQUE | F6: VIRADA DE BANDEIRA | G6: REFORMA | I6: DWA | J6: 1 | M6: 606029 | P6: 59966.33 | R6: =IF(Tabela1[[#This Row],[VALOR A PAGAR]]>1,Tabela1[[#This Row],[VALOR A PAGAR]],Tabela1[[#This Row],[VALOR RC]]) -> 59966.33 | S6: =IF( Tabela1[[#This Row],[PEDIDO]] <> "", "Pedido Criado", IF( AND(Tabela1[[#This Row],[REQUISIÇÃO]] = "", Tabela1[[#This Row],[PEDIDO]] = ""), "Orçamento Recebido", IF( AND(Tabela1[[#This Row],[REQUISIÇÃO]] <> "", Tabela1[[#This Row],[PEDIDO]] = "", Tabela1[[#This Row],[RC ENVIADA?]] = ""), "Requisição Feita", IF( AND(Tabela1[[#This Row],[RC ENVIADA?]] = "SIM", Tabela1[[#This Row],[REQUISIÇÃO]] <> "", Tabela1[[#This Row],[PEDIDO]] = ""), "Aguardando Pedido", "" ) ) ) ) -> Orçamento Recebido | U6: =F6 & " " & " " & B6 & " - " & I6 & " - " & "N°" & H6 & " - " & Tabela1[[#This Row],[Coluna1]] -> VIRADA DE BANDEIRA 7045 - DWA - N° - fazer em 26 | X6: =IF(V6<>"","ABERTO","PENDENTE") -> PENDENTE | AA6: =IF(Tabela1[[#This Row],[CHAMADO]]="ABERTO",Tabela1[[#This Row],[procx status]],"") | AE6: =IF(Tabela1[[#This Row],[Status Result1]]="Aguardando autorização pgto", "sim","") | AF6: =IF(Tabela1[[#This Row],[ID]]<>"", IF(Tabela1[[#This Row],[Data_pgto_sap]]<>"", "Data de pagamento: "&TEXT(Tabela1[[#This Row],[Data_pgto_sap]],"dd/mm/aaaa"), "Chamado aberto, aguardando programação de pagamento"), IF(AND(Tabela1[[#This Row],[PEDIDO]]<>"",Tabela1[[#This Row],[NOTA]]<>""), "Há pedido e há nota, aguardando autorização pgto", IF(AND(Tabela1[[#This Row],[PEDIDO]]<>"",Tabela1[[#This Row],[NOTA]]=""), "Aguardando nota, há pedido", IF(AND(Tabela1[[#This Row],[PEDIDO]]="",Tabela1[[#This Row],[NOTA]]<>""), "Aguardando pedido, há nota",) ))) -> 0 | AG6: =IF(Tabela1[[#This Row],[ID]]<>"", IF(Tabela1[[#This Row],[Data_pgto_sap]]<>"", "Data de pagamento: "&TEXT(Tabela1[[#This Row],[Data_pgto_sap]],"dd/mm/aaaa"), "Chamado aberto, aguardando programação de pagamento"), IF(AND(Tabela1[[#This Row],[PEDIDO]]<>"",Tabela1[[#This Row],[NOTA]]<>""), "Aguardando autorização pgto", IF(AND(Tabela1[[#This Row],[PEDIDO]]<>"",Tabela1[[#This Row],[NOTA]]=""), "Aguardando nota", IF(AND(Tabela1[[#This Row],[PEDIDO]]="",Tabela1[[#This Row],[NOTA]]<>""), "Aguardando pedido", "Aguardando ambos")))) -> Aguardando ambos | AK6: =IF(Tabela1[[#This Row],[procx ticket]]="",Tabela1[[#This Row],[Data criação ticket]],Tabela1[[#This Row],[procx ticket]]) -> 0 | AM6: =IF( OR( Tabela1[[#This Row],[Data criação ticket]]="", Tabela1[[#This Row],[Data criação ticket]]=0, ISERROR(DATEVALUE(Tabela1[[#This Row],[Data criação ticket]])) ), "", RIGHT(Tabela1[[#This Row],[Data criação ticket]],2) & "/" & MID(Tabela1[[#This Row],[Data criação ticket]],6,2) & "/" & LEFT(Tabela1[[#This Row],[Data criação ticket]],4) ) | AN6: =IFERROR( IF( Tabela1[[#This Row],[Data_pgto_sap]] <> "", "pagamento efetivado", IF( AND( Tabela1[[#This Row],[Status Result1]] = "Chamado aberto, aguardando programação de pagamento", TODAY() - Tabela1[[#This Row],[Data criação ticket br]] >= 5 ), "fora do prazo (" & (TODAY() - Tabela1[[#This Row],[Data criação ticket br]]) & " dias)", "no prazo" ) ), "") | AP6: fazer em 26 | AQ6: =Tabela1[[#This Row],[FILIAL]]&Tabela1[[#This Row],[ORDEM]]&Tabela1[[#This Row],[VALOR RC]]&Tabela1[[#This Row],[COORDENADOR]]&Tabela1[[#This Row],[PROJETO]]&Tabela1[[#This Row],[SERVIÇO]]&Tabela1[[#This Row],[FORNECEDOR]] -> 704560602959966,33HENRIQUEVIRADA DE BANDEIRAREFORMADWA | AR6: #N/A
A7: =IF(B7<7000,1000,2000) -> 2000 | B7: 7050 | C7: =_xlfn.XLOOKUP(Tabela1[[#This Row],[FILIAL]],'CNPJ BASE jan25'!A:A,'CNPJ BASE jan25'!B:B) -> SLU38-GetVarga-MA-EF | D7: =_xlfn.XLOOKUP(Tabela1[[#This Row],[FILIAL]],'CNPJ BASE jan25'!A:A,'CNPJ BASE jan25'!C:C) -> 04.899.316/0050-04 | E7: HENRIQUE | F7: VIRADA DE BANDEIRA | G7: REFORMA | I7: DWA | J7: 2 | M7: 606030 | P7: 95704.1 | R7: =IF(Tabela1[[#This Row],[VALOR A PAGAR]]>1,Tabela1[[#This Row],[VALOR A PAGAR]],Tabela1[[#This Row],[VALOR RC]]) -> 95704.1 | S7: =IF( Tabela1[[#This Row],[PEDIDO]] <> "", "Pedido Criado", IF( AND(Tabela1[[#This Row],[REQUISIÇÃO]] = "", Tabela1[[#This Row],[PEDIDO]] = ""), "Orçamento Recebido", IF( AND(Tabela1[[#This Row],[REQUISIÇÃO]] <> "", Tabela1[[#This Row],[PEDIDO]] = "", Tabela1[[#This Row],[RC ENVIADA?]] = ""), "Requisição Feita", IF( AND(Tabela1[[#This Row],[RC ENVIADA?]] = "SIM", Tabela1[[#This Row],[REQUISIÇÃO]] <> "", Tabela1[[#This Row],[PEDIDO]] = ""), "Aguardando Pedido", "" ) ) ) ) -> Orçamento Recebido | U7: =F7 & " " & " " & B7 & " - " & I7 & " - " & "N°" & H7 & " - " & Tabela1[[#This Row],[Coluna1]] -> VIRADA DE BANDEIRA 7050 - DWA - N° - fazer em 26 | X7: =IF(V7<>"","ABERTO","PENDENTE") -> PENDENTE | AA7: =IF(Tabela1[[#This Row],[CHAMADO]]="ABERTO",Tabela1[[#This Row],[procx status]],"") | AE7: =IF(Tabela1[[#This Row],[Status Result1]]="Aguardando autorização pgto", "sim","") | AF7: =IF(Tabela1[[#This Row],[ID]]<>"", IF(Tabela1[[#This Row],[Data_pgto_sap]]<>"", "Data de pagamento: "&TEXT(Tabela1[[#This Row],[Data_pgto_sap]],"dd/mm/aaaa"), "Chamado aberto, aguardando programação de pagamento"), IF(AND(Tabela1[[#This Row],[PEDIDO]]<>"",Tabela1[[#This Row],[NOTA]]<>""), "Há pedido e há nota, aguardando autorização pgto", IF(AND(Tabela1[[#This Row],[PEDIDO]]<>"",Tabela1[[#This Row],[NOTA]]=""), "Aguardando nota, há pedido", IF(AND(Tabela1[[#This Row],[PEDIDO]]="",Tabela1[[#This Row],[NOTA]]<>""), "Aguardando pedido, há nota",) ))) -> 0 | AG7: =IF(Tabela1[[#This Row],[ID]]<>"", IF(Tabela1[[#This Row],[Data_pgto_sap]]<>"", "Data de pagamento: "&TEXT(Tabela1[[#This Row],[Data_pgto_sap]],"dd/mm/aaaa"), "Chamado aberto, aguardando programação de pagamento"), IF(AND(Tabela1[[#This Row],[PEDIDO]]<>"",Tabela1[[#This Row],[NOTA]]<>""), "Aguardando autorização pgto", IF(AND(Tabela1[[#This Row],[PEDIDO]]<>"",Tabela1[[#This Row],[NOTA]]=""), "Aguardando nota", IF(AND(Tabela1[[#This Row],[PEDIDO]]="",Tabela1[[#This Row],[NOTA]]<>""), "Aguardando pedido", "Aguardando ambos")))) -> Aguardando ambos | AK7: =IF(Tabela1[[#This Row],[procx ticket]]="",Tabela1[[#This Row],[Data criação ticket]],Tabela1[[#This Row],[procx ticket]]) -> 0 | AM7: =IF( OR( Tabela1[[#This Row],[Data criação ticket]]="", Tabela1[[#This Row],[Data criação ticket]]=0, ISERROR(DATEVALUE(Tabela1[[#This Row],[Data criação ticket]])) ), "", RIGHT(Tabela1[[#This Row],[Data criação ticket]],2) & "/" & MID(Tabela1[[#This Row],[Data criação ticket]],6,2) & "/" & LEFT(Tabela1[[#This Row],[Data criação ticket]],4) ) | AN7: =IFERROR( IF( Tabela1[[#This Row],[Data_pgto_sap]] <> "", "pagamento efetivado", IF( AND( Tabela1[[#This Row],[Status Result1]] = "Chamado aberto, aguardando programação de pagamento", TODAY() - Tabela1[[#This Row],[Data criação ticket br]] >= 5 ), "fora do prazo (" & (TODAY() - Tabela1[[#This Row],[Data criação ticket br]]) & " dias)", "no prazo" ) ), "") | AP7: fazer em 26 | AQ7: =Tabela1[[#This Row],[FILIAL]]&Tabela1[[#This Row],[ORDEM]]&Tabela1[[#This Row],[VALOR RC]]&Tabela1[[#This Row],[COORDENADOR]]&Tabela1[[#This Row],[PROJETO]]&Tabela1[[#This Row],[SERVIÇO]]&Tabela1[[#This Row],[FORNECEDOR]] -> 705060603095704,1HENRIQUEVIRADA DE BANDEIRAREFORMADWA | AR7: #N/A
A8: =IF(B8<7000,1000,2000) -> 2000 | B8: 7054 | C8: =_xlfn.XLOOKUP(Tabela1[[#This Row],[FILIAL]],'CNPJ BASE jan25'!A:A,'CNPJ BASE jan25'!B:B) -> SLU45-ColMor49-MA-EF | D8: =_xlfn.XLOOKUP(Tabela1[[#This Row],[FILIAL]],'CNPJ BASE jan25'!A:A,'CNPJ BASE jan25'!C:C) -> 04.899.316/0054-20 | E8: HENRIQUE | F8: VIRADA DE BANDEIRA | G8: REFORMA | I8: DWA | J8: 3 | M8: 605161 | P8: 21302.18 | R8: =IF(Tabela1[[#This Row],[VALOR A PAGAR]]>1,Tabela1[[#This Row],[VALOR A PAGAR]],Tabela1[[#This Row],[VALOR RC]]) -> 21302.18 | S8: =IF( Tabela1[[#This Row],[PEDIDO]] <> "", "Pedido Criado", IF( AND(Tabela1[[#This Row],[REQUISIÇÃO]] = "", Tabela1[[#This Row],[PEDIDO]] = ""), "Orçamento Recebido", IF( AND(Tabela1[[#This Row],[REQUISIÇÃO]] <> "", Tabela1[[#This Row],[PEDIDO]] = "", Tabela1[[#This Row],[RC ENVIADA?]] = ""), "Requisição Feita", IF( AND(Tabela1[[#This Row],[RC ENVIADA?]] = "SIM", Tabela1[[#This Row],[REQUISIÇÃO]] <> "", Tabela1[[#This Row],[PEDIDO]] = ""), "Aguardando Pedido", "" ) ) ) ) -> Orçamento Recebido | U8: =F8 & " " & " " & B8 & " - " & I8 & " - " & "N°" & H8 & " - " & Tabela1[[#This Row],[Coluna1]] -> VIRADA DE BANDEIRA 7054 - DWA - N° - fazer em 26 | X8: =IF(V8<>"","ABERTO","PENDENTE") -> PENDENTE | AA8: =IF(Tabela1[[#This Row],[CHAMADO]]="ABERTO",Tabela1[[#This Row],[procx status]],"") | AE8: =IF(Tabela1[[#This Row],[Status Result1]]="Aguardando autorização pgto", "sim","") | AF8: =IF(Tabela1[[#This Row],[ID]]<>"", IF(Tabela1[[#This Row],[Data_pgto_sap]]<>"", "Data de pagamento: "&TEXT(Tabela1[[#This Row],[Data_pgto_sap]],"dd/mm/aaaa"), "Chamado aberto, aguardando programação de pagamento"), IF(AND(Tabela1[[#This Row],[PEDIDO]]<>"",Tabela1[[#This Row],[NOTA]]<>""), "Há pedido e há nota, aguardando autorização pgto", IF(AND(Tabela1[[#This Row],[PEDIDO]]<>"",Tabela1[[#This Row],[NOTA]]=""), "Aguardando nota, há pedido", IF(AND(Tabela1[[#This Row],[PEDIDO]]="",Tabela1[[#This Row],[NOTA]]<>""), "Aguardando pedido, há nota",) ))) -> 0 | AG8: =IF(Tabela1[[#This Row],[ID]]<>"", IF(Tabela1[[#This Row],[Data_pgto_sap]]<>"", "Data de pagamento: "&TEXT(Tabela1[[#This Row],[Data_pgto_sap]],"dd/mm/aaaa"), "Chamado aberto, aguardando programação de pagamento"), IF(AND(Tabela1[[#This Row],[PEDIDO]]<>"",Tabela1[[#This Row],[NOTA]]<>""), "Aguardando autorização pgto", IF(AND(Tabela1[[#This Row],[PEDIDO]]<>"",Tabela1[[#This Row],[NOTA]]=""), "Aguardando nota", IF(AND(Tabela1[[#This Row],[PEDIDO]]="",Tabela1[[#This Row],[NOTA]]<>""), "Aguardando pedido", "Aguardando ambos")))) -> Aguardando ambos | AK8: =IF(Tabela1[[#This Row],[procx ticket]]="",Tabela1[[#This Row],[Data criação ticket]],Tabela1[[#This Row],[procx ticket]]) -> 0 | AM8: =IF( OR( Tabela1[[#This Row],[Data criação ticket]]="", Tabela1[[#This Row],[Data criação ticket]]=0, ISERROR(DATEVALUE(Tabela1[[#This Row],[Data criação ticket]])) ), "", RIGHT(Tabela1[[#This Row],[Data criação ticket]],2) & "/" & MID(Tabela1[[#This Row],[Data criação ticket]],6,2) & "/" & LEFT(Tabela1[[#This Row],[Data criação ticket]],4) ) | AN8: =IFERROR( IF( Tabela1[[#This Row],[Data_pgto_sap]] <> "", "pagamento efetivado", IF( AND( Tabela1[[#This Row],[Status Result1]] = "Chamado aberto, aguardando programação de pagamento", TODAY() - Tabela1[[#This Row],[Data criação ticket br]] >= 5 ), "fora do prazo (" & (TODAY() - Tabela1[[#This Row],[Data criação ticket br]]) & " dias)", "no prazo" ) ), "") | AP8: fazer em 26 | AQ8: =Tabela1[[#This Row],[FILIAL]]&Tabela1[[#This Row],[ORDEM]]&Tabela1[[#This Row],[VALOR RC]]&Tabela1[[#This Row],[COORDENADOR]]&Tabela1[[#This Row],[PROJETO]]&Tabela1[[#This Row],[SERVIÇO]]&Tabela1[[#This Row],[FORNECEDOR]] -> 705460516121302,18HENRIQUEVIRADA DE BANDEIRAREFORMADWA | AR8: #N/A
A9: =IF(B9<7000,1000,2000) -> 2000 | B9: 7126 | C9: =_xlfn.XLOOKUP(Tabela1[[#This Row],[FILIAL]],'CNPJ BASE jan25'!A:A,'CNPJ BASE jan25'!B:B) -> SLU51-Principa-MA-EF | D9: =_xlfn.XLOOKUP(Tabela1[[#This Row],[FILIAL]],'CNPJ BASE jan25'!A:A,'CNPJ BASE jan25'!C:C) -> 04.899.316/0126-39 | E9: HENRIQUE | F9: VIRADA DE BANDEIRA | G9: REFORMA | I9: DWA | J9: 4 | M9: 606032 | P9: 49981.42 | R9: =IF(Tabela1[[#This Row],[VALOR A PAGAR]]>1,Tabela1[[#This Row],[VALOR A PAGAR]],Tabela1[[#This Row],[VALOR RC]]) -> 49981.42 | S9: =IF( Tabela1[[#This Row],[PEDIDO]] <> "", "Pedido Criado", IF( AND(Tabela1[[#This Row],[REQUISIÇÃO]] = "", Tabela1[[#This Row],[PEDIDO]] = ""), "Orçamento Recebido", IF( AND(Tabela1[[#This Row],[REQUISIÇÃO]] <> "", Tabela1[[#This Row],[PEDIDO]] = "", Tabela1[[#This Row],[RC ENVIADA?]] = ""), "Requisição Feita", IF( AND(Tabela1[[#This Row],[RC ENVIADA?]] = "SIM", Tabela1[[#This Row],[REQUISIÇÃO]] <> "", Tabela1[[#This Row],[PEDIDO]] = ""), "Aguardando Pedido", "" ) ) ) ) -> Orçamento Recebido | U9: =F9 & " " & " " & B9 & " - " & I9 & " - " & "N°" & H9 & " - " & Tabela1[[#This Row],[Coluna1]] -> VIRADA DE BANDEIRA 7126 - DWA - N° - fazer em 26 | X9: =IF(V9<>"","ABERTO","PENDENTE") -> PENDENTE | AA9: =IF(Tabela1[[#This Row],[CHAMADO]]="ABERTO",Tabela1[[#This Row],[procx status]],"") | AE9: =IF(Tabela1[[#This Row],[Status Result1]]="Aguardando autorização pgto", "sim","") | AF9: =IF(Tabela1[[#This Row],[ID]]<>"", IF(Tabela1[[#This Row],[Data_pgto_sap]]<>"", "Data de pagamento: "&TEXT(Tabela1[[#This Row],[Data_pgto_sap]],"dd/mm/aaaa"), "Chamado aberto, aguardando programação de pagamento"), IF(AND(Tabela1[[#This Row],[PEDIDO]]<>"",Tabela1[[#This Row],[NOTA]]<>""), "Há pedido e há nota, aguardando autorização pgto", IF(AND(Tabela1[[#This Row],[PEDIDO]]<>"",Tabela1[[#This Row],[NOTA]]=""), "Aguardando nota, há pedido", IF(AND(Tabela1[[#This Row],[PEDIDO]]="",Tabela1[[#This Row],[NOTA]]<>""), "Aguardando pedido, há nota",) ))) -> 0 | AG9: =IF(Tabela1[[#This Row],[ID]]<>"", IF(Tabela1[[#This Row],[Data_pgto_sap]]<>"", "Data de pagamento: "&TEXT(Tabela1[[#This Row],[Data_pgto_sap]],"dd/mm/aaaa"), "Chamado aberto, aguardando programação de pagamento"), IF(AND(Tabela1[[#This Row],[PEDIDO]]<>"",Tabela1[[#This Row],[NOTA]]<>""), "Aguardando autorização pgto", IF(AND(Tabela1[[#This Row],[PEDIDO]]<>"",Tabela1[[#This Row],[NOTA]]=""), "Aguardando nota", IF(AND(Tabela1[[#This Row],[PEDIDO]]="",Tabela1[[#This Row],[NOTA]]<>""), "Aguardando pedido", "Aguardando ambos")))) -> Aguardando ambos | AK9: =IF(Tabela1[[#This Row],[procx ticket]]="",Tabela1[[#This Row],[Data criação ticket]],Tabela1[[#This Row],[procx ticket]]) -> 0 | AM9: =IF( OR( Tabela1[[#This Row],[Data criação ticket]]="", Tabela1[[#This Row],[Data criação ticket]]=0, ISERROR(DATEVALUE(Tabela1[[#This Row],[Data criação ticket]])) ), "", RIGHT(Tabela1[[#This Row],[Data criação ticket]],2) & "/" & MID(Tabela1[[#This Row],[Data criação ticket]],6,2) & "/" & LEFT(Tabela1[[#This Row],[Data criação ticket]],4) ) | AN9: =IFERROR( IF( Tabela1[[#This Row],[Data_pgto_sap]] <> "", "pagamento efetivado", IF( AND( Tabela1[[#This Row],[Status Result1]] = "Chamado aberto, aguardando programação de pagamento", TODAY() - Tabela1[[#This Row],[Data criação ticket br]] >= 5 ), "fora do prazo (" & (TODAY() - Tabela1[[#This Row],[Data criação ticket br]]) & " dias)", "no prazo" ) ), "") | AP9: fazer em 26 | AQ9: =Tabela1[[#This Row],[FILIAL]]&Tabela1[[#This Row],[ORDEM]]&Tabela1[[#This Row],[VALOR RC]]&Tabela1[[#This Row],[COORDENADOR]]&Tabela1[[#This Row],[PROJETO]]&Tabela1[[#This Row],[SERVIÇO]]&Tabela1[[#This Row],[FORNECEDOR]] -> 712660603249981,42HENRIQUEVIRADA DE BANDEIRAREFORMADWA | AR9: #N/A
A10: =IF(B10<7000,1000,2000) -> 2000 | B10: 7129 | C10: =_xlfn.XLOOKUP(Tabela1[[#This Row],[FILIAL]],'CNPJ BASE jan25'!A:A,'CNPJ BASE jan25'!B:B) -> SLU54-DoAraQ52-MA-EF | D10: =_xlfn.XLOOKUP(Tabela1[[#This Row],[FILIAL]],'CNPJ BASE jan25'!A:A,'CNPJ BASE jan25'!C:C) -> 04.899.316/0129-81 | E10: HENRIQUE | F10: VIRADA DE BANDEIRA | G10: REFORMA | I10: DWA | J10: 6 | M10: 606034 | P10: 79000.84 | R10: =IF(Tabela1[[#This Row],[VALOR A PAGAR]]>1,Tabela1[[#This Row],[VALOR A PAGAR]],Tabela1[[#This Row],[VALOR RC]]) -> 79000.84 | S10: =IF( Tabela1[[#This Row],[PEDIDO]] <> "", "Pedido Criado", IF( AND(Tabela1[[#This Row],[REQUISIÇÃO]] = "", Tabela1[[#This Row],[PEDIDO]] = ""), "Orçamento Recebido", IF( AND(Tabela1[[#This Row],[REQUISIÇÃO]] <> "", Tabela1[[#This Row],[PEDIDO]] = "", Tabela1[[#This Row],[RC ENVIADA?]] = ""), "Requisição Feita", IF( AND(Tabela1[[#This Row],[RC ENVIADA?]] = "SIM", Tabela1[[#This Row],[REQUISIÇÃO]] <> "", Tabela1[[#This Row],[PEDIDO]] = ""), "Aguardando Pedido", "" ) ) ) ) -> Orçamento Recebido | U10: =F10 & " " & " " & B10 & " - " & I10 & " - " & "N°" & H10 & " - " & Tabela1[[#This Row],[Coluna1]] -> VIRADA DE BANDEIRA 7129 - DWA - N° - fazer em 26 | X10: =IF(V10<>"","ABERTO","PENDENTE") -> PENDENTE | AA10: =IF(Tabela1[[#This Row],[CHAMADO]]="ABERTO",Tabela1[[#This Row],[procx status]],"") | AE10: =IF(Tabela1[[#This Row],[Status Result1]]="Aguardando autorização pgto", "sim","") | AF10: =IF(Tabela1[[#This Row],[ID]]<>"", IF(Tabela1[[#This Row],[Data_pgto_sap]]<>"", "Data de pagamento: "&TEXT(Tabela1[[#This Row],[Data_pgto_sap]],"dd/mm/aaaa"), "Chamado aberto, aguardando programação de pagamento"), IF(AND(Tabela1[[#This Row],[PEDIDO]]<>"",Tabela1[[#This Row],[NOTA]]<>""), "Há pedido e há nota, aguardando autorização pgto", IF(AND(Tabela1[[#This Row],[PEDIDO]]<>"",Tabela1[[#This Row],[NOTA]]=""), "Aguardando nota, há pedido", IF(AND(Tabela1[[#This Row],[PEDIDO]]="",Tabela1[[#This Row],[NOTA]]<>""), "Aguardando pedido, há nota",) ))) -> 0 | AG10: =IF(Tabela1[[#This Row],[ID]]<>"", IF(Tabela1[[#This Row],[Data_pgto_sap]]<>"", "Data de pagamento: "&TEXT(Tabela1[[#This Row],[Data_pgto_sap]],"dd/mm/aaaa"), "Chamado aberto, aguardando programação de pagamento"), IF(AND(Tabela1[[#This Row],[PEDIDO]]<>"",Tabela1[[#This Row],[NOTA]]<>""), "Aguardando autorização pgto", IF(AND(Tabela1[[#This Row],[PEDIDO]]<>"",Tabela1[[#This Row],[NOTA]]=""), "Aguardando nota", IF(AND(Tabela1[[#This Row],[PEDIDO]]="",Tabela1[[#This Row],[NOTA]]<>""), "Aguardando pedido", "Aguardando ambos")))) -> Aguardando ambos | AK10: =IF(Tabela1[[#This Row],[procx ticket]]="",Tabela1[[#This Row],[Data criação ticket]],Tabela1[[#This Row],[procx ticket]]) -> 0 | AM10: =IF( OR( Tabela1[[#This Row],[Data criação ticket]]="", Tabela1[[#This Row],[Data criação ticket]]=0, ISERROR(DATEVALUE(Tabela1[[#This Row],[Data criação ticket]])) ), "", RIGHT(Tabela1[[#This Row],[Data criação ticket]],2) & "/" & MID(Tabela1[[#This Row],[Data criação ticket]],6,2) & "/" & LEFT(Tabela1[[#This Row],[Data criação ticket]],4) ) | AN10: =IFERROR( IF( Tabela1[[#This Row],[Data_pgto_sap]] <> "", "pagamento efetivado", IF( AND( Tabela1[[#This Row],[Status Result1]] = "Chamado aberto, aguardando programação de pagamento", TODAY() - Tabela1[[#This Row],[Data criação ticket br]] >= 5 ), "fora do prazo (" & (TODAY() - Tabela1[[#This Row],[Data criação ticket br]]) & " dias)", "no prazo" ) ), "") | AP10: fazer em 26 | AQ10: =Tabela1[[#This Row],[FILIAL]]&Tabela1[[#This Row],[ORDEM]]&Tabela1[[#This Row],[VALOR RC]]&Tabela1[[#This Row],[COORDENADOR]]&Tabela1[[#This Row],[PROJETO]]&Tabela1[[#This Row],[SERVIÇO]]&Tabela1[[#This Row],[FORNECEDOR]] -> 712960603479000,84HENRIQUEVIRADA DE BANDEIRAREFORMADWA | AR10: #N/A
A11: =IF(B11<7000,1000,2000) -> 2000 | B11: 7132 | C11: =_xlfn.XLOOKUP(Tabela1[[#This Row],[FILIAL]],'CNPJ BASE jan25'!A:A,'CNPJ BASE jan25'!B:B) -> SLU52-Mitra9-MA-EF | D11: =_xlfn.XLOOKUP(Tabela1[[#This Row],[FILIAL]],'CNPJ BASE jan25'!A:A,'CNPJ BASE jan25'!C:C) -> 04.899.316/0132-87 | E11: HENRIQUE | F11: VIRADA DE BANDEIRA | G11: REFORMA | I11: DWA | M11: 606035 | P11: 54771.19 | R11: =IF(Tabela1[[#This Row],[VALOR A PAGAR]]>1,Tabela1[[#This Row],[VALOR A PAGAR]],Tabela1[[#This Row],[VALOR RC]]) -> 54771.19 | S11: =IF( Tabela1[[#This Row],[PEDIDO]] <> "", "Pedido Criado", IF( AND(Tabela1[[#This Row],[REQUISIÇÃO]] = "", Tabela1[[#This Row],[PEDIDO]] = ""), "Orçamento Recebido", IF( AND(Tabela1[[#This Row],[REQUISIÇÃO]] <> "", Tabela1[[#This Row],[PEDIDO]] = "", Tabela1[[#This Row],[RC ENVIADA?]] = ""), "Requisição Feita", IF( AND(Tabela1[[#This Row],[RC ENVIADA?]] = "SIM", Tabela1[[#This Row],[REQUISIÇÃO]] <> "", Tabela1[[#This Row],[PEDIDO]] = ""), "Aguardando Pedido", "" ) ) ) ) -> Orçamento Recebido | U11: =F11 & " " & " " & B11 & " - " & I11 & " - " & "N°" & H11 & " - " & Tabela1[[#This Row],[Coluna1]] -> VIRADA DE BANDEIRA 7132 - DWA - N° - fazer em 26 | X11: =IF(V11<>"","ABERTO","PENDENTE") -> PENDENTE | AA11: =IF(Tabela1[[#This Row],[CHAMADO]]="ABERTO",Tabela1[[#This Row],[procx status]],"") | AE11: =IF(Tabela1[[#This Row],[Status Result1]]="Aguardando autorização pgto", "sim","") | AF11: =IF(Tabela1[[#This Row],[ID]]<>"", IF(Tabela1[[#This Row],[Data_pgto_sap]]<>"", "Data de pagamento: "&TEXT(Tabela1[[#This Row],[Data_pgto_sap]],"dd/mm/aaaa"), "Chamado aberto, aguardando programação de pagamento"), IF(AND(Tabela1[[#This Row],[PEDIDO]]<>"",Tabela1[[#This Row],[NOTA]]<>""), "Há pedido e há nota, aguardando autorização pgto", IF(AND(Tabela1[[#This Row],[PEDIDO]]<>"",Tabela1[[#This Row],[NOTA]]=""), "Aguardando nota, há pedido", IF(AND(Tabela1[[#This Row],[PEDIDO]]="",Tabela1[[#This Row],[NOTA]]<>""), "Aguardando pedido, há nota",) ))) -> 0 | AG11: =IF(Tabela1[[#This Row],[ID]]<>"", IF(Tabela1[[#This Row],[Data_pgto_sap]]<>"", "Data de pagamento: "&TEXT(Tabela1[[#This Row],[Data_pgto_sap]],"dd/mm/aaaa"), "Chamado aberto, aguardando programação de pagamento"), IF(AND(Tabela1[[#This Row],[PEDIDO]]<>"",Tabela1[[#This Row],[NOTA]]<>""), "Aguardando autorização pgto", IF(AND(Tabela1[[#This Row],[PEDIDO]]<>"",Tabela1[[#This Row],[NOTA]]=""), "Aguardando nota", IF(AND(Tabela1[[#This Row],[PEDIDO]]="",Tabela1[[#This Row],[NOTA]]<>""), "Aguardando pedido", "Aguardando ambos")))) -> Aguardando ambos | AK11: =IF(Tabela1[[#This Row],[procx ticket]]="",Tabela1[[#This Row],[Data criação ticket]],Tabela1[[#This Row],[procx ticket]]) -> 0 | AM11: =IF( OR( Tabela1[[#This Row],[Data criação ticket]]="", Tabela1[[#This Row],[Data criação ticket]]=0, ISERROR(DATEVALUE(Tabela1[[#This Row],[Data criação ticket]])) ), "", RIGHT(Tabela1[[#This Row],[Data criação ticket]],2) & "/" & MID(Tabela1[[#This Row],[Data criação ticket]],6,2) & "/" & LEFT(Tabela1[[#This Row],[Data criação ticket]],4) ) | AN11: =IFERROR( IF( Tabela1[[#This Row],[Data_pgto_sap]] <> "", "pagamento efetivado", IF( AND( Tabela1[[#This Row],[Status Result1]] = "Chamado aberto, aguardando programação de pagamento", TODAY() - Tabela1[[#This Row],[Data criação ticket br]] >= 5 ), "fora do prazo (" & (TODAY() - Tabela1[[#This Row],[Data criação ticket br]]) & " dias)", "no prazo" ) ), "") | AP11: fazer em 26 | AQ11: =Tabela1[[#This Row],[FILIAL]]&Tabela1[[#This Row],[ORDEM]]&Tabela1[[#This Row],[VALOR RC]]&Tabela1[[#This Row],[COORDENADOR]]&Tabela1[[#This Row],[PROJETO]]&Tabela1[[#This Row],[SERVIÇO]]&Tabela1[[#This Row],[FORNECEDOR]] -> 713260603554771,19HENRIQUEVIRADA DE BANDEIRAREFORMADWA | AR11: #N/A
A12: =IF(B12<7000,1000,2000) -> 2000 | B12: 7174 | C12: =_xlfn.XLOOKUP(Tabela1[[#This Row],[FILIAL]],'CNPJ BASE jan25'!A:A,'CNPJ BASE jan25'!B:B) -> SLU58-JoMiJo21-MA-EF | D12: =_xlfn.XLOOKUP(Tabela1[[#This Row],[FILIAL]],'CNPJ BASE jan25'!A:A,'CNPJ BASE jan25'!C:C) -> 04.899.316/0174-36 | E12: HENRIQUE | F12: VIRADA DE BANDEIRA | G12: REFORMA | I12: DWA | J12: 9 | M12: 606037 | P12: 73429.55 | R12: =IF(Tabela1[[#This Row],[VALOR A PAGAR]]>1,Tabela1[[#This Row],[VALOR A PAGAR]],Tabela1[[#This Row],[VALOR RC]]) -> 73429.55 | S12: =IF( Tabela1[[#This Row],[PEDIDO]] <> "", "Pedido Criado", IF( AND(Tabela1[[#This Row],[REQUISIÇÃO]] = "", Tabela1[[#This Row],[PEDIDO]] = ""), "Orçamento Recebido", IF( AND(Tabela1[[#This Row],[REQUISIÇÃO]] <> "", Tabela1[[#This Row],[PEDIDO]] = "", Tabela1[[#This Row],[RC ENVIADA?]] = ""), "Requisição Feita", IF( AND(Tabela1[[#This Row],[RC ENVIADA?]] = "SIM", Tabela1[[#This Row],[REQUISIÇÃO]] <> "", Tabela1[[#This Row],[PEDIDO]] = ""), "Aguardando Pedido", "" ) ) ) ) -> Orçamento Recebido | U12: =F12 & " " & " " & B12 & " - " & I12 & " - " & "N°" & H12 & " - " & Tabela1[[#This Row],[Coluna1]] -> VIRADA DE BANDEIRA 7174 - DWA - N° - fazer em 26 | X12: =IF(V12<>"","ABERTO","PENDENTE") -> PENDENTE | AA12: =IF(Tabela1[[#This Row],[CHAMADO]]="ABERTO",Tabela1[[#This Row],[procx status]],"") | AE12: =IF(Tabela1[[#This Row],[Status Result1]]="Aguardando autorização pgto", "sim","") | AF12: =IF(Tabela1[[#This Row],[ID]]<>"", IF(Tabela1[[#This Row],[Data_pgto_sap]]<>"", "Data de pagamento: "&TEXT(Tabela1[[#This Row],[Data_pgto_sap]],"dd/mm/aaaa"), "Chamado aberto, aguardando programação de pagamento"), IF(AND(Tabela1[[#This Row],[PEDIDO]]<>"",Tabela1[[#This Row],[NOTA]]<>""), "Há pedido e há nota, aguardando autorização pgto", IF(AND(Tabela1[[#This Row],[PEDIDO]]<>"",Tabela1[[#This Row],[NOTA]]=""), "Aguardando nota, há pedido", IF(AND(Tabela1[[#This Row],[PEDIDO]]="",Tabela1[[#This Row],[NOTA]]<>""), "Aguardando pedido, há nota",) ))) -> 0 | AG12: =IF(Tabela1[[#This Row],[ID]]<>"", IF(Tabela1[[#This Row],[Data_pgto_sap]]<>"", "Data de pagamento: "&TEXT(Tabela1[[#This Row],[Data_pgto_sap]],"dd/mm/aaaa"), "Chamado aberto, aguardando programação de pagamento"), IF(AND(Tabela1[[#This Row],[PEDIDO]]<>"",Tabela1[[#This Row],[NOTA]]<>""), "Aguardando autorização pgto", IF(AND(Tabela1[[#This Row],[PEDIDO]]<>"",Tabela1[[#This Row],[NOTA]]=""), "Aguardando nota", IF(AND(Tabela1[[#This Row],[PEDIDO]]="",Tabela1[[#This Row],[NOTA]]<>""), "Aguardando pedido", "Aguardando ambos")))) -> Aguardando ambos | AK12: =IF(Tabela1[[#This Row],[procx ticket]]="",Tabela1[[#This Row],[Data criação ticket]],Tabela1[[#This Row],[procx ticket]]) -> 0 | AM12: =IF( OR( Tabela1[[#This Row],[Data criação ticket]]="", Tabela1[[#This Row],[Data criação ticket]]=0, ISERROR(DATEVALUE(Tabela1[[#This Row],[Data criação ticket]])) ), "", RIGHT(Tabela1[[#This Row],[Data criação ticket]],2) & "/" & MID(Tabela1[[#This Row],[Data criação ticket]],6,2) & "/" & LEFT(Tabela1[[#This Row],[Data criação ticket]],4) ) | AN12: =IFERROR( IF( Tabela1[[#This Row],[Data_pgto_sap]] <> "", "pagamento efetivado", IF( AND( Tabela1[[#This Row],[Status Result1]] = "Chamado aberto, aguardando programação de pagamento", TODAY() - Tabela1[[#This Row],[Data criação ticket br]] >= 5 ), "fora do prazo (" & (TODAY() - Tabela1[[#This Row],[Data criação ticket br]]) & " dias)", "no prazo" ) ), "") | AP12: fazer em 26 | AQ12: =Tabela1[[#This Row],[FILIAL]]&Tabela1[[#This Row],[ORDEM]]&Tabela1[[#This Row],[VALOR RC]]&Tabela1[[#This Row],[COORDENADOR]]&Tabela1[[#This Row],[PROJETO]]&Tabela1[[#This Row],[SERVIÇO]]&Tabela1[[#This Row],[FORNECEDOR]] -> 717460603773429,55HENRIQUEVIRADA DE BANDEIRAREFORMADWA | AR12: #N/A
A13: =IF(B13<7000,1000,2000) -> 2000 | B13: 7175 | C13: =_xlfn.XLOOKUP(Tabela1[[#This Row],[FILIAL]],'CNPJ BASE jan25'!A:A,'CNPJ BASE jan25'!B:B) -> SLU59-01Quadra-MA-EF | D13: 06.626.253/1461-05 | E13: HENRIQUE | F13: VIRADA DE BANDEIRA | G13: REFORMA | I13: DWA | J13: 10 | M13: 606038 | P13: 76139.42 | R13: =IF(Tabela1[[#This Row],[VALOR A PAGAR]]>1,Tabela1[[#This Row],[VALOR A PAGAR]],Tabela1[[#This Row],[VALOR RC]]) -> 76139.42 | S13: =IF( Tabela1[[#This Row],[PEDIDO]] <> "", "Pedido Criado", IF( AND(Tabela1[[#This Row],[REQUISIÇÃO]] = "", Tabela1[[#This Row],[PEDIDO]] = ""), "Orçamento Recebido", IF( AND(Tabela1[[#This Row],[REQUISIÇÃO]] <> "", Tabela1[[#This Row],[PEDIDO]] = "", Tabela1[[#This Row],[RC ENVIADA?]] = ""), "Requisição Feita", IF( AND(Tabela1[[#This Row],[RC ENVIADA?]] = "SIM", Tabela1[[#This Row],[REQUISIÇÃO]] <> "", Tabela1[[#This Row],[PEDIDO]] = ""), "Aguardando Pedido", "" ) ) ) ) -> Orçamento Recebido | U13: =F13 & " " & " " & B13 & " - " & I13 & " - " & "N°" & H13 & " - " & Tabela1[[#This Row],[Coluna1]] -> VIRADA DE BANDEIRA 7175 - DWA - N° - fazer em 26 | X13: =IF(V13<>"","ABERTO","PENDENTE") -> PENDENTE | AA13: =IF(Tabela1[[#This Row],[CHAMADO]]="ABERTO",Tabela1[[#This Row],[procx status]],"") | AE13: =IF(Tabela1[[#This Row],[Status Result1]]="Aguardando autorização pgto", "sim","") | AF13: =IF(Tabela1[[#This Row],[ID]]<>"", IF(Tabela1[[#This Row],[Data_pgto_sap]]<>"", "Data de pagamento: "&TEXT(Tabela1[[#This Row],[Data_pgto_sap]],"dd/mm/aaaa"), "Chamado aberto, aguardando programação de pagamento"), IF(AND(Tabela1[[#This Row],[PEDIDO]]<>"",Tabela1[[#This Row],[NOTA]]<>""), "Há pedido e há nota, aguardando autorização pgto", IF(AND(Tabela1[[#This Row],[PEDIDO]]<>"",Tabela1[[#This Row],[NOTA]]=""), "Aguardando nota, há pedido", IF(AND(Tabela1[[#This Row],[PEDIDO]]="",Tabela1[[#This Row],[NOTA]]<>""), "Aguardando pedido, há nota",) ))) -> 0 | AG13: =IF(Tabela1[[#This Row],[ID]]<>"", IF(Tabela1[[#This Row],[Data_pgto_sap]]<>"", "Data de pagamento: "&TEXT(Tabela1[[#This Row],[Data_pgto_sap]],"dd/mm/aaaa"), "Chamado aberto, aguardando programação de pagamento"), IF(AND(Tabela1[[#This Row],[PEDIDO]]<>"",Tabela1[[#This Row],[NOTA]]<>""), "Aguardando autorização pgto", IF(AND(Tabela1[[#This Row],[PEDIDO]]<>"",Tabela1[[#This Row],[NOTA]]=""), "Aguardando nota", IF(AND(Tabela1[[#This Row],[PEDIDO]]="",Tabela1[[#This Row],[NOTA]]<>""), "Aguardando pedido", "Aguardando ambos")))) -> Aguardando ambos | AK13: =IF(Tabela1[[#This Row],[procx ticket]]="",Tabela1[[#This Row],[Data criação ticket]],Tabela1[[#This Row],[procx ticket]]) -> 0 | AM13: =IF( OR( Tabela1[[#This Row],[Data criação ticket]]="", Tabela1[[#This Row],[Data criação ticket]]=0, ISERROR(DATEVALUE(Tabela1[[#This Row],[Data criação ticket]])) ), "", RIGHT(Tabela1[[#This Row],[Data criação ticket]],2) & "/" & MID(Tabela1[[#This Row],[Data criação ticket]],6,2) & "/" & LEFT(Tabela1[[#This Row],[Data criação ticket]],4) ) | AN13: =IFERROR( IF( Tabela1[[#This Row],[Data_pgto_sap]] <> "", "pagamento efetivado", IF( AND( Tabela1[[#This Row],[Status Result1]] = "Chamado aberto, aguardando programação de pagamento", TODAY() - Tabela1[[#This Row],[Data criação ticket br]] >= 5 ), "fora do prazo (" & (TODAY() - Tabela1[[#This Row],[Data criação ticket br]]) & " dias)", "no prazo" ) ), "") | AP13: fazer em 26 | AQ13: =Tabela1[[#This Row],[FILIAL]]&Tabela1[[#This Row],[ORDEM]]&Tabela1[[#This Row],[VALOR RC]]&Tabela1[[#This Row],[COORDENADOR]]&Tabela1[[#This Row],[PROJETO]]&Tabela1[[#This Row],[SERVIÇO]]&Tabela1[[#This Row],[FORNECEDOR]] -> 717560603876139,42HENRIQUEVIRADA DE BANDEIRAREFORMADWA | AR13: #N/A
A14: =IF(B14<7000,1000,2000) -> 2000 | B14: 7211 | C14: =_xlfn.XLOOKUP(Tabela1[[#This Row],[FILIAL]],'CNPJ BASE jan25'!A:A,'CNPJ BASE jan25'!B:B) -> PIN03-GetVarga-MA-EF | D14: 04.899.316/0211-15 | E14: HENRIQUE | F14: VIRADA DE BANDEIRA | G14: REFORMA | I14: DWA | J14: 12 | M14: 606040 | P14: 38773.39 | R14: =IF(Tabela1[[#This Row],[VALOR A PAGAR]]>1,Tabela1[[#This Row],[VALOR A PAGAR]],Tabela1[[#This Row],[VALOR RC]]) -> 38773.39 | S14: =IF( Tabela1[[#This Row],[PEDIDO]] <> "", "Pedido Criado", IF( AND(Tabela1[[#This Row],[REQUISIÇÃO]] = "", Tabela1[[#This Row],[PEDIDO]] = ""), "Orçamento Recebido", IF( AND(Tabela1[[#This Row],[REQUISIÇÃO]] <> "", Tabela1[[#This Row],[PEDIDO]] = "", Tabela1[[#This Row],[RC ENVIADA?]] = ""), "Requisição Feita", IF( AND(Tabela1[[#This Row],[RC ENVIADA?]] = "SIM", Tabela1[[#This Row],[REQUISIÇÃO]] <> "", Tabela1[[#This Row],[PEDIDO]] = ""), "Aguardando Pedido", "" ) ) ) ) -> Orçamento Recebido | U14: =F14 & " " & " " & B14 & " - " & I14 & " - " & "N°" & H14 & " - " & Tabela1[[#This Row],[Coluna1]] -> VIRADA DE BANDEIRA 7211 - DWA - N° - fazer em 26 | X14: =IF(V14<>"","ABERTO","PENDENTE") -> PENDENTE | AA14: =IF(Tabela1[[#This Row],[CHAMADO]]="ABERTO",Tabela1[[#This Row],[procx status]],"") | AE14: =IF(Tabela1[[#This Row],[Status Result1]]="Aguardando autorização pgto", "sim","") | AF14: =IF(Tabela1[[#This Row],[ID]]<>"", IF(Tabela1[[#This Row],[Data_pgto_sap]]<>"", "Data de pagamento: "&TEXT(Tabela1[[#This Row],[Data_pgto_sap]],"dd/mm/aaaa"), "Chamado aberto, aguardando programação de pagamento"), IF(AND(Tabela1[[#This Row],[PEDIDO]]<>"",Tabela1[[#This Row],[NOTA]]<>""), "Há pedido e há nota, aguardando autorização pgto", IF(AND(Tabela1[[#This Row],[PEDIDO]]<>"",Tabela1[[#This Row],[NOTA]]=""), "Aguardando nota, há pedido", IF(AND(Tabela1[[#This Row],[PEDIDO]]="",Tabela1[[#This Row],[NOTA]]<>""), "Aguardando pedido, há nota",) ))) -> 0 | AG14: =IF(Tabela1[[#This Row],[ID]]<>"", IF(Tabela1[[#This Row],[Data_pgto_sap]]<>"", "Data de pagamento: "&TEXT(Tabela1[[#This Row],[Data_pgto_sap]],"dd/mm/aaaa"), "Chamado aberto, aguardando programação de pagamento"), IF(AND(Tabela1[[#This Row],[PEDIDO]]<>"",Tabela1[[#This Row],[NOTA]]<>""), "Aguardando autorização pgto", IF(AND(Tabela1[[#This Row],[PEDIDO]]<>"",Tabela1[[#This Row],[NOTA]]=""), "Aguardando nota", IF(AND(Tabela1[[#This Row],[PEDIDO]]="",Tabela1[[#This Row],[NOTA]]<>""), "Aguardando pedido", "Aguardando ambos")))) -> Aguardando ambos | AK14: =IF(Tabela1[[#This Row],[procx ticket]]="",Tabela1[[#This Row],[Data criação ticket]],Tabela1[[#This Row],[procx ticket]]) -> 0 | AM14: =IF( OR( Tabela1[[#This Row],[Data criação ticket]]="", Tabela1[[#This Row],[Data criação ticket]]=0, ISERROR(DATEVALUE(Tabela1[[#This Row],[Data criação ticket]])) ), "", RIGHT(Tabela1[[#This Row],[Data criação ticket]],2) & "/" & MID(Tabela1[[#This Row],[Data criação ticket]],6,2) & "/" & LEFT(Tabela1[[#This Row],[Data criação ticket]],4) ) | AN14: =IFERROR( IF( Tabela1[[#This Row],[Data_pgto_sap]] <> "", "pagamento efetivado", IF( AND( Tabela1[[#This Row],[Status Result1]] = "Chamado aberto, aguardando programação de pagamento", TODAY() - Tabela1[[#This Row],[Data criação ticket br]] >= 5 ), "fora do prazo (" & (TODAY() - Tabela1[[#This Row],[Data criação ticket br]]) & " dias)", "no prazo" ) ), "") | AP14: fazer em 26 | AQ14: =Tabela1[[#This Row],[FILIAL]]&Tabela1[[#This Row],[ORDEM]]&Tabela1[[#This Row],[VALOR RC]]&Tabela1[[#This Row],[COORDENADOR]]&Tabela1[[#This Row],[PROJETO]]&Tabela1[[#This Row],[SERVIÇO]]&Tabela1[[#This Row],[FORNECEDOR]] -> 721160604038773,39HENRIQUEVIRADA DE BANDEIRAREFORMADWA | AR14: #N/A
A15: =IF(B15<7000,1000,2000) -> 2000 | B15: 7289 | C15: =_xlfn.XLOOKUP(Tabela1[[#This Row],[FILIAL]],'CNPJ BASE jan25'!A:A,'CNPJ BASE jan25'!B:B) -> IMP08-SimMorei-MA-EF | D15: =_xlfn.XLOOKUP(Tabela1[[#This Row],[FILIAL]],'CNPJ BASE jan25'!A:A,'CNPJ BASE jan25'!C:C) -> 04.899.316/0289-85 | E15: HENRIQUE | F15: VIRADA DE BANDEIRA | G15: REFORMA | I15: DWA | J15: 14 | M15: 606044 | P15: 40989.09 | R15: =IF(Tabela1[[#This Row],[VALOR A PAGAR]]>1,Tabela1[[#This Row],[VALOR A PAGAR]],Tabela1[[#This Row],[VALOR RC]]) -> 40989.09 | S15: =IF( Tabela1[[#This Row],[PEDIDO]] <> "", "Pedido Criado", IF( AND(Tabela1[[#This Row],[REQUISIÇÃO]] = "", Tabela1[[#This Row],[PEDIDO]] = ""), "Orçamento Recebido", IF( AND(Tabela1[[#This Row],[REQUISIÇÃO]] <> "", Tabela1[[#This Row],[PEDIDO]] = "", Tabela1[[#This Row],[RC ENVIADA?]] = ""), "Requisição Feita", IF( AND(Tabela1[[#This Row],[RC ENVIADA?]] = "SIM", Tabela1[[#This Row],[REQUISIÇÃO]] <> "", Tabela1[[#This Row],[PEDIDO]] = ""), "Aguardando Pedido", "" ) ) ) ) -> Orçamento Recebido | U15: =F15 & " " & " " & B15 & " - " & I15 & " - " & "N°" & H15 & " - " & Tabela1[[#This Row],[Coluna1]] -> VIRADA DE BANDEIRA 7289 - DWA - N° - fazer em 26 | X15: =IF(V15<>"","ABERTO","PENDENTE") -> PENDENTE | AA15: =IF(Tabela1[[#This Row],[CHAMADO]]="ABERTO",Tabela1[[#This Row],[procx status]],"") | AE15: =IF(Tabela1[[#This Row],[Status Result1]]="Aguardando autorização pgto", "sim","") | AF15: =IF(Tabela1[[#This Row],[ID]]<>"", IF(Tabela1[[#This Row],[Data_pgto_sap]]<>"", "Data de pagamento: "&TEXT(Tabela1[[#This Row],[Data_pgto_sap]],"dd/mm/aaaa"), "Chamado aberto, aguardando programação de pagamento"), IF(AND(Tabela1[[#This Row],[PEDIDO]]<>"",Tabela1[[#This Row],[NOTA]]<>""), "Há pedido e há nota, aguardando autorização pgto", IF(AND(Tabela1[[#This Row],[PEDIDO]]<>"",Tabela1[[#This Row],[NOTA]]=""), "Aguardando nota, há pedido", IF(AND(Tabela1[[#This Row],[PEDIDO]]="",Tabela1[[#This Row],[NOTA]]<>""), "Aguardando pedido, há nota",) ))) -> 0 | AG15: =IF(Tabela1[[#This Row],[ID]]<>"", IF(Tabela1[[#This Row],[Data_pgto_sap]]<>"", "Data de pagamento: "&TEXT(Tabela1[[#This Row],[Data_pgto_sap]],"dd/mm/aaaa"), "Chamado aberto, aguardando programação de pagamento"), IF(AND(Tabela1[[#This Row],[PEDIDO]]<>"",Tabela1[[#This Row],[NOTA]]<>""), "Aguardando autorização pgto", IF(AND(Tabela1[[#This Row],[PEDIDO]]<>"",Tabela1[[#This Row],[NOTA]]=""), "Aguardando nota", IF(AND(Tabela1[[#This Row],[PEDIDO]]="",Tabela1[[#This Row],[NOTA]]<>""), "Aguardando pedido", "Aguardando ambos")))) -> Aguardando ambos | AK15: =IF(Tabela1[[#This Row],[procx ticket]]="",Tabela1[[#This Row],[Data criação ticket]],Tabela1[[#This Row],[procx ticket]]) -> 0 | AM15: =IF( OR( Tabela1[[#This Row],[Data criação ticket]]="", Tabela1[[#This Row],[Data criação ticket]]=0, ISERROR(DATEVALUE(Tabela1[[#This Row],[Data criação ticket]])) ), "", RIGHT(Tabela1[[#This Row],[Data criação ticket]],2) & "/" & MID(Tabela1[[#This Row],[Data criação ticket]],6,2) & "/" & LEFT(Tabela1[[#This Row],[Data criação ticket]],4) ) | AN15: =IFERROR( IF( Tabela1[[#This Row],[Data_pgto_sap]] <> "", "pagamento efetivado", IF( AND( Tabela1[[#This Row],[Status Result1]] = "Chamado aberto, aguardando programação de pagamento", TODAY() - Tabela1[[#This Row],[Data criação ticket br]] >= 5 ), "fora do prazo (" & (TODAY() - Tabela1[[#This Row],[Data criação ticket br]]) & " dias)", "no prazo" ) ), "") | AP15: fazer em 26 | AQ15: =Tabela1[[#This Row],[FILIAL]]&Tabela1[[#This Row],[ORDEM]]&Tabela1[[#This Row],[VALOR RC]]&Tabela1[[#This Row],[COORDENADOR]]&Tabela1[[#This Row],[PROJETO]]&Tabela1[[#This Row],[SERVIÇO]]&Tabela1[[#This Row],[FORNECEDOR]] -> 728960604440989,09HENRIQUEVIRADA DE BANDEIRAREFORMADWA | AR15: #N/A
A16: =IF(B16<7000,1000,2000) -> 2000 | B16: 7132 | C16: =_xlfn.XLOOKUP(Tabela1[[#This Row],[FILIAL]],'CNPJ BASE jan25'!A:A,'CNPJ BASE jan25'!B:B) -> SLU52-Mitra9-MA-EF | D16: =_xlfn.XLOOKUP(Tabela1[[#This Row],[FILIAL]],'CNPJ BASE jan25'!A:A,'CNPJ BASE jan25'!C:C) -> 04.899.316/0132-87 | E16: HENRIQUE | F16: VIRADA DE BANDEIRA | G16: REFORMA | I16: PLANAC | J16: 3 | M16: 606035 | P16: 1202.09 | R16: =IF(Tabela1[[#This Row],[VALOR A PAGAR]]>1,Tabela1[[#This Row],[VALOR A PAGAR]],Tabela1[[#This Row],[VALOR RC]]) -> 1202.09 | S16: =IF( Tabela1[[#This Row],[PEDIDO]] <> "", "Pedido Criado", IF( AND(Tabela1[[#This Row],[REQUISIÇÃO]] = "", Tabela1[[#This Row],[PEDIDO]] = ""), "Orçamento Recebido", IF( AND(Tabela1[[#This Row],[REQUISIÇÃO]] <> "", Tabela1[[#This Row],[PEDIDO]] = "", Tabela1[[#This Row],[RC ENVIADA?]] = ""), "Requisição Feita", IF( AND(Tabela1[[#This Row],[RC ENVIADA?]] = "SIM", Tabela1[[#This Row],[REQUISIÇÃO]] <> "", Tabela1[[#This Row],[PEDIDO]] = ""), "Aguardando Pedido", "" ) ) ) ) -> Orçamento Recebido | U16: =F16 & " " & " " & B16 & " - " & I16 & " - " & "N°" & H16 & " - " & Tabela1[[#This Row],[Coluna1]] -> VIRADA DE BANDEIRA 7132 - PLANAC - N° - fazer em 26 | X16: =IF(V16<>"","ABERTO","PENDENTE") -> PENDENTE | AA16: =IF(Tabela1[[#This Row],[CHAMADO]]="ABERTO",Tabela1[[#This Row],[procx status]],"") | AE16: =IF(Tabela1[[#This Row],[Status Result1]]="Aguardando autorização pgto", "sim","") | AF16: =IF(Tabela1[[#This Row],[ID]]<>"", IF(Tabela1[[#This Row],[Data_pgto_sap]]<>"", "Data de pagamento: "&TEXT(Tabela1[[#This Row],[Data_pgto_sap]],"dd/mm/aaaa"), "Chamado aberto, aguardando programação de pagamento"), IF(AND(Tabela1[[#This Row],[PEDIDO]]<>"",Tabela1[[#This Row],[NOTA]]<>""), "Há pedido e há nota, aguardando autorização pgto", IF(AND(Tabela1[[#This Row],[PEDIDO]]<>"",Tabela1[[#This Row],[NOTA]]=""), "Aguardando nota, há pedido", IF(AND(Tabela1[[#This Row],[PEDIDO]]="",Tabela1[[#This Row],[NOTA]]<>""), "Aguardando pedido, há nota",) ))) -> 0 | AG16: =IF(Tabela1[[#This Row],[ID]]<>"", IF(Tabela1[[#This Row],[Data_pgto_sap]]<>"", "Data de pagamento: "&TEXT(Tabela1[[#This Row],[Data_pgto_sap]],"dd/mm/aaaa"), "Chamado aberto, aguardando programação de pagamento"), IF(AND(Tabela1[[#This Row],[PEDIDO]]<>"",Tabela1[[#This Row],[NOTA]]<>""), "Aguardando autorização pgto", IF(AND(Tabela1[[#This Row],[PEDIDO]]<>"",Tabela1[[#This Row],[NOTA]]=""), "Aguardando nota", IF(AND(Tabela1[[#This Row],[PEDIDO]]="",Tabela1[[#This Row],[NOTA]]<>""), "Aguardando pedido", "Aguardando ambos")))) -> Aguardando ambos | AK16: =IF(Tabela1[[#This Row],[procx ticket]]="",Tabela1[[#This Row],[Data criação ticket]],Tabela1[[#This Row],[procx ticket]]) -> 0 | AM16: =IF( OR( Tabela1[[#This Row],[Data criação ticket]]="", Tabela1[[#This Row],[Data criação ticket]]=0, ISERROR(DATEVALUE(Tabela1[[#This Row],[Data criação ticket]])) ), "", RIGHT(Tabela1[[#This Row],[Data criação ticket]],2) & "/" & MID(Tabela1[[#This Row],[Data criação ticket]],6,2) & "/" & LEFT(Tabela1[[#This Row],[Data criação ticket]],4) ) | AN16: =IFERROR( IF( Tabela1[[#This Row],[Data_pgto_sap]] <> "", "pagamento efetivado", IF( AND( Tabela1[[#This Row],[Status Result1]] = "Chamado aberto, aguardando programação de pagamento", TODAY() - Tabela1[[#This Row],[Data criação ticket br]] >= 5 ), "fora do prazo (" & (TODAY() - Tabela1[[#This Row],[Data criação ticket br]]) & " dias)", "no prazo" ) ), "") | AP16: fazer em 26 | AQ16: =Tabela1[[#This Row],[FILIAL]]&Tabela1[[#This Row],[ORDEM]]&Tabela1[[#This Row],[VALOR RC]]&Tabela1[[#This Row],[COORDENADOR]]&Tabela1[[#This Row],[PROJETO]]&Tabela1[[#This Row],[SERVIÇO]]&Tabela1[[#This Row],[FORNECEDOR]] -> 71326060351202,09HENRIQUEVIRADA DE BANDEIRAREFORMAPLANAC | AR16: #N/A
A17: =IF(B17<7000,1000,2000) -> 2000 | B17: 7041 | C17: =_xlfn.XLOOKUP(Tabela1[[#This Row],[FILIAL]],'CNPJ BASE jan25'!A:A,'CNPJ BASE jan25'!B:B) -> SLU72-15-MA-EF | D17: =_xlfn.XLOOKUP(Tabela1[[#This Row],[FILIAL]],'CNPJ BASE jan25'!A:A,'CNPJ BASE jan25'!C:C) -> 04.899.316/0041-05 | E17: HENRIQUE | F17: VIRADA DE BANDEIRA | G17: REFORMA | I17: PLANAC | J17: 4 | M17: 606028 | P17: 7716.85 | R17: =IF(Tabela1[[#This Row],[VALOR A PAGAR]]>1,Tabela1[[#This Row],[VALOR A PAGAR]],Tabela1[[#This Row],[VALOR RC]]) -> 7716.85 | S17: =IF( Tabela1[[#This Row],[PEDIDO]] <> "", "Pedido Criado", IF( AND(Tabela1[[#This Row],[REQUISIÇÃO]] = "", Tabela1[[#This Row],[PEDIDO]] = ""), "Orçamento Recebido", IF( AND(Tabela1[[#This Row],[REQUISIÇÃO]] <> "", Tabela1[[#This Row],[PEDIDO]] = "", Tabela1[[#This Row],[RC ENVIADA?]] = ""), "Requisição Feita", IF( AND(Tabela1[[#This Row],[RC ENVIADA?]] = "SIM", Tabela1[[#This Row],[REQUISIÇÃO]] <> "", Tabela1[[#This Row],[PEDIDO]] = ""), "Aguardando Pedido", "" ) ) ) ) -> Orçamento Recebido | U17: =F17 & " " & " " & B17 & " - " & I17 & " - " & "N°" & H17 & " - " & Tabela1[[#This Row],[Coluna1]] -> VIRADA DE BANDEIRA 7041 - PLANAC - N° - fazer em 26 | X17: =IF(V17<>"","ABERTO","PENDENTE") -> PENDENTE | AA17: =IF(Tabela1[[#This Row],[CHAMADO]]="ABERTO",Tabela1[[#This Row],[procx status]],"") | AE17: =IF(Tabela1[[#This Row],[Status Result1]]="Aguardando autorização pgto", "sim","") | AF17: =IF(Tabela1[[#This Row],[ID]]<>"", IF(Tabela1[[#This Row],[Data_pgto_sap]]<>"", "Data de pagamento: "&TEXT(Tabela1[[#This Row],[Data_pgto_sap]],"dd/mm/aaaa"), "Chamado aberto, aguardando programação de pagamento"), IF(AND(Tabela1[[#This Row],[PEDIDO]]<>"",Tabela1[[#This Row],[NOTA]]<>""), "Há pedido e há nota, aguardando autorização pgto", IF(AND(Tabela1[[#This Row],[PEDIDO]]<>"",Tabela1[[#This Row],[NOTA]]=""), "Aguardando nota, há pedido", IF(AND(Tabela1[[#This Row],[PEDIDO]]="",Tabela1[[#This Row],[NOTA]]<>""), "Aguardando pedido, há nota",) ))) -> 0 | AG17: =IF(Tabela1[[#This Row],[ID]]<>"", IF(Tabela1[[#This Row],[Data_pgto_sap]]<>"", "Data de pagamento: "&TEXT(Tabela1[[#This Row],[Data_pgto_sap]],"dd/mm/aaaa"), "Chamado aberto, aguardando programação de pagamento"), IF(AND(Tabela1[[#This Row],[PEDIDO]]<>"",Tabela1[[#This Row],[NOTA]]<>""), "Aguardando autorização pgto", IF(AND(Tabela1[[#This Row],[PEDIDO]]<>"",Tabela1[[#This Row],[NOTA]]=""), "Aguardando nota", IF(AND(Tabela1[[#This Row],[PEDIDO]]="",Tabela1[[#This Row],[NOTA]]<>""), "Aguardando pedido", "Aguardando ambos")))) -> Aguardando ambos | AK17: =IF(Tabela1[[#This Row],[procx ticket]]="",Tabela1[[#This Row],[Data criação ticket]],Tabela1[[#This Row],[procx ticket]]) -> 0 | AM17: =IF( OR( Tabela1[[#This Row],[Data criação ticket]]="", Tabela1[[#This Row],[Data criação ticket]]=0, ISERROR(DATEVALUE(Tabela1[[#This Row],[Data criação ticket]])) ), "", RIGHT(Tabela1[[#This Row],[Data criação ticket]],2) & "/" & MID(Tabela1[[#This Row],[Data criação ticket]],6,2) & "/" & LEFT(Tabela1[[#This Row],[Data criação ticket]],4) ) | AN17: =IFERROR( IF( Tabela1[[#This Row],[Data_pgto_sap]] <> "", "pagamento efetivado", IF( AND( Tabela1[[#This Row],[Status Result1]] = "Chamado aberto, aguardando programação de pagamento", TODAY() - Tabela1[[#This Row],[Data criação ticket br]] >= 5 ), "fora do prazo (" & (TODAY() - Tabela1[[#This Row],[Data criação ticket br]]) & " dias)", "no prazo" ) ), "") | AP17: fazer em 26 | AQ17: =Tabela1[[#This Row],[FILIAL]]&Tabela1[[#This Row],[ORDEM]]&Tabela1[[#This Row],[VALOR RC]]&Tabela1[[#This Row],[COORDENADOR]]&Tabela1[[#This Row],[PROJETO]]&Tabela1[[#This Row],[SERVIÇO]]&Tabela1[[#This Row],[FORNECEDOR]] -> 70416060287716,85HENRIQUEVIRADA DE BANDEIRAREFORMAPLANAC | AR17: #N/A
A18: =IF(B18<7000,1000,2000) -> 2000 | B18: 7041 | C18: =_xlfn.XLOOKUP(Tabela1[[#This Row],[FILIAL]],'CNPJ BASE jan25'!A:A,'CNPJ BASE jan25'!B:B) -> SLU72-15-MA-EF | D18: =_xlfn.XLOOKUP(Tabela1[[#This Row],[FILIAL]],'CNPJ BASE jan25'!A:A,'CNPJ BASE jan25'!C:C) -> 04.899.316/0041-05 | E18: HENRIQUE | F18: VIRADA DE BANDEIRA | G18: REFORMA | I18: PLANAC | J18: 5 | M18: 606028 | P18: 5371.92 | R18: =IF(Tabela1[[#This Row],[VALOR A PAGAR]]>1,Tabela1[[#This Row],[VALOR A PAGAR]],Tabela1[[#This Row],[VALOR RC]]) -> 5371.92 | S18: =IF( Tabela1[[#This Row],[PEDIDO]] <> "", "Pedido Criado", IF( AND(Tabela1[[#This Row],[REQUISIÇÃO]] = "", Tabela1[[#This Row],[PEDIDO]] = ""), "Orçamento Recebido", IF( AND(Tabela1[[#This Row],[REQUISIÇÃO]] <> "", Tabela1[[#This Row],[PEDIDO]] = "", Tabela1[[#This Row],[RC ENVIADA?]] = ""), "Requisição Feita", IF( AND(Tabela1[[#This Row],[RC ENVIADA?]] = "SIM", Tabela1[[#This Row],[REQUISIÇÃO]] <> "", Tabela1[[#This Row],[PEDIDO]] = ""), "Aguardando Pedido", "" ) ) ) ) -> Orçamento Recebido | U18: =F18 & " " & " " & B18 & " - " & I18 & " - " & "N°" & H18 & " - " & Tabela1[[#This Row],[Coluna1]] -> VIRADA DE BANDEIRA 7041 - PLANAC - N° - fazer em 26 | X18: =IF(V18<>"","ABERTO","PENDENTE") -> PENDENTE | AA18: =IF(Tabela1[[#This Row],[CHAMADO]]="ABERTO",Tabela1[[#This Row],[procx status]],"") | AE18: =IF(Tabela1[[#This Row],[Status Result1]]="Aguardando autorização pgto", "sim","") | AF18: =IF(Tabela1[[#This Row],[ID]]<>"", IF(Tabela1[[#This Row],[Data_pgto_sap]]<>"", "Data de pagamento: "&TEXT(Tabela1[[#This Row],[Data_pgto_sap]],"dd/mm/aaaa"), "Chamado aberto, aguardando programação de pagamento"), IF(AND(Tabela1[[#This Row],[PEDIDO]]<>"",Tabela1[[#This Row],[NOTA]]<>""), "Há pedido e há nota, aguardando autorização pgto", IF(AND(Tabela1[[#This Row],[PEDIDO]]<>"",Tabela1[[#This Row],[NOTA]]=""), "Aguardando nota, há pedido", IF(AND(Tabela1[[#This Row],[PEDIDO]]="",Tabela1[[#This Row],[NOTA]]<>""), "Aguardando pedido, há nota",) ))) -> 0 | AG18: =IF(Tabela1[[#This Row],[ID]]<>"", IF(Tabela1[[#This Row],[Data_pgto_sap]]<>"", "Data de pagamento: "&TEXT(Tabela1[[#This Row],[Data_pgto_sap]],"dd/mm/aaaa"), "Chamado aberto, aguardando programação de pagamento"), IF(AND(Tabela1[[#This Row],[PEDIDO]]<>"",Tabela1[[#This Row],[NOTA]]<>""), "Aguardando autorização pgto", IF(AND(Tabela1[[#This Row],[PEDIDO]]<>"",Tabela1[[#This Row],[NOTA]]=""), "Aguardando nota", IF(AND(Tabela1[[#This Row],[PEDIDO]]="",Tabela1[[#This Row],[NOTA]]<>""), "Aguardando pedido", "Aguardando ambos")))) -> Aguardando ambos | AK18: =IF(Tabela1[[#This Row],[procx ticket]]="",Tabela1[[#This Row],[Data criação ticket]],Tabela1[[#This Row],[procx ticket]]) -> 0 | AM18: =IF( OR( Tabela1[[#This Row],[Data criação ticket]]="", Tabela1[[#This Row],[Data criação ticket]]=0, ISERROR(DATEVALUE(Tabela1[[#This Row],[Data criação ticket]])) ), "", RIGHT(Tabela1[[#This Row],[Data criação ticket]],2) & "/" & MID(Tabela1[[#This Row],[Data criação ticket]],6,2) & "/" & LEFT(Tabela1[[#This Row],[Data criação ticket]],4) ) | AN18: =IFERROR( IF( Tabela1[[#This Row],[Data_pgto_sap]] <> "", "pagamento efetivado", IF( AND( Tabela1[[#This Row],[Status Result1]] = "Chamado aberto, aguardando programação de pagamento", TODAY() - Tabela1[[#This Row],[Data criação ticket br]] >= 5 ), "fora do prazo (" & (TODAY() - Tabela1[[#This Row],[Data criação ticket br]]) & " dias)", "no prazo" ) ), "") | AP18: fazer em 26 | AQ18: =Tabela1[[#This Row],[FILIAL]]&Tabela1[[#This Row],[ORDEM]]&Tabela1[[#This Row],[VALOR RC]]&Tabela1[[#This Row],[COORDENADOR]]&Tabela1[[#This Row],[PROJETO]]&Tabela1[[#This Row],[SERVIÇO]]&Tabela1[[#This Row],[FORNECEDOR]] -> 70416060285371,92HENRIQUEVIRADA DE BANDEIRAREFORMAPLANAC | AR18: #N/A
A19: =IF(B19<7000,1000,2000) -> 2000 | B19: 7054 | C19: =_xlfn.XLOOKUP(Tabela1[[#This Row],[FILIAL]],'CNPJ BASE jan25'!A:A,'CNPJ BASE jan25'!B:B) -> SLU45-ColMor49-MA-EF | D19: =_xlfn.XLOOKUP(Tabela1[[#This Row],[FILIAL]],'CNPJ BASE jan25'!A:A,'CNPJ BASE jan25'!C:C) -> 04.899.316/0054-20 | E19: HENRIQUE | F19: VIRADA DE BANDEIRA | G19: REFORMA | I19: PLANAC | J19: 6 | M19: 605161 | P19: 4703.32 | R19: =IF(Tabela1[[#This Row],[VALOR A PAGAR]]>1,Tabela1[[#This Row],[VALOR A PAGAR]],Tabela1[[#This Row],[VALOR RC]]) -> 4703.32 | S19: =IF( Tabela1[[#This Row],[PEDIDO]] <> "", "Pedido Criado", IF( AND(Tabela1[[#This Row],[REQUISIÇÃO]] = "", Tabela1[[#This Row],[PEDIDO]] = ""), "Orçamento Recebido", IF( AND(Tabela1[[#This Row],[REQUISIÇÃO]] <> "", Tabela1[[#This Row],[PEDIDO]] = "", Tabela1[[#This Row],[RC ENVIADA?]] = ""), "Requisição Feita", IF( AND(Tabela1[[#This Row],[RC ENVIADA?]] = "SIM", Tabela1[[#This Row],[REQUISIÇÃO]] <> "", Tabela1[[#This Row],[PEDIDO]] = ""), "Aguardando Pedido", "" ) ) ) ) -> Orçamento Recebido | U19: =F19 & " " & " " & B19 & " - " & I19 & " - " & "N°" & H19 & " - " & Tabela1[[#This Row],[Coluna1]] -> VIRADA DE BANDEIRA 7054 - PLANAC - N° - fazer em 26 | X19: =IF(V19<>"","ABERTO","PENDENTE") -> PENDENTE | AA19: =IF(Tabela1[[#This Row],[CHAMADO]]="ABERTO",Tabela1[[#This Row],[procx status]],"") | AE19: =IF(Tabela1[[#This Row],[Status Result1]]="Aguardando autorização pgto", "sim","") | AF19: =IF(Tabela1[[#This Row],[ID]]<>"", IF(Tabela1[[#This Row],[Data_pgto_sap]]<>"", "Data de pagamento: "&TEXT(Tabela1[[#This Row],[Data_pgto_sap]],"dd/mm/aaaa"), "Chamado aberto, aguardando programação de pagamento"), IF(AND(Tabela1[[#This Row],[PEDIDO]]<>"",Tabela1[[#This Row],[NOTA]]<>""), "Há pedido e há nota, aguardando autorização pgto", IF(AND(Tabela1[[#This Row],[PEDIDO]]<>"",Tabela1[[#This Row],[NOTA]]=""), "Aguardando nota, há pedido", IF(AND(Tabela1[[#This Row],[PEDIDO]]="",Tabela1[[#This Row],[NOTA]]<>""), "Aguardando pedido, há nota",) ))) -> 0 | AG19: =IF(Tabela1[[#This Row],[ID]]<>"", IF(Tabela1[[#This Row],[Data_pgto_sap]]<>"", "Data de pagamento: "&TEXT(Tabela1[[#This Row],[Data_pgto_sap]],"dd/mm/aaaa"), "Chamado aberto, aguardando programação de pagamento"), IF(AND(Tabela1[[#This Row],[PEDIDO]]<>"",Tabela1[[#This Row],[NOTA]]<>""), "Aguardando autorização pgto", IF(AND(Tabela1[[#This Row],[PEDIDO]]<>"",Tabela1[[#This Row],[NOTA]]=""), "Aguardando nota", IF(AND(Tabela1[[#This Row],[PEDIDO]]="",Tabela1[[#This Row],[NOTA]]<>""), "Aguardando pedido", "Aguardando ambos")))) -> Aguardando ambos | AK19: =IF(Tabela1[[#This Row],[procx ticket]]="",Tabela1[[#This Row],[Data criação ticket]],Tabela1[[#This Row],[procx ticket]]) -> 0 | AM19: =IF( OR( Tabela1[[#This Row],[Data criação ticket]]="", Tabela1[[#This Row],[Data criação ticket]]=0, ISERROR(DATEVALUE(Tabela1[[#This Row],[Data criação ticket]])) ), "", RIGHT(Tabela1[[#This Row],[Data criação ticket]],2) & "/" & MID(Tabela1[[#This Row],[Data criação ticket]],6,2) & "/" & LEFT(Tabela1[[#This Row],[Data criação ticket]],4) ) | AN19: =IFERROR( IF( Tabela1[[#This Row],[Data_pgto_sap]] <> "", "pagamento efetivado", IF( AND( Tabela1[[#This Row],[Status Result1]] = "Chamado aberto, aguardando programação de pagamento", TODAY() - Tabela1[[#This Row],[Data criação ticket br]] >= 5 ), "fora do prazo (" & (TODAY() - Tabela1[[#This Row],[Data criação ticket br]]) & " dias)", "no prazo" ) ), "") | AP19: fazer em 26 | AQ19: =Tabela1[[#This Row],[FILIAL]]&Tabela1[[#This Row],[ORDEM]]&Tabela1[[#This Row],[VALOR RC]]&Tabela1[[#This Row],[COORDENADOR]]&Tabela1[[#This Row],[PROJETO]]&Tabela1[[#This Row],[SERVIÇO]]&Tabela1[[#This Row],[FORNECEDOR]] -> 70546051614703,32HENRIQUEVIRADA DE BANDEIRAREFORMAPLANAC | AR19: #N/A
A20: =IF(B20<7000,1000,2000) -> 2000 | B20: 7126 | C20: =_xlfn.XLOOKUP(Tabela1[[#This Row],[FILIAL]],'CNPJ BASE jan25'!A:A,'CNPJ BASE jan25'!B:B) -> SLU51-Principa-MA-EF | D20: =_xlfn.XLOOKUP(Tabela1[[#This Row],[FILIAL]],'CNPJ BASE jan25'!A:A,'CNPJ BASE jan25'!C:C) -> 04.899.316/0126-39 | E20: HENRIQUE | F20: VIRADA DE BANDEIRA | G20: REFORMA | I20: PLANAC | J20: 7 | M20: 606032 | P20: 4980.64 | R20: =IF(Tabela1[[#This Row],[VALOR A PAGAR]]>1,Tabela1[[#This Row],[VALOR A PAGAR]],Tabela1[[#This Row],[VALOR RC]]) -> 4980.64 | S20: =IF( Tabela1[[#This Row],[PEDIDO]] <> "", "Pedido Criado", IF( AND(Tabela1[[#This Row],[REQUISIÇÃO]] = "", Tabela1[[#This Row],[PEDIDO]] = ""), "Orçamento Recebido", IF( AND(Tabela1[[#This Row],[REQUISIÇÃO]] <> "", Tabela1[[#This Row],[PEDIDO]] = "", Tabela1[[#This Row],[RC ENVIADA?]] = ""), "Requisição Feita", IF( AND(Tabela1[[#This Row],[RC ENVIADA?]] = "SIM", Tabela1[[#This Row],[REQUISIÇÃO]] <> "", Tabela1[[#This Row],[PEDIDO]] = ""), "Aguardando Pedido", "" ) ) ) ) -> Orçamento Recebido | U20: =F20 & " " & " " & B20 & " - " & I20 & " - " & "N°" & H20 & " - " & Tabela1[[#This Row],[Coluna1]] -> VIRADA DE BANDEIRA 7126 - PLANAC - N° - fazer em 26 | X20: =IF(V20<>"","ABERTO","PENDENTE") -> PENDENTE | AA20: =IF(Tabela1[[#This Row],[CHAMADO]]="ABERTO",Tabela1[[#This Row],[procx status]],"") | AE20: =IF(Tabela1[[#This Row],[Status Result1]]="Aguardando autorização pgto", "sim","") | AF20: =IF(Tabela1[[#This Row],[ID]]<>"", IF(Tabela1[[#This Row],[Data_pgto_sap]]<>"", "Data de pagamento: "&TEXT(Tabela1[[#This Row],[Data_pgto_sap]],"dd/mm/aaaa"), "Chamado aberto, aguardando programação de pagamento"), IF(AND(Tabela1[[#This Row],[PEDIDO]]<>"",Tabela1[[#This Row],[NOTA]]<>""), "Há pedido e há nota, aguardando autorização pgto", IF(AND(Tabela1[[#This Row],[PEDIDO]]<>"",Tabela1[[#This Row],[NOTA]]=""), "Aguardando nota, há pedido", IF(AND(Tabela1[[#This Row],[PEDIDO]]="",Tabela1[[#This Row],[NOTA]]<>""), "Aguardando pedido, há nota",) ))) -> 0 | AG20: =IF(Tabela1[[#This Row],[ID]]<>"", IF(Tabela1[[#This Row],[Data_pgto_sap]]<>"", "Data de pagamento: "&TEXT(Tabela1[[#This Row],[Data_pgto_sap]],"dd/mm/aaaa"), "Chamado aberto, aguardando programação de pagamento"), IF(AND(Tabela1[[#This Row],[PEDIDO]]<>"",Tabela1[[#This Row],[NOTA]]<>""), "Aguardando autorização pgto", IF(AND(Tabela1[[#This Row],[PEDIDO]]<>"",Tabela1[[#This Row],[NOTA]]=""), "Aguardando nota", IF(AND(Tabela1[[#This Row],[PEDIDO]]="",Tabela1[[#This Row],[NOTA]]<>""), "Aguardando pedido", "Aguardando ambos")))) -> Aguardando ambos | AK20: =IF(Tabela1[[#This Row],[procx ticket]]="",Tabela1[[#This Row],[Data criação ticket]],Tabela1[[#This Row],[procx ticket]]) -> 0 | AM20: =IF( OR( Tabela1[[#This Row],[Data criação ticket]]="", Tabela1[[#This Row],[Data criação ticket]]=0, ISERROR(DATEVALUE(Tabela1[[#This Row],[Data criação ticket]])) ), "", RIGHT(Tabela1[[#This Row],[Data criação ticket]],2) & "/" & MID(Tabela1[[#This Row],[Data criação ticket]],6,2) & "/" & LEFT(Tabela1[[#This Row],[Data criação ticket]],4) ) | AN20: =IFERROR( IF( Tabela1[[#This Row],[Data_pgto_sap]] <> "", "pagamento efetivado", IF( AND( Tabela1[[#This Row],[Status Result1]] = "Chamado aberto, aguardando programação de pagamento", TODAY() - Tabela1[[#This Row],[Data criação ticket br]] >= 5 ), "fora do prazo (" & (TODAY() - Tabela1[[#This Row],[Data criação ticket br]]) & " dias)", "no prazo" ) ), "") | AP20: fazer em 26 | AQ20: =Tabela1[[#This Row],[FILIAL]]&Tabela1[[#This Row],[ORDEM]]&Tabela1[[#This Row],[VALOR RC]]&Tabela1[[#This Row],[COORDENADOR]]&Tabela1[[#This Row],[PROJETO]]&Tabela1[[#This Row],[SERVIÇO]]&Tabela1[[#This Row],[FORNECEDOR]] -> 71266060324980,64HENRIQUEVIRADA DE BANDEIRAREFORMAPLANAC | AR20: #N/A
A21: =IF(B21<7000,1000,2000) -> 2000 | B21: 7174 | C21: =_xlfn.XLOOKUP(Tabela1[[#This Row],[FILIAL]],'CNPJ BASE jan25'!A:A,'CNPJ BASE jan25'!B:B) -> SLU58-JoMiJo21-MA-EF | D21: =_xlfn.XLOOKUP(Tabela1[[#This Row],[FILIAL]],'CNPJ BASE jan25'!A:A,'CNPJ BASE jan25'!C:C) -> 04.899.316/0174-36 | E21: HENRIQUE | F21: VIRADA DE BANDEIRA | G21: REFORMA | I21: PLANAC | J21: 8 | M21: 606037 | P21: 6822.8 | R21: =IF(Tabela1[[#This Row],[VALOR A PAGAR]]>1,Tabela1[[#This Row],[VALOR A PAGAR]],Tabela1[[#This Row],[VALOR RC]]) -> 6822.8 | S21: =IF( Tabela1[[#This Row],[PEDIDO]] <> "", "Pedido Criado", IF( AND(Tabela1[[#This Row],[REQUISIÇÃO]] = "", Tabela1[[#This Row],[PEDIDO]] = ""), "Orçamento Recebido", IF( AND(Tabela1[[#This Row],[REQUISIÇÃO]] <> "", Tabela1[[#This Row],[PEDIDO]] = "", Tabela1[[#This Row],[RC ENVIADA?]] = ""), "Requisição Feita", IF( AND(Tabela1[[#This Row],[RC ENVIADA?]] = "SIM", Tabela1[[#This Row],[REQUISIÇÃO]] <> "", Tabela1[[#This Row],[PEDIDO]] = ""), "Aguardando Pedido", "" ) ) ) ) -> Orçamento Recebido | U21: =F21 & " " & " " & B21 & " - " & I21 & " - " & "N°" & H21 & " - " & Tabela1[[#This Row],[Coluna1]] -> VIRADA DE BANDEIRA 7174 - PLANAC - N° - fazer em 26 | X21: =IF(V21<>"","ABERTO","PENDENTE") -> PENDENTE | AA21: =IF(Tabela1[[#This Row],[CHAMADO]]="ABERTO",Tabela1[[#This Row],[procx status]],"") | AE21: =IF(Tabela1[[#This Row],[Status Result1]]="Aguardando autorização pgto", "sim","") | AF21: =IF(Tabela1[[#This Row],[ID]]<>"", IF(Tabela1[[#This Row],[Data_pgto_sap]]<>"", "Data de pagamento: "&TEXT(Tabela1[[#This Row],[Data_pgto_sap]],"dd/mm/aaaa"), "Chamado aberto, aguardando programação de pagamento"), IF(AND(Tabela1[[#This Row],[PEDIDO]]<>"",Tabela1[[#This Row],[NOTA]]<>""), "Há pedido e há nota, aguardando autorização pgto", IF(AND(Tabela1[[#This Row],[PEDIDO]]<>"",Tabela1[[#This Row],[NOTA]]=""), "Aguardando nota, há pedido", IF(AND(Tabela1[[#This Row],[PEDIDO]]="",Tabela1[[#This Row],[NOTA]]<>""), "Aguardando pedido, há nota",) ))) -> 0 | AG21: =IF(Tabela1[[#This Row],[ID]]<>"", IF(Tabela1[[#This Row],[Data_pgto_sap]]<>"", "Data de pagamento: "&TEXT(Tabela1[[#This Row],[Data_pgto_sap]],"dd/mm/aaaa"), "Chamado aberto, aguardando programação de pagamento"), IF(AND(Tabela1[[#This Row],[PEDIDO]]<>"",Tabela1[[#This Row],[NOTA]]<>""), "Aguardando autorização pgto", IF(AND(Tabela1[[#This Row],[PEDIDO]]<>"",Tabela1[[#This Row],[NOTA]]=""), "Aguardando nota", IF(AND(Tabela1[[#This Row],[PEDIDO]]="",Tabela1[[#This Row],[NOTA]]<>""), "Aguardando pedido", "Aguardando ambos")))) -> Aguardando ambos | AK21: =IF(Tabela1[[#This Row],[procx ticket]]="",Tabela1[[#This Row],[Data criação ticket]],Tabela1[[#This Row],[procx ticket]]) -> 0 | AM21: =IF( OR( Tabela1[[#This Row],[Data criação ticket]]="", Tabela1[[#This Row],[Data criação ticket]]=0, ISERROR(DATEVALUE(Tabela1[[#This Row],[Data criação ticket]])) ), "", RIGHT(Tabela1[[#This Row],[Data criação ticket]],2) & "/" & MID(Tabela1[[#This Row],[Data criação ticket]],6,2) & "/" & LEFT(Tabela1[[#This Row],[Data criação ticket]],4) ) | AN21: =IFERROR( IF( Tabela1[[#This Row],[Data_pgto_sap]] <> "", "pagamento efetivado", IF( AND( Tabela1[[#This Row],[Status Result1]] = "Chamado aberto, aguardando programação de pagamento", TODAY() - Tabela1[[#This Row],[Data criação ticket br]] >= 5 ), "fora do prazo (" & (TODAY() - Tabela1[[#This Row],[Data criação ticket br]]) & " dias)", "no prazo" ) ), "") | AP21: fazer em 26 | AQ21: =Tabela1[[#This Row],[FILIAL]]&Tabela1[[#This Row],[ORDEM]]&Tabela1[[#This Row],[VALOR RC]]&Tabela1[[#This Row],[COORDENADOR]]&Tabela1[[#This Row],[PROJETO]]&Tabela1[[#This Row],[SERVIÇO]]&Tabela1[[#This Row],[FORNECEDOR]] -> 71746060376822,8HENRIQUEVIRADA DE BANDEIRAREFORMAPLANAC | AR21: #N/A
A22: =IF(B22<7000,1000,2000) -> 2000 | B22: 7360 | C22: =_xlfn.XLOOKUP(Tabela1[[#This Row],[FILIAL]],'CNPJ BASE jan25'!A:A,'CNPJ BASE jan25'!B:B) -> FOR141-BezDMen-CE-EF | D22: =_xlfn.XLOOKUP(Tabela1[[#This Row],[FILIAL]],'CNPJ BASE jan25'!A:A,'CNPJ BASE jan25'!C:C) -> 04.899.316/0360-66 | E22: ADRIANO | F22: VIRADA DE BANDEIRA | G22: Persianas | H22: 256 | I22: PERSUN | J22: 8 | M22: 605990 | P22: 1880 | R22: =IF(Tabela1[[#This Row],[VALOR A PAGAR]]>1,Tabela1[[#This Row],[VALOR A PAGAR]],Tabela1[[#This Row],[VALOR RC]]) -> 1880 | S22: =IF( Tabela1[[#This Row],[PEDIDO]] <> "", "Pedido Criado", IF( AND(Tabela1[[#This Row],[REQUISIÇÃO]] = "", Tabela1[[#This Row],[PEDIDO]] = ""), "Orçamento Recebido", IF( AND(Tabela1[[#This Row],[REQUISIÇÃO]] <> "", Tabela1[[#This Row],[PEDIDO]] = "", Tabela1[[#This Row],[RC ENVIADA?]] = ""), "Requisição Feita", IF( AND(Tabela1[[#This Row],[RC ENVIADA?]] = "SIM", Tabela1[[#This Row],[REQUISIÇÃO]] <> "", Tabela1[[#This Row],[PEDIDO]] = ""), "Aguardando Pedido", "" ) ) ) ) -> Orçamento Recebido | U22: =F22 & " " & " " & B22 & " - " & I22 & " - " & "N°" & H22 & " - " & Tabela1[[#This Row],[Coluna1]] -> VIRADA DE BANDEIRA 7360 - PERSUN - N°256 - suplementar 200 | X22: =IF(V22<>"","ABERTO","PENDENTE") -> PENDENTE | AA22: =IF(Tabela1[[#This Row],[CHAMADO]]="ABERTO",Tabela1[[#This Row],[procx status]],"") | AE22: Feito pela automação | AF22: =IF(Tabela1[[#This Row],[ID]]<>"", IF(Tabela1[[#This Row],[Data_pgto_sap]]<>"", "Data de pagamento: "&TEXT(Tabela1[[#This Row],[Data_pgto_sap]],"dd/mm/aaaa"), "Chamado aberto, aguardando programação de pagamento"), IF(AND(Tabela1[[#This Row],[PEDIDO]]<>"",Tabela1[[#This Row],[NOTA]]<>""), "Há pedido e há nota, aguardando autorização pgto", IF(AND(Tabela1[[#This Row],[PEDIDO]]<>"",Tabela1[[#This Row],[NOTA]]=""), "Aguardando nota, há pedido", IF(AND(Tabela1[[#This Row],[PEDIDO]]="",Tabela1[[#This Row],[NOTA]]<>""), "Aguardando pedido, há nota",) ))) -> Aguardando pedido, há nota | AG22: =IF(Tabela1[[#This Row],[ID]]<>"", IF(Tabela1[[#This Row],[Data_pgto_sap]]<>"", "Data de pagamento: "&TEXT(Tabela1[[#This Row],[Data_pgto_sap]],"dd/mm/aaaa"), "Chamado aberto, aguardando programação de pagamento"), IF(AND(Tabela1[[#This Row],[PEDIDO]]<>"",Tabela1[[#This Row],[NOTA]]<>""), "Aguardando autorização pgto", IF(AND(Tabela1[[#This Row],[PEDIDO]]<>"",Tabela1[[#This Row],[NOTA]]=""), "Aguardando nota", IF(AND(Tabela1[[#This Row],[PEDIDO]]="",Tabela1[[#This Row],[NOTA]]<>""), "Aguardando pedido", "Aguardando ambos")))) -> Aguardando pedido | AK22: =IF(Tabela1[[#This Row],[procx ticket]]="",Tabela1[[#This Row],[Data criação ticket]],Tabela1[[#This Row],[procx ticket]]) -> 0 | AN22: =IFERROR( IF( Tabela1[[#This Row],[Data_pgto_sap]] <> "", "pagamento efetivado", IF( AND( Tabela1[[#This Row],[Status Result1]] = "Chamado aberto, aguardando programação de pagamento", TODAY() - Tabela1[[#This Row],[Data criação ticket br]] >= 5 ), "fora do prazo (" & (TODAY() - Tabela1[[#This Row],[Data criação ticket br]]) & " dias)", "no prazo" ) ), "") -> no prazo | AP22: suplementar 200 | AQ22: =Tabela1[[#This Row],[FILIAL]]&Tabela1[[#This Row],[ORDEM]]&Tabela1[[#This Row],[VALOR RC]]&Tabela1[[#This Row],[COORDENADOR]]&Tabela1[[#This Row],[PROJETO]]&Tabela1[[#This Row],[SERVIÇO]]&Tabela1[[#This Row],[FORNECEDOR]] -> 73606059901880ADRIANOVIRADA DE BANDEIRAPersianasPERSUN | AR22: #N/A
